{
  "type": "Feature",
  "properties": {
    "gn:admin1_code":"075",
    "gn:admin2_code":"7269038",
    "gn:asciiname":"Cristina",
    "gn:country_code":"PR",
    "gn:dem":69,
    "gn:elevation":"69.0",
    "gn:feature_class":"P",
    "gn:feature_code":"PPL",
    "gn:name":"Cristina",
    "gn:population":0,
    "gn:timezone":"America/Puerto_Rico",
    "iso:country":"PR",
    "wof:name":"Cristina",
    "wof:placetype":"locality"
},
  "geometry": {"coordinates":[-66.49989000000001,18.04857],"type":"Point"}
}