{
  "type": "Feature",
  "properties": {
    "gn:admin1_code":"037",
    "gn:admin2_code":"7268583",
    "gn:asciiname":"Brisas de Ceiba I",
    "gn:country_code":"PR",
    "gn:dem":9,
    "gn:elevation":"7.0",
    "gn:feature_class":"P",
    "gn:feature_code":"PPL",
    "gn:name":"Brisas de Ceiba I",
    "gn:population":0,
    "gn:timezone":"America/Puerto_Rico",
    "iso:country":"PR",
    "wof:name":"Brisas de Ceiba I",
    "wof:placetype":"locality"
},
  "geometry": {"coordinates":[-65.63766,18.26746],"type":"Point"}
}