{
  "type": "Feature",
  "properties": {
    "gn:admin1_code":"139",
    "gn:admin2_code":"7268347",
    "gn:asciiname":"La Lomita",
    "gn:country_code":"PR",
    "gn:dem":29,
    "gn:elevation":"33.0",
    "gn:feature_class":"P",
    "gn:feature_code":"PPL",
    "gn:name":"La Lomita",
    "gn:population":0,
    "gn:timezone":"America/Puerto_Rico",
    "iso:country":"PR",
    "wof:name":"La Lomita",
    "wof:placetype":"locality"
},
  "geometry": {"coordinates":[-66.00878,18.35023],"type":"Point"}
}