{
  "type": "Feature",
  "properties": {
    "gn:admin1_code":"051",
    "gn:admin2_code":"7268474",
    "gn:asciiname":"Minima San Antonio",
    "gn:country_code":"PR",
    "gn:dem":8,
    "gn:elevation":"8.0",
    "gn:feature_class":"P",
    "gn:feature_code":"PPL",
    "gn:name":"Minima San Antonio",
    "gn:population":0,
    "gn:timezone":"America/Puerto_Rico",
    "iso:country":"PR",
    "wof:name":"Minima San Antonio",
    "wof:placetype":"locality"
},
  "geometry": {"coordinates":[-66.26683,18.45939],"type":"Point"}
}