{
  "type": "Feature",
  "properties": {
    "gn:admin1_code":"021",
    "gn:admin2_code":"7268466",
    "gn:asciiname":"Flamingo Hills",
    "gn:country_code":"PR",
    "gn:dem":40,
    "gn:elevation":"39.0",
    "gn:feature_class":"P",
    "gn:feature_code":"PPL",
    "gn:name":"Flamingo Hills",
    "gn:population":0,
    "gn:timezone":"America/Puerto_Rico",
    "iso:country":"PR",
    "wof:name":"Flamingo Hills",
    "wof:placetype":"locality"
},
  "geometry": {"coordinates":[-66.18489,18.39106],"type":"Point"}
}