{
  "type": "Feature",
  "properties": {
    "gn:country":"PR",
    "gn:elevation":3,
    "gn:fcode":"PPL",
    "gn:population":0,
    "iso:country":"PR",
    "name:ceb_x_preferred":[
        "Condado Subbarrio"
    ],
    "name:eng_x_preferred":[
        "Condado"
    ],
    "name:spa_x_preferred":[
        "Condado"
    ],
    "qs:gn_adm0_cc":"PR",
    "qs:gn_fcode":"PPL",
    "qs:gn_local":4568220,
    "qs:gn_nam_loc":"aguacate",
    "qs:gn_name":"Condado",
    "qs:local_max":29505,
    "qs:local_sum":50313,
    "qs:localhoods":63,
    "qs:name":"Condado",
    "qs:name_adm0":"Puerto Rico",
    "qs:name_adm1":"San Juan",
    "qs:name_adm2":"Santurce",
    "qs:name_local":"San Juan",
    "qs:photo_max":704,
    "qs:photo_sum":4448,
    "qs:placetype":"Suburb",
    "qs:quad_count":37,
    "qs:woe_adm0":23424935,
    "qs:woe_adm1":2346815,
    "qs:woe_adm2":26806706,
    "qs:woe_lau":0,
    "qs:woe_local":161685,
    "qs:woe_ver":"7.10.0",
    "qs_pg:aaroncc":"PR",
    "qs_pg:gn_country":"PR",
    "qs_pg:gn_fcode":"PPL",
    "qs_pg:gn_pop":0,
    "qs_pg:name":"Condado",
    "qs_pg:name_adm0":"Puerto Rico",
    "qs_pg:name_adm1":"San Juan",
    "qs_pg:photos":3429,
    "qs_pg:photos_1k":695,
    "qs_pg:photos_9k":15,
    "qs_pg:photos_9r":11,
    "qs_pg:photos_all":3429,
    "qs_pg:photos_sr":20,
    "qs_pg:pop_sr":0,
    "qs_pg:qs_pg_placetype":"neighbourhood",
    "qs_pg:qs_pg_placetype_gp":"Suburb",
    "qs_pg:woe_adm0":23424935,
    "wof:lang":[
        "spa"
    ],
    "wof:name":"Condado",
    "wof:placetype":"neighbourhood"
},
  "geometry": {"coordinates":[-66.069856,18.453499],"type":"Point"}
}