{
  "type": "Feature",
  "properties": {
    "gn:admin1_code":"113",
    "gn:admin2_code":"7268586",
    "gn:asciiname":"Villa Esperanza",
    "gn:country_code":"PR",
    "gn:dem":23,
    "gn:elevation":"20.0",
    "gn:feature_class":"P",
    "gn:feature_code":"PPL",
    "gn:name":"Villa Esperanza",
    "gn:population":0,
    "gn:timezone":"America/Puerto_Rico",
    "iso:country":"PR",
    "wof:name":"Villa Esperanza",
    "wof:placetype":"locality"
},
  "geometry": {"coordinates":[-66.60155999999999,18.01969],"type":"Point"}
}