{
  "type": "Feature",
  "properties": {
    "gn:admin1_code":"069",
    "gn:admin2_code":"7268579",
    "gn:asciiname":"Extension Roig",
    "gn:country_code":"PR",
    "gn:dem":27,
    "gn:elevation":"22.0",
    "gn:feature_class":"P",
    "gn:feature_code":"PPL",
    "gn:name":"Extension Roig",
    "gn:population":0,
    "gn:timezone":"America/Puerto_Rico",
    "iso:country":"PR",
    "wof:name":"Extension Roig",
    "wof:placetype":"locality"
},
  "geometry": {"coordinates":[-65.82850000000001,18.15524],"type":"Point"}
}