{
  "type": "Feature",
  "properties": {
    "gn:admin1_code":"113",
    "gn:admin2_code":"7268200",
    "gn:asciiname":"Hacienda Yani",
    "gn:country_code":"PR",
    "gn:dem":289,
    "gn:elevation":"287.0",
    "gn:feature_class":"P",
    "gn:feature_code":"PPL",
    "gn:name":"Hacienda Yani",
    "gn:population":0,
    "gn:timezone":"America/Puerto_Rico",
    "iso:country":"PR",
    "wof:name":"Hacienda Yani",
    "wof:placetype":"locality"
},
  "geometry": {"coordinates":[-66.57628000000001,18.12163],"type":"Point"}
}