{
  "type": "Feature",
  "properties": {
    "gn:admin1_code":"125",
    "gn:asciiname":"Alturas de Lajas Number 2",
    "gn:country_code":"PR",
    "gn:dem":57,
    "gn:elevation":"52.0",
    "gn:feature_class":"P",
    "gn:feature_code":"PPL",
    "gn:name":"Alturas de Lajas Number 2",
    "gn:population":0,
    "gn:timezone":"America/Puerto_Rico",
    "iso:country":"PR",
    "wof:name":"Alturas de Lajas Number 2",
    "wof:placetype":"locality"
},
  "geometry": {"coordinates":[-67.05601,18.04524],"type":"Point"}
}