{
  "type": "Feature",
  "properties": {
    "gn:admin1_code":"019",
    "gn:admin2_code":"7268726",
    "gn:asciiname":"Carro",
    "gn:country_code":"PR",
    "gn:dem":698,
    "gn:elevation":"691.0",
    "gn:feature_class":"P",
    "gn:feature_code":"PPL",
    "gn:name":"Carro",
    "gn:population":0,
    "gn:timezone":"America/Puerto_Rico",
    "iso:country":"PR",
    "wof:name":"Carro",
    "wof:placetype":"locality"
},
  "geometry": {"coordinates":[-66.33795000000001,18.18968],"type":"Point"}
}