{
  "type": "Feature",
  "properties": {
    "gn:admin1_code":"019",
    "gn:admin2_code":"7268726",
    "gn:asciiname":"Carro",
    "gn:country_code":"PR",
    "gn:dem":698,
    "gn:elevation":"691.0",
    "gn:feature_class":"P",
    "gn:feature_code":"PPL",
    "gn:name":"Carro",
    "gn:population":0,
    "gn:timezone":"America/Puerto_Rico",
    "iso:country":"PR",
    "name:azb_x_preferred":[
        "\u06a9\u0627\u0631\u0648"
    ],
    "name:bel_x_preferred":[
        "\u041a\u0430\u0440\u0430"
    ],
    "name:bul_x_preferred":[
        "\u041a\u0430\u0440\u043e"
    ],
    "name:cat_x_preferred":[
        "Carro"
    ],
    "name:ceb_x_preferred":[
        "Carro"
    ],
    "name:deu_x_preferred":[
        "Carro"
    ],
    "name:epo_x_preferred":[
        "Carro"
    ],
    "name:eus_x_preferred":[
        "Carro"
    ],
    "name:fas_x_preferred":[
        "\u06a9\u0627\u0631\u0648"
    ],
    "name:fra_x_preferred":[
        "Carro"
    ],
    "name:hun_x_preferred":[
        "Carro"
    ],
    "name:hye_x_preferred":[
        "\u053f\u0561\u0580\u0578"
    ],
    "name:ina_x_preferred":[
        "Carro"
    ],
    "name:ita_x_preferred":[
        "Carro"
    ],
    "name:jpn_x_preferred":[
        "\u30ab\u30c3\u30ed"
    ],
    "name:kaz_x_preferred":[
        "\u041a\u0430\u0440\u0440\u043e"
    ],
    "name:lat_x_preferred":[
        "Carrum"
    ],
    "name:lij_x_preferred":[
        "O C\u00e4ro"
    ],
    "name:lmo_x_preferred":[
        "Carro"
    ],
    "name:msa_x_preferred":[
        "Carro"
    ],
    "name:nap_x_preferred":[
        "Carro"
    ],
    "name:nld_x_preferred":[
        "Carro"
    ],
    "name:pms_x_preferred":[
        "Carro"
    ],
    "name:pol_x_preferred":[
        "Carro"
    ],
    "name:por_x_preferred":[
        "Carro"
    ],
    "name:ron_x_preferred":[
        "Carro"
    ],
    "name:rus_x_preferred":[
        "\u041a\u0430\u0440\u0440\u043e"
    ],
    "name:scn_x_preferred":[
        "Carro"
    ],
    "name:spa_x_preferred":[
        "Carro"
    ],
    "name:srp_x_preferred":[
        "\u041a\u0430\u0440\u043e"
    ],
    "name:swe_x_preferred":[
        "Carro"
    ],
    "name:ukr_x_preferred":[
        "\u041a\u0430\u0440\u0440\u043e"
    ],
    "name:uzb_x_preferred":[
        "Carro"
    ],
    "name:vie_x_preferred":[
        "Carro"
    ],
    "name:vol_x_preferred":[
        "Carro"
    ],
    "name:war_x_preferred":[
        "Carro"
    ],
    "wof:name":"Carro",
    "wof:placetype":"locality"
},
  "geometry": {"coordinates":[-66.33795000000001,18.18968],"type":"Point"}
}