{
  "type": "Feature",
  "properties": {
    "gn:admin1_code":"113",
    "gn:admin2_code":"7268962",
    "gn:asciiname":"Los Almendros",
    "gn:country_code":"PR",
    "gn:dem":22,
    "gn:elevation":"16.0",
    "gn:feature_class":"P",
    "gn:feature_code":"PPL",
    "gn:name":"Los Almendros",
    "gn:population":0,
    "gn:timezone":"America/Puerto_Rico",
    "iso:country":"PR",
    "wof:name":"Los Almendros",
    "wof:placetype":"locality"
},
  "geometry": {"coordinates":[-66.59600999999999,18.01274],"type":"Point"}
}