{
  "type": "Feature",
  "properties": {
    "gn:admin1_code":"097",
    "gn:admin2_code":"7268645",
    "gn:asciiname":"Cuebas",
    "gn:country_code":"PR",
    "gn:dem":15,
    "gn:elevation":"16.0",
    "gn:feature_class":"P",
    "gn:feature_code":"PPL",
    "gn:name":"Cuebas",
    "gn:population":0,
    "gn:timezone":"America/Puerto_Rico",
    "iso:country":"PR",
    "name:spa_x_preferred":[
        "Cuebas"
    ],
    "wof:name":"Cuebas",
    "wof:placetype":"locality"
},
  "geometry": {"coordinates":[-67.13296,18.20051],"type":"Point"}
}