{
  "type": "Feature",
  "properties": {
    "gn:admin1_code":"153",
    "gn:admin2_code":"7269017",
    "gn:asciiname":"Campamento Susua",
    "gn:country_code":"PR",
    "gn:dem":150,
    "gn:elevation":"148.0",
    "gn:feature_class":"P",
    "gn:feature_code":"PPL",
    "gn:name":"Campamento Sus\u00faa",
    "gn:population":0,
    "gn:timezone":"America/Puerto_Rico",
    "iso:country":"PR",
    "wof:name":"Campamento Susua",
    "wof:placetype":"locality"
},
  "geometry": {"coordinates":[-66.90684,18.07024],"type":"Point"}
}