{
  "type": "Feature",
  "properties": {
    "gn:admin1_code":"075",
    "gn:admin2_code":"7268943",
    "gn:asciiname":"Sabana Llana Arriba",
    "gn:country_code":"PR",
    "gn:dem":33,
    "gn:elevation":"26.0",
    "gn:feature_class":"P",
    "gn:feature_code":"PPL",
    "gn:name":"Sabana Llana Arriba",
    "gn:population":0,
    "gn:timezone":"America/Puerto_Rico",
    "iso:country":"PR",
    "wof:name":"Sabana Llana Arriba",
    "wof:placetype":"locality"
},
  "geometry": {"coordinates":[-66.51295,18.03135],"type":"Point"}
}