{
  "type": "Feature",
  "properties": {
    "gn:admin1_code":"081",
    "gn:admin2_code":"7268548",
    "gn:asciiname":"Sector Arizon",
    "gn:country_code":"PR",
    "gn:dem":365,
    "gn:elevation":"363.0",
    "gn:feature_class":"P",
    "gn:feature_code":"PPL",
    "gn:name":"Sector Arizon",
    "gn:population":0,
    "gn:timezone":"America/Puerto_Rico",
    "iso:country":"PR",
    "wof:name":"Sector Arizon",
    "wof:placetype":"locality"
},
  "geometry": {"coordinates":[-66.8874,18.2919],"type":"Point"}
}