{
  "type": "Feature",
  "properties": {
    "gn:admin1_code":"013",
    "gn:admin2_code":"7268214",
    "gn:asciiname":"Las Cantaras",
    "gn:country_code":"PR",
    "gn:dem":244,
    "gn:elevation":"243.0",
    "gn:feature_class":"P",
    "gn:feature_code":"PPL",
    "gn:name":"Las C\u00e1ntaras",
    "gn:population":0,
    "gn:timezone":"America/Puerto_Rico",
    "iso:country":"PR",
    "wof:name":"Las Cantaras",
    "wof:placetype":"locality"
},
  "geometry": {"coordinates":[-66.67129,18.37523],"type":"Point"}
}