{
  "type": "Feature",
  "properties": {
    "gn:admin1_code":"053",
    "gn:admin2_code":"7268385",
    "gn:asciiname":"Melendez",
    "gn:country_code":"PR",
    "gn:dem":28,
    "gn:elevation":"25.0",
    "gn:feature_class":"P",
    "gn:feature_code":"PPL",
    "gn:name":"Melendez",
    "gn:population":0,
    "gn:timezone":"America/Puerto_Rico",
    "iso:country":"PR",
    "wof:name":"Melendez",
    "wof:placetype":"locality"
},
  "geometry": {"coordinates":[-65.65876999999999,18.32662],"type":"Point"}
}