{
  "type": "Feature",
  "properties": {
    "gn:admin1_code":"023",
    "gn:admin2_code":"7268419",
    "gn:asciiname":"Cornelia",
    "gn:country_code":"PR",
    "gn:dem":16,
    "gn:elevation":"14.0",
    "gn:feature_class":"P",
    "gn:feature_code":"PPL",
    "gn:name":"Cornelia",
    "gn:population":0,
    "gn:timezone":"America/Puerto_Rico",
    "iso:country":"PR",
    "name:cat_x_preferred":[
        "Corn\u00e8lia"
    ],
    "name:ceb_x_preferred":[
        "Cornelia"
    ],
    "name:ces_x_preferred":[
        "Cornelia"
    ],
    "name:deu_x_preferred":[
        "Cornelia"
    ],
    "name:est_x_preferred":[
        "Cornelia"
    ],
    "name:fra_x_preferred":[
        "Cornelia"
    ],
    "name:ita_x_preferred":[
        "Cornelia"
    ],
    "name:jpn_x_preferred":[
        "\u30b3\u30fc\u30cd\u30ea\u30a2"
    ],
    "name:nld_x_preferred":[
        "Cornelia"
    ],
    "name:por_x_preferred":[
        "Corn\u00e9lia"
    ],
    "name:ron_x_preferred":[
        "Cornelia"
    ],
    "name:rus_x_preferred":[
        "\u041a\u043e\u0440\u043d\u0435\u043b\u0438\u044f"
    ],
    "name:spa_x_preferred":[
        "Cornelia"
    ],
    "wof:name":"Cornelia",
    "wof:placetype":"locality"
},
  "geometry": {"coordinates":[-67.1699,18.15162],"type":"Point"}
}