{
  "type": "Feature",
  "properties": {
    "gn:country":"PR",
    "gn:elevation":33,
    "gn:fcode":"PPL",
    "gn:population":0,
    "iso:country":"PR",
    "name:cat_x_preferred":[
        "R\u00edo Piedras"
    ],
    "name:cym_x_preferred":[
        "R\u00edo Piedras"
    ],
    "name:dan_x_preferred":[
        "R\u00edo Piedras"
    ],
    "name:deu_x_preferred":[
        "R\u00edo Piedras"
    ],
    "name:eng_x_preferred":[
        "R\u00edo Piedras"
    ],
    "name:fao_x_preferred":[
        "R\u00edo Piedras"
    ],
    "name:fra_x_preferred":[
        "R\u00edo Piedras"
    ],
    "name:heb_x_preferred":[
        "\u05e8\u05d9\u05d5 \u05e4\u05d9\u05d9\u05d3\u05e8\u05d0\u05e1"
    ],
    "name:hye_x_preferred":[
        "\u054c\u056b\u0578 \u054a\u056b\u0565\u0564\u0580\u0561\u057d"
    ],
    "name:isl_x_preferred":[
        "R\u00edo Piedras"
    ],
    "name:ita_x_preferred":[
        "R\u00edo Piedras"
    ],
    "name:jpn_x_preferred":[
        "\u30ea\u30aa\u30fb\u30d4\u30a8\u30c9\u30e9\u30b9"
    ],
    "name:kal_x_preferred":[
        "R\u00edo Piedras"
    ],
    "name:kor_x_preferred":[
        "\ub9ac\uc624\ud53c\uc5d0\ub4dc\ub77c\uc2a4"
    ],
    "name:nld_x_preferred":[
        "R\u00edo Piedras"
    ],
    "name:nno_x_preferred":[
        "R\u00edo Piedras"
    ],
    "name:nob_x_preferred":[
        "R\u00edo Piedras"
    ],
    "name:por_x_preferred":[
        "R\u00edo Piedras"
    ],
    "name:rus_x_preferred":[
        "\u0420\u0438\u043e-\u041f\u0438\u0435\u0434\u0440\u0430\u0441"
    ],
    "name:spa_x_preferred":[
        "Rio Piedras",
        "R\u00edo Piedras"
    ],
    "name:spa_x_variant":[
        "Riopiedras"
    ],
    "name:swe_x_preferred":[
        "R\u00edo Piedras"
    ],
    "qs_pg:aaroncc":"PR",
    "qs_pg:gn_country":"PR",
    "qs_pg:gn_fcode":"PPL",
    "qs_pg:gn_pop":0,
    "qs_pg:name":"Rio Piedras",
    "qs_pg:name_adm0":"Puerto Rico",
    "qs_pg:name_adm1":"San Juan",
    "qs_pg:photos":252,
    "qs_pg:photos_1k":51,
    "qs_pg:photos_9k":1,
    "qs_pg:photos_9r":4,
    "qs_pg:photos_all":252,
    "qs_pg:photos_sr":5,
    "qs_pg:pop_sr":5,
    "qs_pg:qs_pg_placetype":"neighbourhood",
    "qs_pg:qs_pg_placetype_gp":"Suburb",
    "qs_pg:woe_adm0":23424935,
    "woe:adm0_id":23424935,
    "woe:name_adm0":"Puerto Rico",
    "woe:name_adm1":"San Juan",
    "woe:placetype":"Suburb",
    "wof:name":"Rio Piedras",
    "wof:placetype":"neighbourhood"
},
  "geometry": {"coordinates":[-66.04989,18.39745],"type":"Point"}
}