{
  "type": "Feature",
  "properties": {
    "gn:elevation":33,
    "gn:gn_country":"PR",
    "gn:gn_fcode":"PPL",
    "gn:gn_pop":0,
    "iso:country":"PR",
    "name:cat_x_preferred":[
        "R\u00edo Piedras"
    ],
    "name:deu_x_preferred":[
        "R\u00edo Piedras"
    ],
    "name:fra_x_preferred":[
        "R\u00edo Piedras"
    ],
    "name:ita_x_preferred":[
        "R\u00edo Piedras"
    ],
    "name:kor_x_preferred":[
        "\ub9ac\uc624\ud53c\uc5d0\ub4dc\ub77c\uc2a4"
    ],
    "name:por_x_preferred":[
        "R\u00edo Piedras"
    ],
    "name:spa_x_preferred":[
        "Rio Piedras",
        "R\u00edo Piedras"
    ],
    "name:spa_x_variant":[
        "Riopiedras"
    ],
    "name:unk_x_variant":[
        "Rio Piedras"
    ],
    "qs_pg:aaroncc":"PR",
    "qs_pg:gn_country":"PR",
    "qs_pg:gn_fcode":"PPL",
    "qs_pg:gn_pop":0,
    "qs_pg:name":"Rio Piedras",
    "qs_pg:name_adm0":"Puerto Rico",
    "qs_pg:name_adm1":"San Juan",
    "qs_pg:photos":252,
    "qs_pg:photos_1k":51,
    "qs_pg:photos_9k":1,
    "qs_pg:photos_9r":4,
    "qs_pg:photos_all":252,
    "qs_pg:photos_sr":5,
    "qs_pg:pop_sr":5,
    "qs_pg:qs_pg_placetype":"neighbourhood",
    "qs_pg:qs_pg_placetype_gp":"Suburb",
    "qs_pg:woe_adm0":23424935,
    "woe:adm0_id":23424935,
    "woe:name_adm0":"Puerto Rico",
    "woe:name_adm1":"San Juan",
    "woe:placetype":"Suburb",
    "wof:name":"Rio Piedras",
    "wof:placetype":"neighbourhood"
},
  "geometry": {"coordinates":[-66.04989,18.39745],"type":"Point"}
}