{
  "type": "Feature",
  "properties": {
    "gn:admin1_code":"097",
    "gn:admin2_code":"7268421",
    "gn:asciiname":"Paseo la Sultana",
    "gn:country_code":"PR",
    "gn:dem":26,
    "gn:elevation":"18.0",
    "gn:feature_class":"P",
    "gn:feature_code":"PPL",
    "gn:name":"Paseo la Sultana",
    "gn:population":0,
    "gn:timezone":"America/Puerto_Rico",
    "iso:country":"PR",
    "wof:name":"Paseo la Sultana",
    "wof:placetype":"locality"
},
  "geometry": {"coordinates":[-67.13768,18.16662],"type":"Point"}
}