{
  "type": "Feature",
  "properties": {
    "gn:admin1_code":"079",
    "gn:admin2_code":"7268947",
    "gn:asciiname":"Extension El Valle",
    "gn:country_code":"PR",
    "gn:dem":34,
    "gn:elevation":"30.0",
    "gn:feature_class":"P",
    "gn:feature_code":"PPL",
    "gn:name":"Extension El Valle",
    "gn:population":0,
    "gn:timezone":"America/Puerto_Rico",
    "iso:country":"PR",
    "wof:name":"Extension El Valle",
    "wof:placetype":"locality"
},
  "geometry": {"coordinates":[-67.05379000000001,18.0383],"type":"Point"}
}