{
  "type": "Feature",
  "properties": {
    "gn:admin1_code":"001",
    "gn:admin2_code":"7268167",
    "gn:asciiname":"Joaquin M Andino",
    "gn:country_code":"PR",
    "gn:dem":527,
    "gn:elevation":"520.0",
    "gn:feature_class":"P",
    "gn:feature_code":"PPL",
    "gn:name":"Joaquin M Andino",
    "gn:population":0,
    "gn:timezone":"America/Puerto_Rico",
    "iso:country":"PR",
    "wof:name":"Joaquin M Andino",
    "wof:placetype":"locality"
},
  "geometry": {"coordinates":[-66.71850999999999,18.16163],"type":"Point"}
}