{
  "type": "Feature",
  "properties": {
    "gn:admin1_code":"113",
    "gn:admin2_code":"7268770",
    "gn:asciiname":"Barriada El Caribe",
    "gn:country_code":"PR",
    "gn:dem":6,
    "gn:elevation":"8.0",
    "gn:feature_class":"P",
    "gn:feature_code":"PPL",
    "gn:name":"Barriada El Caribe",
    "gn:population":0,
    "gn:timezone":"America/Puerto_Rico",
    "iso:country":"PR",
    "wof:name":"Barriada El Caribe",
    "wof:placetype":"locality"
},
  "geometry": {"coordinates":[-66.62156,17.98302],"type":"Point"}
}