{
  "type": "Feature",
  "properties": {
    "gn:admin1_code":"097",
    "gn:admin2_code":"7268933",
    "gn:asciiname":"San Benito",
    "gn:country_code":"PR",
    "gn:dem":28,
    "gn:elevation":"24.0",
    "gn:feature_class":"P",
    "gn:feature_code":"PPL",
    "gn:name":"San Benito",
    "gn:population":0,
    "gn:timezone":"America/Puerto_Rico",
    "iso:country":"PR",
    "wof:name":"San Benito",
    "wof:placetype":"locality"
},
  "geometry": {"coordinates":[-67.13768,18.18662],"type":"Point"}
}