{
  "type": "Feature",
  "properties": {
    "gn:admin1_code":"001",
    "gn:admin2_code":"7268167",
    "gn:asciiname":"Barriada Vega",
    "gn:country_code":"PR",
    "gn:dem":516,
    "gn:elevation":"523.0",
    "gn:feature_class":"P",
    "gn:feature_code":"PPL",
    "gn:name":"Barriada Vega",
    "gn:population":0,
    "gn:timezone":"America/Puerto_Rico",
    "iso:country":"PR",
    "wof:name":"Barriada Vega",
    "wof:placetype":"locality"
},
  "geometry": {"coordinates":[-66.71795,18.16024],"type":"Point"}
}