{
  "type": "Feature",
  "properties": {
    "gn:admin1_code":"013",
    "gn:admin2_code":"7268376",
    "gn:asciiname":"La Esperanza",
    "gn:country_code":"PR",
    "gn:dem":225,
    "gn:elevation":"225.0",
    "gn:feature_class":"P",
    "gn:feature_code":"PPL",
    "gn:name":"La Esperanza",
    "gn:population":0,
    "gn:timezone":"America/Puerto_Rico",
    "iso:country":"PR",
    "wof:name":"La Esperanza",
    "wof:placetype":"locality"
},
  "geometry": {"coordinates":[-66.74684000000001,18.38189],"type":"Point"}
}