{
  "type": "Feature",
  "properties": {
    "gn:admin1_code":"007",
    "gn:asciiname":"Bosque de Rio",
    "gn:country_code":"PR",
    "gn:dem":52,
    "gn:elevation":"44.0",
    "gn:feature_class":"P",
    "gn:feature_code":"PPL",
    "gn:name":"Bosque de Rio",
    "gn:population":0,
    "gn:timezone":"America/Puerto_Rico",
    "iso:country":"PR",
    "wof:name":"Bosque de Rio",
    "wof:placetype":"locality"
},
  "geometry": {"coordinates":[-66.00461,18.36106],"type":"Point"}
}