{
  "type": "Feature",
  "properties": {
    "gn:admin1_code":"101",
    "gn:admin2_code":"7268682",
    "gn:asciiname":"Villas del Norte",
    "gn:country_code":"PR",
    "gn:dem":196,
    "gn:elevation":"188.0",
    "gn:feature_class":"P",
    "gn:feature_code":"PPL",
    "gn:name":"Villas del Norte",
    "gn:population":0,
    "gn:timezone":"America/Puerto_Rico",
    "iso:country":"PR",
    "wof:name":"Villas del Norte",
    "wof:placetype":"locality"
},
  "geometry": {"coordinates":[-66.40434,18.33801],"type":"Point"}
}