{
  "type": "Feature",
  "properties": {
    "gn:admin1_code":"129",
    "gn:admin2_code":"7268457",
    "gn:asciiname":"Las Mercedes",
    "gn:country_code":"PR",
    "gn:dem":89,
    "gn:elevation":"86.0",
    "gn:feature_class":"P",
    "gn:feature_code":"PPL",
    "gn:name":"Las Mercedes",
    "gn:population":0,
    "gn:timezone":"America/Puerto_Rico",
    "iso:country":"PR",
    "wof:name":"Las Mercedes",
    "wof:placetype":"locality"
},
  "geometry": {"coordinates":[-65.96460999999999,18.18996],"type":"Point"}
}