{
  "type": "Feature",
  "properties": {
    "gn:admin1_code":"057",
    "gn:admin2_code":"7268439",
    "gn:asciiname":"Amalia Marin",
    "gn:country_code":"PR",
    "gn:dem":53,
    "gn:elevation":"54.0",
    "gn:feature_class":"P",
    "gn:feature_code":"PPL",
    "gn:name":"Amalia Marin",
    "gn:population":0,
    "gn:timezone":"America/Puerto_Rico",
    "iso:country":"PR",
    "wof:name":"Amalia Marin",
    "wof:placetype":"locality"
},
  "geometry": {"coordinates":[-66.10878000000001,17.97663],"type":"Point"}
}