{
  "type": "Feature",
  "properties": {
    "gn:admin1_code":"047",
    "gn:admin2_code":"7268730",
    "gn:asciiname":"Medina",
    "gn:country_code":"PR",
    "gn:dem":390,
    "gn:elevation":"400.0",
    "gn:feature_class":"P",
    "gn:feature_code":"PPL",
    "gn:name":"Medina",
    "gn:population":0,
    "gn:timezone":"America/Puerto_Rico",
    "iso:country":"PR",
    "wof:name":"Medina",
    "wof:placetype":"locality"
},
  "geometry": {"coordinates":[-66.2985,18.29829],"type":"Point"}
}