{
  "type": "Feature",
  "properties": {
    "gn:admin1_code":"021",
    "gn:admin2_code":"7268466",
    "gn:asciiname":"Comunidad Rio Plantation",
    "gn:country_code":"PR",
    "gn:dem":33,
    "gn:elevation":"30.0",
    "gn:feature_class":"P",
    "gn:feature_code":"PPL",
    "gn:name":"Comunidad Rio Plantation",
    "gn:population":0,
    "gn:timezone":"America/Puerto_Rico",
    "iso:country":"PR",
    "wof:name":"Comunidad Rio Plantation",
    "wof:placetype":"locality"
},
  "geometry": {"coordinates":[-66.17572,18.41689],"type":"Point"}
}