{
  "type": "Feature",
  "properties": {
    "gn:admin1_code":"041",
    "gn:admin2_code":"7268080",
    "gn:asciiname":"Fernandez",
    "gn:country_code":"PR",
    "gn:dem":429,
    "gn:elevation":"429.0",
    "gn:feature_class":"P",
    "gn:feature_code":"PPL",
    "gn:name":"Fernandez",
    "gn:population":0,
    "gn:timezone":"America/Puerto_Rico",
    "iso:country":"PR",
    "wof:name":"Fernandez",
    "wof:placetype":"locality"
},
  "geometry": {"coordinates":[-66.16016999999999,18.17718],"type":"Point"}
}