{
  "type": "Feature",
  "properties": {
    "gn:admin1_code":"141",
    "gn:admin2_code":"7268606",
    "gn:asciiname":"Hacienda La Isolina",
    "gn:country_code":"PR",
    "gn:dem":341,
    "gn:elevation":"320.0",
    "gn:feature_class":"P",
    "gn:feature_code":"PPL",
    "gn:name":"Hacienda La Isolina",
    "gn:population":0,
    "gn:timezone":"America/Puerto_Rico",
    "iso:country":"PR",
    "wof:name":"Hacienda La Isolina",
    "wof:placetype":"locality"
},
  "geometry": {"coordinates":[-66.59045,18.2944],"type":"Point"}
}