{
  "type": "Feature",
  "properties": {
    "gn:admin1_code":"133",
    "gn:admin2_code":"7268148",
    "gn:asciiname":"Las Ollas Comunidad",
    "gn:country_code":"PR",
    "gn:dem":43,
    "gn:elevation":"43.0",
    "gn:feature_class":"P",
    "gn:feature_code":"PPL",
    "gn:name":"Las Ollas Comunidad",
    "gn:population":0,
    "gn:timezone":"America/Puerto_Rico",
    "iso:country":"PR",
    "wof:name":"Las Ollas Comunidad",
    "wof:placetype":"locality"
},
  "geometry": {"coordinates":[-66.42059999999999,18.01417],"type":"Point"}
}