{
  "type": "Feature",
  "properties": {
    "gn:admin1_code":"021",
    "gn:admin2_code":"7268466",
    "gn:asciiname":"Hato Tejas",
    "gn:country_code":"PR",
    "gn:dem":71,
    "gn:elevation":"69.0",
    "gn:feature_class":"P",
    "gn:feature_code":"PPL",
    "gn:name":"Hato Tejas",
    "gn:population":0,
    "gn:timezone":"America/Puerto_Rico",
    "iso:country":"PR",
    "wof:name":"Hato Tejas",
    "wof:placetype":"locality"
},
  "geometry": {"coordinates":[-66.18933,18.4055],"type":"Point"}
}