{
  "type": "Feature",
  "properties": {
    "gn:gn_country":"PR",
    "gn:gn_fcode":"PPL",
    "gn:gn_pop":2297,
    "gn:population":2297,
    "iso:country":"PR",
    "qs_pg:aaroncc":"PR",
    "qs_pg:gn_country":"PR",
    "qs_pg:gn_fcode":"PPL",
    "qs_pg:gn_pop":2297,
    "qs_pg:name":"Vazquez",
    "qs_pg:name_adm0":"Puerto Rico",
    "qs_pg:name_adm1":"Salinas",
    "qs_pg:photos":10,
    "qs_pg:photos_1k":2,
    "qs_pg:photos_9k":1,
    "qs_pg:photos_9r":1,
    "qs_pg:photos_all":10,
    "qs_pg:photos_sr":1,
    "qs_pg:pop_sr":4,
    "qs_pg:qs_pg_placetype":"locality",
    "qs_pg:qs_pg_placetype_gp":"Town",
    "qs_pg:woe_adm0":23424935,
    "woe:adm0_id":23424935,
    "woe:name_adm0":"Puerto Rico",
    "woe:name_adm1":"Salinas",
    "woe:placetype":"Town",
    "wof:name":"Vazquez",
    "wof:placetype":"locality",
    "wof:population":2297
},
  "geometry": {"coordinates":[-66.2385,18.0658],"type":"Point"}
}