{
  "type": "Feature",
  "properties": {
    "gn:admin1_code":"137",
    "gn:admin2_code":"7268318",
    "gn:asciiname":"Candelaria Comunidad",
    "gn:country_code":"PR",
    "gn:dem":71,
    "gn:elevation":"69.0",
    "gn:feature_class":"P",
    "gn:feature_code":"PPL",
    "gn:name":"Candelaria Comunidad",
    "gn:population":0,
    "gn:timezone":"America/Puerto_Rico",
    "iso:country":"PR",
    "wof:name":"Candelaria Comunidad",
    "wof:placetype":"locality"
},
  "geometry": {"coordinates":[-66.21753000000001,18.40426],"type":"Point"}
}