{
  "type": "Feature",
  "properties": {
    "iso:country":"PR",
    "qs:a0":"Portugal",
    "qs:a1":"*Porto",
    "qs:a1r":"0",
    "qs:adm0":"Portugal",
    "qs:la_lc":"*",
    "qs:level":"locality",
    "qs:loc":"Paranho de Areia",
    "qs:loc_alt":"Paranho de Areia",
    "qs:pop":0,
    "qs:type":"buffered point",
    "wof:name":"Paranho de Areia",
    "wof:placetype":"locality"
},
  "geometry": {"coordinates":[-8.782699,41.396352],"type":"Point"}
}