{
  "type": "Feature",
  "properties": {
    "gn:admin1_code":"017",
    "gn:admin2_code":"7268408",
    "gn:asciiname":"Villa Barcelona",
    "gn:country_code":"PR",
    "gn:dem":3,
    "gn:elevation":"3.0",
    "gn:feature_class":"P",
    "gn:feature_code":"PPL",
    "gn:name":"Villa Barcelona",
    "gn:population":0,
    "gn:timezone":"America/Puerto_Rico",
    "iso:country":"PR",
    "wof:name":"Villa Barcelona",
    "wof:placetype":"locality"
},
  "geometry": {"coordinates":[-66.54823,18.45578],"type":"Point"}
}