{
  "type": "Feature",
  "properties": {
    "gn:admin1_code":"097",
    "gn:admin2_code":"7268421",
    "gn:asciiname":"San Jose",
    "gn:country_code":"PR",
    "gn:dem":5,
    "gn:elevation":"2.0",
    "gn:feature_class":"P",
    "gn:feature_code":"PPL",
    "gn:name":"San Jos\u00e9",
    "gn:population":0,
    "gn:timezone":"America/Puerto_Rico",
    "iso:country":"PR",
    "name:und_x_variant":[
        "Guanajibo"
    ],
    "wof:name":"San Jose",
    "wof:placetype":"locality"
},
  "geometry": {"coordinates":[-67.17282,18.17411],"type":"Point"}
}