{
  "type": "Feature",
  "properties": {
    "gn:admin1_code":"075",
    "gn:admin2_code":"7268501",
    "gn:asciiname":"Las Viudas",
    "gn:country_code":"PR",
    "gn:dem":73,
    "gn:elevation":"73.0",
    "gn:feature_class":"P",
    "gn:feature_code":"PPL",
    "gn:name":"Las Viudas",
    "gn:population":0,
    "gn:timezone":"America/Puerto_Rico",
    "iso:country":"PR",
    "wof:name":"Las Viudas",
    "wof:placetype":"locality"
},
  "geometry": {"coordinates":[-66.52739,18.05191],"type":"Point"}
}