{
  "type": "Feature",
  "properties": {
    "gn:admin1_code":"073",
    "gn:admin2_code":"7268607",
    "gn:asciiname":"Hacienda Santa Barbara",
    "gn:country_code":"PR",
    "gn:dem":561,
    "gn:elevation":"550.0",
    "gn:feature_class":"P",
    "gn:feature_code":"PPL",
    "gn:name":"Hacienda Santa B\u00e1rbara",
    "gn:population":0,
    "gn:timezone":"America/Puerto_Rico",
    "iso:country":"PR",
    "wof:name":"Hacienda Santa Barbara",
    "wof:placetype":"locality"
},
  "geometry": {"coordinates":[-66.56267,18.25384],"type":"Point"}
}