{
  "type": "Feature",
  "properties": {
    "gn:admin1_code":"039",
    "gn:admin2_code":"7268401",
    "gn:asciiname":"Hacienda Santa Elena",
    "gn:country_code":"PR",
    "gn:dem":349,
    "gn:elevation":"351.0",
    "gn:feature_class":"P",
    "gn:feature_code":"PPL",
    "gn:name":"Hacienda Santa Elena",
    "gn:population":0,
    "gn:timezone":"America/Puerto_Rico",
    "iso:country":"PR",
    "wof:name":"Hacienda Santa Elena",
    "wof:placetype":"locality"
},
  "geometry": {"coordinates":[-66.53239000000001,18.30384],"type":"Point"}
}