{
  "type": "Feature",
  "properties": {
    "gn:admin1_code":"139",
    "gn:admin2_code":"7268156",
    "gn:asciiname":"Primavera",
    "gn:country_code":"PR",
    "gn:dem":29,
    "gn:elevation":"23.0",
    "gn:feature_class":"P",
    "gn:feature_code":"PPL",
    "gn:name":"Primavera",
    "gn:population":0,
    "gn:timezone":"America/Puerto_Rico",
    "iso:country":"PR",
    "name:bel_x_preferred":[
        "\u0412\u044f\u0441\u043d\u0430"
    ],
    "name:bre_x_preferred":[
        "Primavera"
    ],
    "name:cat_x_preferred":[
        "Primavera"
    ],
    "name:ceb_x_preferred":[
        "Primavera"
    ],
    "name:deu_x_preferred":[
        "Primavera"
    ],
    "name:fas_x_preferred":[
        "\u067e\u0631\u06cc\u0645\u0627\u0648\u0631\u0627"
    ],
    "name:fin_x_preferred":[
        "Primavera"
    ],
    "name:fra_x_preferred":[
        "Primavera"
    ],
    "name:ita_x_preferred":[
        "Primavera"
    ],
    "name:jpn_x_preferred":[
        "\u30d7\u30ea\u30de\u30f4\u30a7\u30fc\u30e9"
    ],
    "name:kor_x_preferred":[
        "\ud504\ub9ac\ub9c8\ubca0\ub77c"
    ],
    "name:nld_x_preferred":[
        "Primavera"
    ],
    "name:nor_x_preferred":[
        "Primavera"
    ],
    "name:por_x_preferred":[
        "Primavera"
    ],
    "name:rus_x_preferred":[
        "\u0412\u0435\u0441\u043d\u0430"
    ],
    "name:slk_x_preferred":[
        "Primavera"
    ],
    "name:spa_x_preferred":[
        "Primavera"
    ],
    "name:srp_x_preferred":[
        "\u041f\u0440\u0438\u043c\u0430\u0432\u0435\u0440\u0430"
    ],
    "name:swe_x_preferred":[
        "Primavera"
    ],
    "name:ukr_x_preferred":[
        "\u0412\u0435\u0441\u043d\u0430"
    ],
    "name:vol_x_preferred":[
        "Primavera"
    ],
    "wof:name":"Primavera",
    "wof:placetype":"locality"
},
  "geometry": {"coordinates":[-65.98989,18.34384],"type":"Point"}
}