{
  "type": "Feature",
  "properties": {
    "gn:admin1_code":"043",
    "gn:admin2_code":"7268092",
    "gn:asciiname":"Jardines de San Blas",
    "gn:country_code":"PR",
    "gn:dem":145,
    "gn:elevation":"142.0",
    "gn:feature_class":"P",
    "gn:feature_code":"PPL",
    "gn:name":"Jardines de San Blas",
    "gn:population":0,
    "gn:timezone":"America/Puerto_Rico",
    "iso:country":"PR",
    "wof:name":"Jardines de San Blas",
    "wof:placetype":"locality"
},
  "geometry": {"coordinates":[-66.36516999999999,18.0758],"type":"Point"}
}