{
  "type": "Feature",
  "properties": {
    "gn:admin1_code":"025",
    "gn:admin2_code":"7269055",
    "gn:asciiname":"Villas de Rio Verde",
    "gn:country_code":"PR",
    "gn:dem":87,
    "gn:elevation":"78.0",
    "gn:feature_class":"P",
    "gn:feature_code":"PPL",
    "gn:name":"Villas de Rio Verde",
    "gn:population":0,
    "gn:timezone":"America/Puerto_Rico",
    "iso:country":"PR",
    "name:und_x_variant":[
        "Rio Verde"
    ],
    "wof:name":"Villas de Rio Verde",
    "wof:placetype":"locality"
},
  "geometry": {"coordinates":[-66.03572,18.21412],"type":"Point"}
}