{
  "type": "Feature",
  "properties": {
    "gn:admin1_code":"127",
    "gn:admin2_code":"7268463",
    "gn:asciiname":"Davita y Llenza",
    "gn:country_code":"PR",
    "gn:dem":7,
    "gn:elevation":"6.0",
    "gn:feature_class":"P",
    "gn:feature_code":"PPL",
    "gn:name":"Davita y Llenza",
    "gn:population":0,
    "gn:timezone":"America/Puerto_Rico",
    "iso:country":"PR",
    "wof:name":"Davita y Llenza",
    "wof:placetype":"locality"
},
  "geometry": {"coordinates":[-66.04767,18.41828],"type":"Point"}
}