{
  "type": "Feature",
  "properties": {
    "gn:admin1_code":"005",
    "gn:admin2_code":"7268171",
    "gn:asciiname":"Nuevo",
    "gn:country_code":"PR",
    "gn:dem":8,
    "gn:elevation":"3.0",
    "gn:feature_class":"P",
    "gn:feature_code":"PPL",
    "gn:name":"Nuevo",
    "gn:population":0,
    "gn:timezone":"America/Puerto_Rico",
    "iso:country":"PR",
    "wof:name":"Nuevo",
    "wof:placetype":"locality"
},
  "geometry": {"coordinates":[-67.15406999999999,18.42578],"type":"Point"}
}