{
  "type": "Feature",
  "properties": {
    "gn:admin1_code":"139",
    "gn:admin2_code":"7268133",
    "gn:asciiname":"Las Cuevas",
    "gn:country_code":"PR",
    "gn:dem":58,
    "gn:elevation":"62.0",
    "gn:feature_class":"P",
    "gn:feature_code":"PPL",
    "gn:name":"Las Cuevas",
    "gn:population":0,
    "gn:timezone":"America/Puerto_Rico",
    "iso:country":"PR",
    "wof:name":"Las Cuevas",
    "wof:placetype":"locality"
},
  "geometry": {"coordinates":[-66.01517,18.36773],"type":"Point"}
}