{
  "type": "Feature",
  "properties": {
    "gn:admin1_code":"133",
    "gn:admin2_code":"7268258",
    "gn:asciiname":"Hacienda Altura",
    "gn:country_code":"PR",
    "gn:dem":25,
    "gn:elevation":"23.0",
    "gn:feature_class":"P",
    "gn:feature_code":"PPL",
    "gn:name":"Hacienda Altura",
    "gn:population":0,
    "gn:timezone":"America/Puerto_Rico",
    "iso:country":"PR",
    "name:und_x_variant":[
        "Colinia Altura"
    ],
    "wof:name":"Hacienda Altura",
    "wof:placetype":"locality"
},
  "geometry": {"coordinates":[-66.41489,17.99969],"type":"Point"}
}