{
  "type": "Feature",
  "properties": {
    "gn:country":"PR",
    "gn:fcode":"PPL",
    "gn:population":20295,
    "iso:country":"PR",
    "name:azb_x_preferred":[
        "\u06cc\u0627\u0648\u06a9\u0648"
    ],
    "name:bpy_x_preferred":[
        "\u09af\u09bc\u09be\u0989\u0995\u09cb"
    ],
    "name:cat_x_preferred":[
        "Yauco"
    ],
    "name:ceb_x_preferred":[
        "Yauco"
    ],
    "name:deu_x_preferred":[
        "Yauco"
    ],
    "name:eng_x_preferred":[
        "Yauco"
    ],
    "name:epo_x_preferred":[
        "Yauco"
    ],
    "name:fas_x_preferred":[
        "\u06cc\u0627\u0648\u06a9\u0648"
    ],
    "name:fra_x_preferred":[
        "Yauco"
    ],
    "name:gle_x_preferred":[
        "Yauco"
    ],
    "name:ita_x_preferred":[
        "Yauco"
    ],
    "name:jpn_x_preferred":[
        "\u30e4\u30a6\u30b3"
    ],
    "name:nld_x_preferred":[
        "Yauco"
    ],
    "name:pol_x_preferred":[
        "Yauco"
    ],
    "name:por_x_preferred":[
        "Yauco"
    ],
    "name:rus_x_preferred":[
        "\u042f\u0443\u043a\u043e"
    ],
    "name:scn_x_preferred":[
        "Yauco"
    ],
    "name:spa_x_preferred":[
        "Yauco"
    ],
    "name:srp_x_preferred":[
        "\u0408\u0430\u0443\u043a\u043e"
    ],
    "name:srp_x_variant":[
        "Yauco"
    ],
    "name:ukr_x_preferred":[
        "\u042f\u0443\u043a\u043e"
    ],
    "name:und_x_variant":[
        "Coayuco"
    ],
    "name:urd_x_preferred":[
        "\u06cc\u0627\u0648\u06a9\u0648\u060c \u067e\u0648\u0631\u0679\u0648 \u0631\u06cc\u06a9\u0648"
    ],
    "name:urd_x_variant":[
        "\u06cc\u0648\u06a9\u0648"
    ],
    "name:war_x_preferred":[
        "Yauco"
    ],
    "name:zho_x_preferred":[
        "\u582f\u79d1"
    ],
    "qs_pg:aaroncc":"PR",
    "qs_pg:gn_country":"PR",
    "qs_pg:gn_fcode":"PPL",
    "qs_pg:gn_pop":20295,
    "qs_pg:name":"Yauco",
    "qs_pg:name_adm0":"Puerto Rico",
    "qs_pg:name_adm1":"Yauco",
    "qs_pg:photos":141,
    "qs_pg:photos_1k":29,
    "qs_pg:photos_9k":1,
    "qs_pg:photos_9r":3,
    "qs_pg:photos_all":141,
    "qs_pg:photos_sr":3,
    "qs_pg:pop_sr":7,
    "qs_pg:qs_pg_placetype":"locality",
    "qs_pg:qs_pg_placetype_gp":"Town",
    "qs_pg:woe_adm0":23424935,
    "woe:adm0_id":23424935,
    "woe:name_adm0":"Puerto Rico",
    "woe:name_adm1":"Yauco",
    "woe:placetype":"Town",
    "wof:name":"Yauco",
    "wof:placetype":"locality",
    "wof:population":20295
},
  "geometry": {"coordinates":[-66.84990000000001,18.03496],"type":"Point"}
}