{
  "type": "Feature",
  "properties": {
    "gn:admin1_code":"017",
    "gn:admin2_code":"7268408",
    "gn:asciiname":"Garrochales Comunidad",
    "gn:country_code":"PR",
    "gn:dem":41,
    "gn:elevation":"36.0",
    "gn:feature_class":"P",
    "gn:feature_code":"PPL",
    "gn:name":"Garrochales Comunidad",
    "gn:population":0,
    "gn:timezone":"America/Puerto_Rico",
    "iso:country":"PR",
    "wof:name":"Garrochales Comunidad",
    "wof:placetype":"locality"
},
  "geometry": {"coordinates":[-66.56755,18.4572],"type":"Point"}
}