{
  "type": "Feature",
  "properties": {
    "gn:admin1_code":"083",
    "gn:admin2_code":"7268613",
    "gn:asciiname":"Munoz Torruellas",
    "gn:country_code":"PR",
    "gn:dem":264,
    "gn:elevation":"257.0",
    "gn:feature_class":"P",
    "gn:feature_code":"PPL",
    "gn:name":"Mu\u00f1oz Torruellas",
    "gn:population":0,
    "gn:timezone":"America/Puerto_Rico",
    "iso:country":"PR",
    "name:und_x_variant":[
        "Parce Las Torruellas"
    ],
    "wof:name":"Munoz Torruellas",
    "wof:placetype":"locality"
},
  "geometry": {"coordinates":[-66.98546,18.25468],"type":"Point"}
}