{
  "type": "Feature",
  "properties": {
    "gn:admin1_code":"139",
    "gn:admin2_code":"7268133",
    "gn:asciiname":"Sunville",
    "gn:country_code":"PR",
    "gn:dem":83,
    "gn:elevation":"87.0",
    "gn:feature_class":"P",
    "gn:feature_code":"PPL",
    "gn:name":"Sunville",
    "gn:population":0,
    "gn:timezone":"America/Puerto_Rico",
    "iso:country":"PR",
    "wof:name":"Sunville",
    "wof:placetype":"locality"
},
  "geometry": {"coordinates":[-66.02044000000001,18.36356],"type":"Point"}
}