{
  "type": "Feature",
  "properties": {
    "gn:admin1_code":"127",
    "gn:admin2_code":"7268293",
    "gn:asciiname":"Bucare",
    "gn:country_code":"PR",
    "gn:dem":62,
    "gn:elevation":"61.0",
    "gn:feature_class":"P",
    "gn:feature_code":"PPL",
    "gn:name":"Bucar\u00e9",
    "gn:population":0,
    "gn:timezone":"America/Puerto_Rico",
    "iso:country":"PR",
    "wof:name":"Bucare",
    "wof:placetype":"locality"
},
  "geometry": {"coordinates":[-66.08711,18.36439],"type":"Point"}
}