{
  "type": "Feature",
  "properties": {
    "gn:admin1_code":"033",
    "gn:admin2_code":"7268723",
    "gn:asciiname":"Catano Zona Urbana",
    "gn:country_code":"PR",
    "gn:dem":0,
    "gn:elevation":"0.0",
    "gn:feature_class":"P",
    "gn:feature_code":"PPL",
    "gn:name":"Cata\u00f1o Zona Urbana",
    "gn:population":0,
    "gn:timezone":"America/Puerto_Rico",
    "iso:country":"PR",
    "wof:name":"Catano Zona Urbana",
    "wof:placetype":"locality"
},
  "geometry": {"coordinates":[-66.13884,18.44157],"type":"Point"}
}