{
  "type": "Feature",
  "properties": {
    "gn:admin1_code":"059",
    "gn:admin2_code":"7268440",
    "gn:asciiname":"Extension Santa Elena De Monte II",
    "gn:country_code":"PR",
    "gn:dem":30,
    "gn:elevation":"26.0",
    "gn:feature_class":"P",
    "gn:feature_code":"PPL",
    "gn:name":"Extension Santa Elena De Monte II",
    "gn:population":0,
    "gn:timezone":"America/Puerto_Rico",
    "iso:country":"PR",
    "wof:name":"Extension Santa Elena De Monte II",
    "wof:placetype":"locality"
},
  "geometry": {"coordinates":[-66.78962,18.0283],"type":"Point"}
}