{
  "type": "Feature",
  "properties": {
    "gn:admin1_code":"071",
    "gn:admin2_code":"7268496",
    "gn:asciiname":"Lamela",
    "gn:country_code":"PR",
    "gn:dem":65,
    "gn:elevation":"62.0",
    "gn:feature_class":"P",
    "gn:feature_code":"PPL",
    "gn:name":"Lamela",
    "gn:population":0,
    "gn:timezone":"America/Puerto_Rico",
    "iso:country":"PR",
    "wof:name":"Lamela",
    "wof:placetype":"locality"
},
  "geometry": {"coordinates":[-67.0274,18.50494],"type":"Point"}
}