{
  "type": "Feature",
  "properties": {
    "gn:admin1_code":"123",
    "gn:admin2_code":"7268174",
    "gn:asciiname":"Coqui Comunidad",
    "gn:country_code":"PR",
    "gn:dem":11,
    "gn:elevation":"10.0",
    "gn:feature_class":"P",
    "gn:feature_code":"PPL",
    "gn:name":"Coqu\u00ed Comunidad",
    "gn:population":0,
    "gn:timezone":"America/Puerto_Rico",
    "iso:country":"PR",
    "wof:name":"Coqui Comunidad",
    "wof:placetype":"locality"
},
  "geometry": {"coordinates":[-66.22551999999999,17.97928],"type":"Point"}
}