{
  "type": "Feature",
  "properties": {
    "gn:admin1_code":"011",
    "gn:admin2_code":"7268285",
    "gn:asciiname":"La Tosca",
    "gn:country_code":"PR",
    "gn:dem":27,
    "gn:elevation":"13.0",
    "gn:feature_class":"P",
    "gn:feature_code":"PPL",
    "gn:name":"La Tosca",
    "gn:population":0,
    "gn:timezone":"America/Puerto_Rico",
    "iso:country":"PR",
    "wof:name":"La Tosca",
    "wof:placetype":"locality"
},
  "geometry": {"coordinates":[-67.20879000000001,18.29773],"type":"Point"}
}