{
  "type": "Feature",
  "properties": {
    "gn:admin1_code":"065",
    "gn:admin2_code":"7268308",
    "gn:asciiname":"Rafael Capo Comunidad",
    "gn:country_code":"PR",
    "gn:dem":196,
    "gn:elevation":"182.0",
    "gn:feature_class":"P",
    "gn:feature_code":"PPL",
    "gn:name":"Rafael Cap\u00f3 Comunidad",
    "gn:population":0,
    "gn:timezone":"America/Puerto_Rico",
    "iso:country":"PR",
    "wof:name":"Rafael Capo Comunidad",
    "wof:placetype":"locality"
},
  "geometry": {"coordinates":[-66.7908,18.39978],"type":"Point"}
}