{
  "type": "Feature",
  "properties": {
    "gn:admin1_code":"047",
    "gn:admin2_code":"7268713",
    "gn:asciiname":"Padilla",
    "gn:country_code":"PR",
    "gn:dem":234,
    "gn:elevation":"241.0",
    "gn:feature_class":"P",
    "gn:feature_code":"PPL",
    "gn:name":"Padilla",
    "gn:population":0,
    "gn:timezone":"America/Puerto_Rico",
    "iso:country":"PR",
    "name:ceb_x_preferred":[
        "Padilla"
    ],
    "name:deu_x_preferred":[
        "Padilla"
    ],
    "name:fra_x_preferred":[
        "Padilla"
    ],
    "name:ita_x_preferred":[
        "Padilla"
    ],
    "name:nds_x_preferred":[
        "Padilla"
    ],
    "name:nld_x_preferred":[
        "Padilla"
    ],
    "name:rus_x_preferred":[
        "\u041f\u0430\u0434\u0438\u043b\u044c\u044f"
    ],
    "name:spa_x_preferred":[
        "Padilla"
    ],
    "name:swe_x_preferred":[
        "Padilla"
    ],
    "wof:name":"Padilla",
    "wof:placetype":"locality"
},
  "geometry": {"coordinates":[-66.34461,18.3219],"type":"Point"}
}