{
  "type": "Feature",
  "properties": {
    "gn:admin1_code":"077",
    "gn:admin2_code":"7268603",
    "gn:asciiname":"Cantagallo",
    "gn:country_code":"PR",
    "gn:dem":88,
    "gn:elevation":"84.0",
    "gn:feature_class":"P",
    "gn:feature_code":"PPL",
    "gn:name":"Cantagallo",
    "gn:population":0,
    "gn:timezone":"America/Puerto_Rico",
    "iso:country":"PR",
    "wof:name":"Cantagallo",
    "wof:placetype":"locality"
},
  "geometry": {"coordinates":[-65.93489,18.24245],"type":"Point"}
}