{
  "type": "Feature",
  "properties": {
    "gn:admin1_code":"131",
    "gn:admin2_code":"7268456",
    "gn:asciiname":"Hato Arriba Comunidad",
    "gn:country_code":"PR",
    "gn:dem":49,
    "gn:elevation":"54.0",
    "gn:feature_class":"P",
    "gn:feature_code":"PPL",
    "gn:name":"Hato Arriba Comunidad",
    "gn:population":0,
    "gn:timezone":"America/Puerto_Rico",
    "iso:country":"PR",
    "wof:name":"Hato Arriba Comunidad",
    "wof:placetype":"locality"
},
  "geometry": {"coordinates":[-67.0334,18.35036],"type":"Point"}
}