{
  "type": "Feature",
  "properties": {
    "gn:admin1_code":"025",
    "gn:admin2_code":"7269055",
    "gn:asciiname":"Residencial Jose Gautier Benitez",
    "gn:country_code":"PR",
    "gn:dem":91,
    "gn:elevation":"87.0",
    "gn:feature_class":"P",
    "gn:feature_code":"PPL",
    "gn:name":"Residencial Jose Gautier Benitez",
    "gn:population":0,
    "gn:timezone":"America/Puerto_Rico",
    "iso:country":"PR",
    "wof:name":"Residencial Jose Gautier Benitez",
    "wof:placetype":"locality"
},
  "geometry": {"coordinates":[-66.041,18.2169],"type":"Point"}
}