{
  "type": "Feature",
  "properties": {
    "gn:admin1_code":"025",
    "gn:admin2_code":"7269043",
    "gn:asciiname":"Villa Borinquen",
    "gn:country_code":"PR",
    "gn:dem":82,
    "gn:elevation":"78.0",
    "gn:feature_class":"P",
    "gn:feature_code":"PPL",
    "gn:name":"Villa Borinquen",
    "gn:population":0,
    "gn:timezone":"America/Puerto_Rico",
    "iso:country":"PR",
    "wof:name":"Villa Borinquen",
    "wof:placetype":"locality"
},
  "geometry": {"coordinates":[-66.01989,18.21412],"type":"Point"}
}