{
  "type": "Feature",
  "properties": {
    "gn:admin1_code":"095",
    "gn:admin2_code":"7268642",
    "gn:asciiname":"Residencial Carmen H Martorell",
    "gn:country_code":"PR",
    "gn:dem":14,
    "gn:elevation":"10.0",
    "gn:feature_class":"P",
    "gn:feature_code":"PPL",
    "gn:name":"Residencial Carmen H Martorell",
    "gn:population":0,
    "gn:timezone":"America/Puerto_Rico",
    "iso:country":"PR",
    "wof:name":"Residencial Carmen H Martorell",
    "wof:placetype":"locality"
},
  "geometry": {"coordinates":[-65.89933000000001,18.00607999999999],"type":"Point"}
}