{
  "type": "Feature",
  "properties": {
    "gn:country":"PR",
    "gn:fcode":"PPL",
    "gn:population":0,
    "iso:country":"PR",
    "name:fra_x_preferred":[
        "Sabana"
    ],
    "name:lat_x_preferred":[
        "Sabana"
    ],
    "name:spa_x_preferred":[
        "Sabana"
    ],
    "name:swe_x_preferred":[
        "Sabana"
    ],
    "qs_pg:aaroncc":"PR",
    "qs_pg:gn_country":"PR",
    "qs_pg:gn_fcode":"PPL",
    "qs_pg:gn_pop":0,
    "qs_pg:name":"Sabana",
    "qs_pg:name_adm0":"Puerto Rico",
    "qs_pg:name_adm1":"Luquillo",
    "qs_pg:photos":2229,
    "qs_pg:photos_1k":452,
    "qs_pg:photos_9k":10,
    "qs_pg:photos_9r":9,
    "qs_pg:photos_all":2229,
    "qs_pg:photos_sr":16,
    "qs_pg:pop_sr":0,
    "qs_pg:qs_pg_placetype":"locality",
    "qs_pg:qs_pg_placetype_gp":"Town",
    "qs_pg:woe_adm0":23424935,
    "woe:adm0_id":23424935,
    "woe:name_adm0":"Puerto Rico",
    "woe:name_adm1":"Luquillo",
    "woe:placetype":"Town",
    "wof:name":"Sabana",
    "wof:placetype":"locality"
},
  "geometry": {"coordinates":[-65.72766,18.32468],"type":"Point"}
}