{
  "type": "Feature",
  "properties": {
    "gn:admin1_code":"135",
    "gn:admin2_code":"7268105",
    "gn:asciiname":"Villa Amparo",
    "gn:country_code":"PR",
    "gn:dem":23,
    "gn:elevation":"28.0",
    "gn:feature_class":"P",
    "gn:feature_code":"PPL",
    "gn:name":"Villa Amparo",
    "gn:population":0,
    "gn:timezone":"America/Puerto_Rico",
    "iso:country":"PR",
    "wof:name":"Villa Amparo",
    "wof:placetype":"locality"
},
  "geometry": {"coordinates":[-66.25211,18.38717],"type":"Point"}
}