{
  "type": "Feature",
  "properties": {
    "gn:admin1_code":"031",
    "gn:admin2_code":"7268282",
    "gn:asciiname":"Mariana",
    "gn:country_code":"PR",
    "gn:dem":147,
    "gn:elevation":"142.0",
    "gn:feature_class":"P",
    "gn:feature_code":"PPL",
    "gn:name":"Mariana",
    "gn:population":0,
    "gn:timezone":"America/Puerto_Rico",
    "iso:country":"PR",
    "wof:name":"Mariana",
    "wof:placetype":"locality"
},
  "geometry": {"coordinates":[-65.95322,18.33356],"type":"Point"}
}