{
  "type": "Feature",
  "properties": {
    "gn:admin1_code":"031",
    "gn:admin2_code":"7268282",
    "gn:asciiname":"Mariana",
    "gn:country_code":"PR",
    "gn:dem":147,
    "gn:elevation":"142.0",
    "gn:feature_class":"P",
    "gn:feature_code":"PPL",
    "gn:name":"Mariana",
    "gn:population":0,
    "gn:timezone":"America/Puerto_Rico",
    "iso:country":"PR",
    "name:cat_x_preferred":[
        "Mariana"
    ],
    "name:ceb_x_preferred":[
        "Mariana"
    ],
    "name:deu_x_preferred":[
        "Mariana"
    ],
    "name:epo_x_preferred":[
        "Mariana"
    ],
    "name:est_x_preferred":[
        "Mariana"
    ],
    "name:fra_x_preferred":[
        "Mariana"
    ],
    "name:heb_x_preferred":[
        "\u05de\u05e8\u05d9\u05d0\u05e0\u05d4"
    ],
    "name:ind_x_preferred":[
        "Mariana"
    ],
    "name:ita_x_preferred":[
        "Mariana"
    ],
    "name:jpn_x_preferred":[
        "\u30de\u30ea\u30a2\u30ca"
    ],
    "name:mlg_x_preferred":[
        "Mariana"
    ],
    "name:nld_x_preferred":[
        "Mariana"
    ],
    "name:por_x_preferred":[
        "Mariana"
    ],
    "name:ron_x_preferred":[
        "Mariana"
    ],
    "name:rus_x_preferred":[
        "\u041c\u0430\u0440\u0438\u0430\u043d\u0430"
    ],
    "name:sco_x_preferred":[
        "Mariana"
    ],
    "name:spa_x_preferred":[
        "Mariana"
    ],
    "name:swe_x_preferred":[
        "Mariana"
    ],
    "wof:name":"Mariana",
    "wof:placetype":"locality"
},
  "geometry": {"coordinates":[-65.95322,18.33356],"type":"Point"}
}