{
  "type": "Feature",
  "properties": {
    "gn:admin1_code":"001",
    "gn:asciiname":"Corozal",
    "gn:country_code":"PR",
    "gn:dem":212,
    "gn:elevation":"190.0",
    "gn:feature_class":"P",
    "gn:feature_code":"PPL",
    "gn:name":"Corozal",
    "gn:population":0,
    "gn:timezone":"America/Puerto_Rico",
    "iso:country":"PR",
    "wof:name":"Corozal",
    "wof:placetype":"locality"
},
  "geometry": {"coordinates":[-66.70573,18.08024],"type":"Point"}
}