{
  "type": "Feature",
  "properties": {
    "gn:admin1_code":"021",
    "gn:admin2_code":"7268466",
    "gn:asciiname":"Rio Hondo IV",
    "gn:country_code":"PR",
    "gn:dem":4,
    "gn:elevation":"3.0",
    "gn:feature_class":"P",
    "gn:feature_code":"PPL",
    "gn:name":"Rio Hondo IV",
    "gn:population":0,
    "gn:timezone":"America/Puerto_Rico",
    "iso:country":"PR",
    "wof:name":"Rio Hondo IV",
    "wof:placetype":"locality"
},
  "geometry": {"coordinates":[-66.16367,18.42559],"type":"Point"}
}