{
  "type": "Feature",
  "properties": {
    "gn:admin1_code":"131",
    "gn:admin2_code":"7268757",
    "gn:asciiname":"El Guayabal",
    "gn:country_code":"PR",
    "gn:dem":132,
    "gn:elevation":"121.0",
    "gn:feature_class":"P",
    "gn:feature_code":"PPL",
    "gn:name":"El Guayabal",
    "gn:population":0,
    "gn:timezone":"America/Puerto_Rico",
    "iso:country":"PR",
    "wof:name":"El Guayabal",
    "wof:placetype":"locality"
},
  "geometry": {"coordinates":[-66.97296,18.33912],"type":"Point"}
}