{
  "type": "Feature",
  "properties": {
    "gn:admin1_code":"149",
    "gn:admin2_code":"7269079",
    "gn:asciiname":"Jagueyes",
    "gn:country_code":"PR",
    "gn:dem":141,
    "gn:elevation":"142.0",
    "gn:feature_class":"P",
    "gn:feature_code":"PPL",
    "gn:name":"Jagueyes",
    "gn:population":0,
    "gn:timezone":"America/Puerto_Rico",
    "iso:country":"PR",
    "wof:name":"Jagueyes",
    "wof:placetype":"locality"
},
  "geometry": {"coordinates":[-66.50851,18.11024],"type":"Point"}
}