{
  "type": "Feature",
  "properties": {
    "gn:elevation":10,
    "gn:gn_country":"PR",
    "gn:gn_fcode":"PPL",
    "gn:gn_pop":0,
    "iso:country":"PR",
    "name:spa_x_preferred":[
        "Eleanor Roosevelt"
    ],
    "name:unk_x_variant":[
        "Eleanor Roosevelt"
    ],
    "qs:gn_adm0_cc":"PR",
    "qs:gn_fcode":"PPL",
    "qs:gn_local":4568220,
    "qs:gn_nam_loc":"aguacate",
    "qs:gn_namadm1":"127",
    "qs:gn_name":"Eleanor Roosevelt",
    "qs:local_max":29505,
    "qs:local_sum":50313,
    "qs:localhoods":63,
    "qs:name":"Eleanor Roosevelt",
    "qs:name_adm0":"Puerto Rico",
    "qs:name_adm1":"San Juan",
    "qs:name_adm2":"Hato Rey Norte",
    "qs:name_local":"San Juan",
    "qs:photo_max":26,
    "qs:photo_sum":98,
    "qs:placetype":"Suburb",
    "qs:quad_count":9,
    "qs:woe_adm0":23424935,
    "qs:woe_adm1":2346815,
    "qs:woe_adm2":26806696,
    "qs:woe_lau":0,
    "qs:woe_local":161685,
    "qs:woe_ver":"7.10.0",
    "qs_pg:aaroncc":"PR",
    "qs_pg:gn_country":"PR",
    "qs_pg:gn_fcode":"PPL",
    "qs_pg:gn_pop":0,
    "qs_pg:name":"Eleanor Roosevelt",
    "qs_pg:name_adm0":"Puerto Rico",
    "qs_pg:name_adm1":"San Juan",
    "qs_pg:photos":68,
    "qs_pg:photos_1k":14,
    "qs_pg:photos_9k":1,
    "qs_pg:photos_9r":2,
    "qs_pg:photos_all":68,
    "qs_pg:photos_sr":2,
    "qs_pg:pop_sr":0,
    "qs_pg:qs_pg_placetype":"neighbourhood",
    "qs_pg:qs_pg_placetype_gp":"Suburb",
    "qs_pg:woe_adm0":23424935,
    "wd:wordcount":9369,
    "wof:lang":[
        "spa"
    ],
    "wof:name":"Eleanor Roosevelt",
    "wof:placetype":"neighbourhood"
},
  "geometry": {"coordinates":[-66.06822200000001,18.418637],"type":"Point"}
}