{
  "type": "Feature",
  "properties": {
    "gn:admin1_code":"011",
    "gn:admin2_code":"7268143",
    "gn:asciiname":"Jardines de Anasco",
    "gn:country_code":"PR",
    "gn:dem":16,
    "gn:elevation":"11.0",
    "gn:feature_class":"P",
    "gn:feature_code":"PPL",
    "gn:name":"Jardines de Anasco",
    "gn:population":0,
    "gn:timezone":"America/Puerto_Rico",
    "iso:country":"PR",
    "wof:name":"Jardines de Anasco",
    "wof:placetype":"locality"
},
  "geometry": {"coordinates":[-67.13685,18.28884],"type":"Point"}
}