{
  "type": "Feature",
  "properties": {
    "gn:admin1_code":"127",
    "gn:admin2_code":"7268944",
    "gn:asciiname":"Villa Prades",
    "gn:country_code":"PR",
    "gn:dem":19,
    "gn:elevation":"16.0",
    "gn:feature_class":"P",
    "gn:feature_code":"PPL",
    "gn:name":"Villa Prades",
    "gn:population":0,
    "gn:timezone":"America/Puerto_Rico",
    "iso:country":"PR",
    "wof:name":"Villa Prades",
    "wof:placetype":"locality"
},
  "geometry": {"coordinates":[-66.02489,18.40689],"type":"Point"}
}