{
  "type": "Feature",
  "properties": {
    "gn:admin1_code":"111",
    "gn:admin2_code":"7268511",
    "gn:asciiname":"Jardines de Penuelas",
    "gn:country_code":"PR",
    "gn:dem":73,
    "gn:elevation":"73.0",
    "gn:feature_class":"P",
    "gn:feature_code":"PPL",
    "gn:name":"Jardines de Penuelas",
    "gn:population":0,
    "gn:timezone":"America/Puerto_Rico",
    "iso:country":"PR",
    "wof:name":"Jardines de Penuelas",
    "wof:placetype":"locality"
},
  "geometry": {"coordinates":[-66.72045,18.06163],"type":"Point"}
}