{
  "type": "Feature",
  "properties": {
    "gn:admin1_code":"025",
    "gn:admin2_code":"7268250",
    "gn:asciiname":"Munoz Grillo",
    "gn:country_code":"PR",
    "gn:dem":460,
    "gn:elevation":"444.0",
    "gn:feature_class":"P",
    "gn:feature_code":"PPL",
    "gn:name":"Mu\u00f1oz Grillo",
    "gn:population":0,
    "gn:timezone":"America/Puerto_Rico",
    "iso:country":"PR",
    "wof:name":"Munoz Grillo",
    "wof:placetype":"locality"
},
  "geometry": {"coordinates":[-66.09044,18.17551],"type":"Point"}
}