{
  "type": "Feature",
  "properties": {
    "gn:admin1_code":"001",
    "gn:admin2_code":"7268558",
    "gn:asciiname":"Hacienda Esperanza",
    "gn:country_code":"PR",
    "gn:dem":563,
    "gn:elevation":"556.0",
    "gn:feature_class":"P",
    "gn:feature_code":"PPL",
    "gn:name":"Hacienda Esperanza",
    "gn:population":0,
    "gn:timezone":"America/Puerto_Rico",
    "iso:country":"PR",
    "wof:name":"Hacienda Esperanza",
    "wof:placetype":"locality"
},
  "geometry": {"coordinates":[-66.7974,18.1744],"type":"Point"}
}