{
  "type": "Feature",
  "properties": {
    "gn:country":"PR",
    "iso:country":"PR",
    "name:spa_x_preferred":[
        "Hato Rey Norte"
    ],
    "qs_pg:aaroncc":"PR",
    "qs_pg:gn_country":"PR",
    "qs_pg:name":"Hato Rey Norte",
    "qs_pg:name_adm0":"Puerto Rico",
    "qs_pg:name_adm1":"San Juan",
    "qs_pg:photos":35,
    "qs_pg:photos_1k":7,
    "qs_pg:photos_9k":1,
    "qs_pg:photos_9r":2,
    "qs_pg:photos_all":35,
    "qs_pg:photos_sr":2,
    "qs_pg:pop_sr":0,
    "qs_pg:qs_pg_placetype":"locality",
    "qs_pg:qs_pg_placetype_gp":"Town",
    "qs_pg:woe_adm0":23424935,
    "woe:adm0_id":23424935,
    "woe:name_adm0":"Puerto Rico",
    "woe:name_adm1":"San Juan",
    "woe:placetype":"Town",
    "wof:name":"Hato Rey Norte",
    "wof:placetype":"locality"
},
  "geometry": {"coordinates":[-66.069946,18.42147],"type":"Point"}
}