{
  "type": "Feature",
  "properties": {
    "gn:admin1_code":"131",
    "gn:admin2_code":"7268220",
    "gn:asciiname":"Emerito Estra da Rivera",
    "gn:country_code":"PR",
    "gn:dem":66,
    "gn:elevation":"56.0",
    "gn:feature_class":"P",
    "gn:feature_code":"PPL",
    "gn:name":"Emerito Estra da Rivera",
    "gn:population":0,
    "gn:timezone":"America/Puerto_Rico",
    "iso:country":"PR",
    "wof:name":"Emerito Estra da Rivera",
    "wof:placetype":"locality"
},
  "geometry": {"coordinates":[-66.99157,18.33384],"type":"Point"}
}