{
  "type": "Feature",
  "properties": {
    "gn:admin1_code":"057",
    "gn:admin2_code":"7268582",
    "gn:asciiname":"Barrancas",
    "gn:country_code":"PR",
    "gn:dem":10,
    "gn:elevation":"9.0",
    "gn:feature_class":"P",
    "gn:feature_code":"PPL",
    "gn:name":"Barrancas",
    "gn:population":0,
    "gn:timezone":"America/Puerto_Rico",
    "iso:country":"PR",
    "wof:name":"Barrancas",
    "wof:placetype":"locality"
},
  "geometry": {"coordinates":[-66.12961,17.94802],"type":"Point"}
}