{
  "type": "Feature",
  "properties": {
    "iso:country":"PR",
    "name:por_x_colloquial":[
        "Lavadores"
    ],
    "name:por_x_preferred":[
        "Lavadores"
    ],
    "name:unk_x_variant":[
        "Lavadores"
    ],
    "qs:gn_adm0_cc":"PT",
    "qs:gn_fcode":"PPL",
    "qs:gn_local":8010592,
    "qs:gn_nam_loc":"Vila Nova de Gaia, Porto, PT",
    "qs:gn_namadm1":"17",
    "qs:gn_name":"Lavadores",
    "qs:local_max":20031,
    "qs:local_sum":26947,
    "qs:localhoods":5,
    "qs:name":"Lavadores",
    "qs:name_adm0":"Portugal",
    "qs:name_adm1":"Porto",
    "qs:name_adm2":"Vila Nova de Gaia",
    "qs:name_local":"Vila Nova de Gaia",
    "qs:photo_max":320,
    "qs:photo_sum":2152,
    "qs:placetype":"Suburb",
    "qs:quad_count":72,
    "qs:woe_adm0":23424925,
    "qs:woe_adm1":2346575,
    "qs:woe_adm2":12596513,
    "qs:woe_lau":0,
    "qs:woe_local":12596513,
    "qs:woe_ver":"7.10.0",
    "wof:lang":[
        "por"
    ],
    "wof:name":"Lavadores",
    "wof:placetype":"neighbourhood"
},
  "geometry": {"coordinates":[-8.663034,41.134162],"type":"Point"}
}