{
  "type": "Feature",
  "properties": {
    "gn:admin1_code":"039",
    "gn:admin2_code":"7269044",
    "gn:asciiname":"Hacienda Ralate",
    "gn:country_code":"PR",
    "gn:dem":449,
    "gn:elevation":"448.0",
    "gn:feature_class":"P",
    "gn:feature_code":"PPL",
    "gn:name":"Hacienda Ralate",
    "gn:population":0,
    "gn:timezone":"America/Puerto_Rico",
    "iso:country":"PR",
    "wof:name":"Hacienda Ralate",
    "wof:placetype":"locality"
},
  "geometry": {"coordinates":[-66.51434,18.21079],"type":"Point"}
}