{
  "type": "Feature",
  "properties": {
    "gn:admin1_code":"145",
    "gn:admin2_code":"7268833",
    "gn:asciiname":"Pugnado Afuera",
    "gn:country_code":"PR",
    "gn:dem":83,
    "gn:elevation":"79.0",
    "gn:feature_class":"P",
    "gn:feature_code":"PPL",
    "gn:name":"Pugnado Afuera",
    "gn:population":0,
    "gn:timezone":"America/Puerto_Rico",
    "iso:country":"PR",
    "wof:name":"Pugnado Afuera",
    "wof:placetype":"locality"
},
  "geometry": {"coordinates":[-66.41405999999999,18.42911],"type":"Point"}
}