{
  "type": "Feature",
  "properties": {
    "gn:admin1_code":"143",
    "gn:admin2_code":"7268383",
    "gn:asciiname":"Villa Linares",
    "gn:country_code":"PR",
    "gn:dem":48,
    "gn:elevation":"48.0",
    "gn:feature_class":"P",
    "gn:feature_code":"PPL",
    "gn:name":"Villa Linares",
    "gn:population":0,
    "gn:timezone":"America/Puerto_Rico",
    "iso:country":"PR",
    "wof:name":"Villa Linares",
    "wof:placetype":"locality"
},
  "geometry": {"coordinates":[-66.32378,18.40911],"type":"Point"}
}