{
  "type": "Feature",
  "properties": {
    "gn:admin1_code":"135",
    "gn:admin2_code":"7268105",
    "gn:asciiname":"Jardines de Toa Alta",
    "gn:country_code":"PR",
    "gn:dem":17,
    "gn:elevation":"20.0",
    "gn:feature_class":"P",
    "gn:feature_code":"PPL",
    "gn:name":"Jardines de Toa Alta",
    "gn:population":0,
    "gn:timezone":"America/Puerto_Rico",
    "iso:country":"PR",
    "wof:name":"Jardines de Toa Alta",
    "wof:placetype":"locality"
},
  "geometry": {"coordinates":[-66.25072,18.393],"type":"Point"}
}