{
  "type": "Feature",
  "properties": {
    "gn:admin1_code":"057",
    "gn:admin2_code":"7268344",
    "gn:asciiname":"El Chino",
    "gn:country_code":"PR",
    "gn:dem":575,
    "gn:elevation":"575.0",
    "gn:feature_class":"P",
    "gn:feature_code":"PPL",
    "gn:name":"El Chino",
    "gn:population":0,
    "gn:timezone":"America/Puerto_Rico",
    "iso:country":"PR",
    "wof:name":"El Chino",
    "wof:placetype":"locality"
},
  "geometry": {"coordinates":[-66.09654999999999,18.04913],"type":"Point"}
}