{
  "type": "Feature",
  "properties": {
    "gn:country":"PR",
    "gn:fcode":"PPL",
    "gn:population":9427,
    "iso:country":"PR",
    "name:bpy_x_preferred":[
        "\u099c\u09c1\u09af\u09bc\u09be\u09a8\u09be \u09a1\u09bf\u09af\u09bc\u09be\u099c"
    ],
    "name:cat_x_preferred":[
        "Juana D\u00edaz"
    ],
    "name:ceb_x_preferred":[
        "Juana D\u00edaz"
    ],
    "name:ces_x_preferred":[
        "Juana D\u00edaz"
    ],
    "name:eng_x_preferred":[
        "Juana D\u00edaz"
    ],
    "name:fra_x_preferred":[
        "Juana D\u00edaz"
    ],
    "name:ita_x_preferred":[
        "Juana D\u00edaz"
    ],
    "name:jpn_x_preferred":[
        "\u30d5\u30a1\u30ca\u30fb\u30c7\u30a3\u30a2\u30b9"
    ],
    "name:nld_x_preferred":[
        "Juana D\u00edaz"
    ],
    "name:pol_x_preferred":[
        "Juana D\u00edaz"
    ],
    "name:por_x_preferred":[
        "Juana D\u00edaz"
    ],
    "name:slk_x_preferred":[
        "Juana D\u00edaz"
    ],
    "name:spa_x_preferred":[
        "Juana D\u00edaz"
    ],
    "name:srp_x_preferred":[
        "\u0425\u0443\u0430\u043d\u0430 \u0414\u0438\u0458\u0430\u0437"
    ],
    "name:srp_x_variant":[
        "Juana D\u00edaz"
    ],
    "name:ukr_x_preferred":[
        "\u0425\u0443\u0430\u043d\u0430-\u0414\u0456\u0430\u0441"
    ],
    "name:urd_x_preferred":[
        "\u062e\u0648\u0627\u0646\u0627 \u062f\u06cc\u0627\u0632\u060c \u067e\u0648\u0631\u0679\u0648 \u0631\u06cc\u06a9\u0648"
    ],
    "name:urd_x_variant":[
        "\u062e\u0648\u0627\u0646\u0627 \u062f\u06cc\u0627\u0632"
    ],
    "name:war_x_preferred":[
        "Juana Diaz"
    ],
    "name:zho_x_preferred":[
        "\u80e1\u5b89\u5a1c\u8fea\u4e9e\u65af"
    ],
    "qs_pg:aaroncc":"PR",
    "qs_pg:gn_country":"PR",
    "qs_pg:gn_fcode":"PPL",
    "qs_pg:gn_pop":9427,
    "qs_pg:name":"Juana Diaz",
    "qs_pg:name_adm0":"Puerto Rico",
    "qs_pg:name_adm1":"Juana D\u00edaz",
    "qs_pg:photos":224,
    "qs_pg:photos_1k":45,
    "qs_pg:photos_9k":1,
    "qs_pg:photos_9r":4,
    "qs_pg:photos_all":224,
    "qs_pg:photos_sr":4,
    "qs_pg:pop_sr":5,
    "qs_pg:qs_pg_placetype":"locality",
    "qs_pg:qs_pg_placetype_gp":"Town",
    "qs_pg:woe_adm0":23424935,
    "woe:adm0_id":23424935,
    "woe:name_adm0":"Puerto Rico",
    "woe:name_adm1":"Juana D\u00edaz",
    "woe:placetype":"Town",
    "wof:name":"Juana Diaz",
    "wof:placetype":"locality",
    "wof:population":9427
},
  "geometry": {"coordinates":[-66.50655999999999,18.05246],"type":"Point"}
}