{
  "type": "Feature",
  "properties": {
    "gn:admin1_code":"039",
    "gn:admin2_code":"7268508",
    "gn:asciiname":"Ciales Zona Urbana",
    "gn:country_code":"PR",
    "gn:dem":93,
    "gn:elevation":"89.0",
    "gn:feature_class":"P",
    "gn:feature_code":"PPL",
    "gn:name":"Ciales Zona Urbana",
    "gn:population":0,
    "gn:timezone":"America/Puerto_Rico",
    "iso:country":"PR",
    "wof:name":"Ciales Zona Urbana",
    "wof:placetype":"locality"
},
  "geometry": {"coordinates":[-66.47036,18.33441],"type":"Point"}
}