{
  "type": "Feature",
  "properties": {
    "gn:admin1_code":"087",
    "gn:admin2_code":"7268647",
    "gn:asciiname":"Mini Mini",
    "gn:country_code":"PR",
    "gn:dem":2,
    "gn:elevation":"3.0",
    "gn:feature_class":"P",
    "gn:feature_code":"PPL",
    "gn:name":"Mi\u00f1i Mi\u00f1i",
    "gn:population":0,
    "gn:timezone":"America/Puerto_Rico",
    "iso:country":"PR",
    "wof:name":"Mini Mini",
    "wof:placetype":"locality"
},
  "geometry": {"coordinates":[-65.84461,18.42217],"type":"Point"}
}