{
  "type": "Feature",
  "properties": {
    "gn:admin1_code":"121",
    "gn:admin2_code":"7268996",
    "gn:asciiname":"Campamento Santana",
    "gn:country_code":"PR",
    "gn:dem":681,
    "gn:elevation":"671.0",
    "gn:feature_class":"P",
    "gn:feature_code":"PPL",
    "gn:name":"Campamento Santana",
    "gn:population":0,
    "gn:timezone":"America/Puerto_Rico",
    "iso:country":"PR",
    "wof:name":"Campamento Santana",
    "wof:placetype":"locality"
},
  "geometry": {"coordinates":[-66.96823000000001,18.13885],"type":"Point"}
}