{
  "type": "Feature",
  "properties": {
    "gn:admin1_code":"063",
    "gn:admin2_code":"7268459",
    "gn:asciiname":"Maria Jimenez",
    "gn:country_code":"PR",
    "gn:dem":94,
    "gn:elevation":"87.0",
    "gn:feature_class":"P",
    "gn:feature_code":"PPL",
    "gn:name":"Mar\u00eda Jim\u00e9nez",
    "gn:population":0,
    "gn:timezone":"America/Puerto_Rico",
    "iso:country":"PR",
    "wof:name":"Maria Jimenez",
    "wof:placetype":"locality"
},
  "geometry": {"coordinates":[-65.94155000000001,18.26468],"type":"Point"}
}