{
  "type": "Feature",
  "properties": {
    "gn:admin1_code":"069",
    "gn:admin2_code":"7268579",
    "gn:asciiname":"Roosevelt",
    "gn:country_code":"PR",
    "gn:dem":30,
    "gn:elevation":"23.0",
    "gn:feature_class":"P",
    "gn:feature_code":"PPL",
    "gn:name":"Roosevelt",
    "gn:population":0,
    "gn:timezone":"America/Puerto_Rico",
    "iso:country":"PR",
    "wof:name":"Roosevelt",
    "wof:placetype":"locality"
},
  "geometry": {"coordinates":[-65.82905,18.15635],"type":"Point"}
}