{
  "type": "Feature",
  "properties": {
    "gn:admin1_code":"081",
    "gn:admin2_code":"7268916",
    "gn:asciiname":"Hacienda Monserrate",
    "gn:country_code":"PR",
    "gn:dem":380,
    "gn:elevation":"375.0",
    "gn:feature_class":"P",
    "gn:feature_code":"PPL",
    "gn:name":"Hacienda Monserrate",
    "gn:population":0,
    "gn:timezone":"America/Puerto_Rico",
    "iso:country":"PR",
    "wof:name":"Hacienda Monserrate",
    "wof:placetype":"locality"
},
  "geometry": {"coordinates":[-66.88045,18.19051],"type":"Point"}
}