{
  "type": "Feature",
  "properties": {
    "gn:admin1_code":"127",
    "gn:asciiname":"Parque Isla Verde",
    "gn:country_code":"PR",
    "gn:dem":4,
    "gn:elevation":"3.0",
    "gn:feature_class":"P",
    "gn:feature_code":"PPL",
    "gn:name":"Parque Isla Verde",
    "gn:population":0,
    "gn:timezone":"America/Puerto_Rico",
    "iso:country":"PR",
    "wof:name":"Parque Isla Verde",
    "wof:placetype":"locality"
},
  "geometry": {"coordinates":[-66.00961,18.4255],"type":"Point"}
}