{
  "type": "Feature",
  "properties": {
    "gn:admin1_code":"019",
    "gn:asciiname":"Brisas de Aibonito",
    "gn:country_code":"PR",
    "gn:dem":636,
    "gn:elevation":"626.0",
    "gn:feature_class":"P",
    "gn:feature_code":"PPL",
    "gn:name":"Brisas de Aibonito",
    "gn:population":0,
    "gn:timezone":"America/Puerto_Rico",
    "iso:country":"PR",
    "wof:name":"Brisas de Aibonito",
    "wof:placetype":"locality"
},
  "geometry": {"coordinates":[-66.25322,18.13357],"type":"Point"}
}