{
  "type": "Feature",
  "properties": {
    "gn:admin1_code":"103",
    "gn:admin2_code":"7268485",
    "gn:asciiname":"Estacion Naguabo",
    "gn:country_code":"PR",
    "gn:dem":11,
    "gn:elevation":"9.0",
    "gn:feature_class":"P",
    "gn:feature_code":"PPL",
    "gn:name":"Estaci\u00f3n Naguabo",
    "gn:population":0,
    "gn:timezone":"America/Puerto_Rico",
    "iso:country":"PR",
    "wof:name":"Estacion Naguabo",
    "wof:placetype":"locality"
},
  "geometry": {"coordinates":[-65.72960999999999,18.20413],"type":"Point"}
}