{
  "type": "Feature",
  "properties": {
    "gn:admin1_code":"041",
    "gn:admin2_code":"7268051",
    "gn:asciiname":"Sector Santa Teresita",
    "gn:country_code":"PR",
    "gn:dem":427,
    "gn:elevation":"431.0",
    "gn:feature_class":"P",
    "gn:feature_code":"PPL",
    "gn:name":"Sector Santa Teresita",
    "gn:population":0,
    "gn:timezone":"America/Puerto_Rico",
    "iso:country":"PR",
    "wof:name":"Sector Santa Teresita",
    "wof:placetype":"locality"
},
  "geometry": {"coordinates":[-66.16322,18.18079],"type":"Point"}
}