{
  "type": "Feature",
  "properties": {
    "gn:admin1_code":"123",
    "gn:admin2_code":"7268546",
    "gn:asciiname":"Rabo del Buey",
    "gn:country_code":"PR",
    "gn:dem":74,
    "gn:elevation":"76.0",
    "gn:feature_class":"P",
    "gn:feature_code":"PPL",
    "gn:name":"Rabo del Buey",
    "gn:population":0,
    "gn:timezone":"America/Puerto_Rico",
    "iso:country":"PR",
    "wof:name":"Rabo del Buey",
    "wof:placetype":"locality"
},
  "geometry": {"coordinates":[-66.24045,18.03496],"type":"Point"}
}