{
  "type": "Feature",
  "properties": {
    "gn:admin1_code":"135",
    "gn:admin2_code":"7268685",
    "gn:asciiname":"Bucarabones",
    "gn:country_code":"PR",
    "gn:dem":66,
    "gn:elevation":"62.0",
    "gn:feature_class":"P",
    "gn:feature_code":"PPL",
    "gn:name":"Bucarabones",
    "gn:population":0,
    "gn:timezone":"America/Puerto_Rico",
    "iso:country":"PR",
    "wof:name":"Bucarabones",
    "wof:placetype":"locality"
},
  "geometry": {"coordinates":[-66.21850000000001,18.39606],"type":"Point"}
}