{
  "type": "Feature",
  "properties": {
    "gn:admin1_code":"045",
    "gn:admin2_code":"7268760",
    "gn:asciiname":"Sector Villa Brava",
    "gn:country_code":"PR",
    "gn:dem":263,
    "gn:elevation":"260.0",
    "gn:feature_class":"P",
    "gn:feature_code":"PPL",
    "gn:name":"Sector Villa Brava",
    "gn:population":0,
    "gn:timezone":"America/Puerto_Rico",
    "iso:country":"PR",
    "wof:name":"Sector Villa Brava",
    "wof:placetype":"locality"
},
  "geometry": {"coordinates":[-66.22906,18.21023],"type":"Point"}
}