{
  "type": "Feature",
  "properties": {
    "gn:admin1_code":"113",
    "gn:admin2_code":"7268779",
    "gn:asciiname":"El Yerbo",
    "gn:country_code":"PR",
    "gn:dem":81,
    "gn:elevation":"73.0",
    "gn:feature_class":"P",
    "gn:feature_code":"PPL",
    "gn:name":"El Yerbo",
    "gn:population":0,
    "gn:timezone":"America/Puerto_Rico",
    "iso:country":"PR",
    "wof:name":"El Yerbo",
    "wof:placetype":"locality"
},
  "geometry": {"coordinates":[-66.62573,18.03635],"type":"Point"}
}