{
  "type": "Feature",
  "properties": {
    "gn:admin1_code":"057",
    "gn:admin2_code":"7268181",
    "gn:asciiname":"Santa Elena",
    "gn:country_code":"PR",
    "gn:dem":26,
    "gn:elevation":"24.0",
    "gn:feature_class":"P",
    "gn:feature_code":"PPL",
    "gn:name":"Santa Elena",
    "gn:population":0,
    "gn:timezone":"America/Puerto_Rico",
    "iso:country":"PR",
    "name:und_x_variant":[
        "Hacienda Santa Elena"
    ],
    "wof:name":"Santa Elena",
    "wof:placetype":"locality"
},
  "geometry": {"coordinates":[-66.09905000000001,17.9708],"type":"Point"}
}