{
  "type": "Feature",
  "properties": {
    "gn:admin1_code":"127",
    "gn:admin2_code":"7268162",
    "gn:asciiname":"Ramon Nevares",
    "gn:country_code":"PR",
    "gn:dem":12,
    "gn:elevation":"10.0",
    "gn:feature_class":"P",
    "gn:feature_code":"PPL",
    "gn:name":"Ram\u00f3n Nevares",
    "gn:population":0,
    "gn:timezone":"America/Puerto_Rico",
    "iso:country":"PR",
    "wof:name":"Ramon Nevares",
    "wof:placetype":"locality"
},
  "geometry": {"coordinates":[-66.06683000000001,18.39856],"type":"Point"}
}