{
  "type": "Feature",
  "properties": {
    "gn:admin1_code":"033",
    "gn:admin2_code":"7268723",
    "gn:asciiname":"Mansion del Sur",
    "gn:country_code":"PR",
    "gn:dem":2,
    "gn:elevation":"3.0",
    "gn:feature_class":"P",
    "gn:feature_code":"PPL",
    "gn:name":"Mansion del Sur",
    "gn:population":0,
    "gn:timezone":"America/Puerto_Rico",
    "iso:country":"PR",
    "wof:name":"Mansion del Sur",
    "wof:placetype":"locality"
},
  "geometry": {"coordinates":[-66.16266999999999,18.43495],"type":"Point"}
}