{
  "type": "Feature",
  "properties": {
    "gn:admin1_code":"137",
    "gn:admin2_code":"7268946",
    "gn:asciiname":"Los Magos",
    "gn:country_code":"PR",
    "gn:dem":10,
    "gn:elevation":"10.0",
    "gn:feature_class":"P",
    "gn:feature_code":"PPL",
    "gn:name":"Los Magos",
    "gn:population":0,
    "gn:timezone":"America/Puerto_Rico",
    "iso:country":"PR",
    "wof:name":"Los Magos",
    "wof:placetype":"locality"
},
  "geometry": {"coordinates":[-66.18906,18.43328],"type":"Point"}
}