{
  "type": "Feature",
  "properties": {
    "gn:admin1_code":"001",
    "gn:admin2_code":"7268442",
    "gn:asciiname":"Hacienda La Balear",
    "gn:country_code":"PR",
    "gn:dem":461,
    "gn:elevation":"453.0",
    "gn:feature_class":"P",
    "gn:feature_code":"PPL",
    "gn:name":"Hacienda La Balear",
    "gn:population":0,
    "gn:timezone":"America/Puerto_Rico",
    "iso:country":"PR",
    "wof:name":"Hacienda La Balear",
    "wof:placetype":"locality"
},
  "geometry": {"coordinates":[-66.82989999999999,18.19829],"type":"Point"}
}