{
  "type": "Feature",
  "properties": {
    "gn:admin1_code":"127",
    "gn:admin2_code":"7268945",
    "gn:asciiname":"Jardines de Monte Hatillo",
    "gn:country_code":"PR",
    "gn:dem":55,
    "gn:elevation":"55.0",
    "gn:feature_class":"P",
    "gn:feature_code":"PPL",
    "gn:name":"Jardines de Monte Hatillo",
    "gn:population":0,
    "gn:timezone":"America/Puerto_Rico",
    "iso:country":"PR",
    "name:und_x_variant":[
        "Monte Carlo"
    ],
    "wof:name":"Jardines de Monte Hatillo",
    "wof:placetype":"locality"
},
  "geometry": {"coordinates":[-66.01044,18.388],"type":"Point"}
}