{
  "type": "Feature",
  "properties": {
    "gn:admin1_code":"003",
    "gn:admin2_code":"7268434",
    "gn:asciiname":"Residencial Francisco Egipciaco",
    "gn:country_code":"PR",
    "gn:dem":14,
    "gn:elevation":"12.0",
    "gn:feature_class":"P",
    "gn:feature_code":"PPL",
    "gn:name":"Residencial Francisco Egipciaco",
    "gn:population":0,
    "gn:timezone":"America/Puerto_Rico",
    "iso:country":"PR",
    "wof:name":"Residencial Francisco Egipciaco",
    "wof:placetype":"locality"
},
  "geometry": {"coordinates":[-67.19324,18.38106],"type":"Point"}
}