{
  "type": "Feature",
  "properties": {
    "gn:admin1_code":"127",
    "gn:admin2_code":"7268666",
    "gn:asciiname":"Yambelle",
    "gn:country_code":"PR",
    "gn:dem":52,
    "gn:elevation":"50.0",
    "gn:feature_class":"P",
    "gn:feature_code":"PPL",
    "gn:name":"Yambelle",
    "gn:population":0,
    "gn:timezone":"America/Puerto_Rico",
    "iso:country":"PR",
    "wof:name":"Yambelle",
    "wof:placetype":"locality"
},
  "geometry": {"coordinates":[-66.10239,18.38273],"type":"Point"}
}