{
  "type": "Feature",
  "properties": {
    "gn:admin1_code":"021",
    "gn:admin2_code":"7268714",
    "gn:asciiname":"Royal Gardens",
    "gn:country_code":"PR",
    "gn:dem":27,
    "gn:elevation":"22.0",
    "gn:feature_class":"P",
    "gn:feature_code":"PPL",
    "gn:name":"Royal Gardens",
    "gn:population":0,
    "gn:timezone":"America/Puerto_Rico",
    "iso:country":"PR",
    "wof:name":"Royal Gardens",
    "wof:placetype":"locality"
},
  "geometry": {"coordinates":[-66.17933000000001,18.37606],"type":"Point"}
}