{
  "type": "Feature",
  "properties": {
    "gn:country":"PR",
    "iso:country":"PR",
    "qs_pg:aaroncc":"PR",
    "qs_pg:gn_country":"PR",
    "qs_pg:name":"Marueeo",
    "qs_pg:name_adm0":"Puerto Rico",
    "qs_pg:name_adm1":"Ponce",
    "qs_pg:photos":62,
    "qs_pg:photos_1k":13,
    "qs_pg:photos_9k":1,
    "qs_pg:photos_9r":2,
    "qs_pg:photos_all":62,
    "qs_pg:photos_sr":2,
    "qs_pg:pop_sr":0,
    "qs_pg:qs_pg_placetype":"locality",
    "qs_pg:qs_pg_placetype_gp":"Town",
    "qs_pg:woe_adm0":23424935,
    "woe:adm0_id":23424935,
    "woe:name_adm0":"Puerto Rico",
    "woe:name_adm1":"Ponce",
    "woe:placetype":"Town",
    "wof:name":"Marueeo",
    "wof:placetype":"locality"
},
  "geometry": {"coordinates":[-66.654578,18.084159],"type":"Point"}
}