{
  "type": "Feature",
  "properties": {
    "gn:admin1_code":"021",
    "gn:admin2_code":"7268270",
    "gn:asciiname":"El Porton",
    "gn:country_code":"PR",
    "gn:dem":110,
    "gn:elevation":"108.0",
    "gn:feature_class":"P",
    "gn:feature_code":"PPL",
    "gn:name":"El Port\u00f3n",
    "gn:population":0,
    "gn:timezone":"America/Puerto_Rico",
    "iso:country":"PR",
    "wof:name":"El Porton",
    "wof:placetype":"locality"
},
  "geometry": {"coordinates":[-66.19989,18.33912],"type":"Point"}
}