{
  "type": "Feature",
  "properties": {
    "gn:admin1_code":"135",
    "gn:admin2_code":"7268685",
    "gn:asciiname":"Las Arenas",
    "gn:country_code":"PR",
    "gn:dem":48,
    "gn:elevation":"43.0",
    "gn:feature_class":"P",
    "gn:feature_code":"PPL",
    "gn:name":"Las Arenas",
    "gn:population":0,
    "gn:timezone":"America/Puerto_Rico",
    "iso:country":"PR",
    "name:cat_x_preferred":[
        "Areeta"
    ],
    "name:eus_x_preferred":[
        "Areeta"
    ],
    "name:fra_x_preferred":[
        "Areeta"
    ],
    "name:glg_x_preferred":[
        "Areeta"
    ],
    "name:ita_x_preferred":[
        "Las Arenas"
    ],
    "name:spa_x_preferred":[
        "Las Arenas"
    ],
    "wof:name":"Las Arenas",
    "wof:placetype":"locality"
},
  "geometry": {"coordinates":[-66.21406,18.39023],"type":"Point"}
}