{
  "type": "Feature",
  "properties": {
    "gn:admin1_code":"139",
    "gn:admin2_code":"7268347",
    "gn:asciiname":"Carraizo Alto",
    "gn:country_code":"PR",
    "gn:dem":152,
    "gn:elevation":"150.0",
    "gn:feature_class":"P",
    "gn:feature_code":"PPL",
    "gn:name":"Carraizo Alto",
    "gn:population":0,
    "gn:timezone":"America/Puerto_Rico",
    "iso:country":"PR",
    "wof:name":"Carraizo Alto",
    "wof:placetype":"locality"
},
  "geometry": {"coordinates":[-66.03294,18.34245],"type":"Point"}
}