{
  "type": "Feature",
  "properties": {
    "gn:admin1_code":"087",
    "gn:admin2_code":"7269048",
    "gn:asciiname":"Campamento Pinones",
    "gn:country_code":"PR",
    "gn:dem":6,
    "gn:elevation":"6.0",
    "gn:feature_class":"P",
    "gn:feature_code":"PPL",
    "gn:name":"Campamento Pi\u00f1ones",
    "gn:population":0,
    "gn:timezone":"America/Puerto_Rico",
    "iso:country":"PR",
    "wof:name":"Campamento Pinones",
    "wof:placetype":"locality"
},
  "geometry": {"coordinates":[-65.95739,18.44189],"type":"Point"}
}