{
  "type": "Feature",
  "properties": {
    "gn:admin1_code":"125",
    "gn:admin2_code":"7268477",
    "gn:asciiname":"Pico",
    "gn:country_code":"PR",
    "gn:dem":88,
    "gn:elevation":"79.0",
    "gn:feature_class":"P",
    "gn:feature_code":"PPL",
    "gn:name":"Pico",
    "gn:population":0,
    "gn:timezone":"America/Puerto_Rico",
    "iso:country":"PR",
    "name:ara_x_preferred":[
        "\u0628\u064a\u0643\u0648"
    ],
    "name:ben_x_preferred":[
        "\u09aa\u09bf\u0995\u09cb"
    ],
    "name:bre_x_preferred":[
        "Pico"
    ],
    "name:ceb_x_preferred":[
        "Pico"
    ],
    "name:ces_x_preferred":[
        "Pico"
    ],
    "name:dan_x_preferred":[
        "Pico"
    ],
    "name:deu_x_preferred":[
        "Pico"
    ],
    "name:eus_x_preferred":[
        "Pico"
    ],
    "name:fas_x_preferred":[
        "\u062f\u0631\u06cc\u0627\u0631\u0627\u0647 \u067e\u06cc\u06a9\u0648\u06a9"
    ],
    "name:fin_x_preferred":[
        "Pico"
    ],
    "name:fra_x_preferred":[
        "Pico"
    ],
    "name:glg_x_preferred":[
        "Pico"
    ],
    "name:heb_x_preferred":[
        "\u05e4\u05d9\u05e7\u05d5"
    ],
    "name:ita_x_preferred":[
        "Pico"
    ],
    "name:jpn_x_preferred":[
        "\u30d4\u30b3"
    ],
    "name:kor_x_preferred":[
        "\ud53c\ucf54"
    ],
    "name:lit_x_preferred":[
        "Pikas"
    ],
    "name:nds_x_preferred":[
        "Pico"
    ],
    "name:nld_x_preferred":[
        "Pico"
    ],
    "name:pol_x_preferred":[
        "Pico"
    ],
    "name:por_x_preferred":[
        "Pico"
    ],
    "name:slk_x_preferred":[
        "Pico"
    ],
    "name:spa_x_preferred":[
        "Pico"
    ],
    "name:srp_x_preferred":[
        "\u041f\u0438\u0446\u043e"
    ],
    "name:swe_x_preferred":[
        "Pico"
    ],
    "name:urd_x_preferred":[
        "\u067e\u06cc\u06a9\u0648"
    ],
    "name:vie_x_preferred":[
        "\u0110\u1ea3o Pico"
    ],
    "name:vie_x_variant":[
        "Pico"
    ],
    "wof:name":"Pico",
    "wof:placetype":"locality"
},
  "geometry": {"coordinates":[-67.04379,18.12885],"type":"Point"}
}