{
  "type": "Feature",
  "properties": {
    "gn:admin1_code":"125",
    "gn:admin2_code":"7268477",
    "gn:asciiname":"Pico",
    "gn:country_code":"PR",
    "gn:dem":88,
    "gn:elevation":"79.0",
    "gn:feature_class":"P",
    "gn:feature_code":"PPL",
    "gn:name":"Pico",
    "gn:population":0,
    "gn:timezone":"America/Puerto_Rico",
    "iso:country":"PR",
    "wof:name":"Pico",
    "wof:placetype":"locality"
},
  "geometry": {"coordinates":[-67.04379,18.12885],"type":"Point"}
}