{
  "type": "Feature",
  "properties": {
    "gn:admin1_code":"057",
    "gn:admin2_code":"7268181",
    "gn:asciiname":"Paseo Rivera",
    "gn:country_code":"PR",
    "gn:dem":19,
    "gn:elevation":"20.0",
    "gn:feature_class":"P",
    "gn:feature_code":"PPL",
    "gn:name":"Paseo Rivera",
    "gn:population":0,
    "gn:timezone":"America/Puerto_Rico",
    "iso:country":"PR",
    "wof:name":"Paseo Rivera",
    "wof:placetype":"locality"
},
  "geometry": {"coordinates":[-66.09489000000001,17.97663],"type":"Point"}
}