{
  "type": "Feature",
  "properties": {
    "gn:admin1_code":"023",
    "gn:admin2_code":"7268657",
    "gn:asciiname":"Parabueyon",
    "gn:country_code":"PR",
    "gn:dem":40,
    "gn:elevation":"33.0",
    "gn:feature_class":"P",
    "gn:feature_code":"PPL",
    "gn:name":"Parabuey\u00f3n",
    "gn:population":0,
    "gn:timezone":"America/Puerto_Rico",
    "iso:country":"PR",
    "wof:name":"Parabueyon",
    "wof:placetype":"locality"
},
  "geometry": {"coordinates":[-67.16212,18.09274],"type":"Point"}
}