{
  "type": "Feature",
  "properties": {
    "gn:admin1_code":"003",
    "gn:admin2_code":"7268905",
    "gn:asciiname":"Santoni",
    "gn:country_code":"PR",
    "gn:dem":5,
    "gn:elevation":"5.0",
    "gn:feature_class":"P",
    "gn:feature_code":"PPL",
    "gn:name":"Santoni",
    "gn:population":0,
    "gn:timezone":"America/Puerto_Rico",
    "iso:country":"PR",
    "name:ita_x_preferred":[
        "I Santoni"
    ],
    "wof:name":"Santoni",
    "wof:placetype":"locality"
},
  "geometry": {"coordinates":[-67.23045999999999,18.3755],"type":"Point"}
}