{
  "type": "Feature",
  "properties": {
    "gn:admin1_code":"013",
    "gn:admin2_code":"7268384",
    "gn:asciiname":"Animas Comunidad",
    "gn:country_code":"PR",
    "gn:dem":62,
    "gn:elevation":"59.0",
    "gn:feature_class":"P",
    "gn:feature_code":"PPL",
    "gn:name":"Animas Comunidad",
    "gn:population":0,
    "gn:timezone":"America/Puerto_Rico",
    "iso:country":"PR",
    "wof:name":"Animas Comunidad",
    "wof:placetype":"locality"
},
  "geometry": {"coordinates":[-66.63643,18.44575],"type":"Point"}
}