{
  "type": "Feature",
  "properties": {
    "gn:country":"PR",
    "gn:fcode":"PPL",
    "gn:population":0,
    "iso:country":"PR",
    "qs_pg:aaroncc":"PR",
    "qs_pg:gn_country":"PR",
    "qs_pg:gn_fcode":"PPL",
    "qs_pg:gn_pop":0,
    "qs_pg:name":"Roosevelt Roads",
    "qs_pg:name_adm0":"Puerto Rico",
    "qs_pg:name_adm1":"Ceiba",
    "qs_pg:photos":150,
    "qs_pg:photos_1k":30,
    "qs_pg:photos_9k":1,
    "qs_pg:photos_9r":3,
    "qs_pg:photos_all":150,
    "qs_pg:photos_sr":3,
    "qs_pg:pop_sr":0,
    "qs_pg:qs_pg_placetype":"locality",
    "qs_pg:qs_pg_placetype_gp":"Town",
    "qs_pg:woe_adm0":23424935,
    "woe:adm0_id":23424935,
    "woe:name_adm0":"Puerto Rico",
    "woe:name_adm1":"Ceiba",
    "woe:placetype":"Town",
    "wof:name":"Roosevelt Roads",
    "wof:placetype":"locality"
},
  "geometry": {"coordinates":[-65.62909999999999,18.23498],"type":"Point"}
}