{
  "type": "Feature",
  "properties": {
    "gn:admin1_code":"133",
    "gn:admin2_code":"7268258",
    "gn:asciiname":"Velazquez",
    "gn:country_code":"PR",
    "gn:dem":9,
    "gn:elevation":"10.0",
    "gn:feature_class":"P",
    "gn:feature_code":"PPL",
    "gn:name":"Vel\u00e1zquez",
    "gn:population":0,
    "gn:timezone":"America/Puerto_Rico",
    "iso:country":"PR",
    "wof:name":"Velazquez",
    "wof:placetype":"locality"
},
  "geometry": {"coordinates":[-66.41684000000001,17.9733],"type":"Point"}
}