{
  "type": "Feature",
  "properties": {
    "gn:admin1_code":"133",
    "gn:admin2_code":"7268989",
    "gn:asciiname":"Barriada Monserrate",
    "gn:country_code":"PR",
    "gn:dem":10,
    "gn:elevation":"7.0",
    "gn:feature_class":"P",
    "gn:feature_code":"PPL",
    "gn:name":"Barriada Monserrate",
    "gn:population":0,
    "gn:timezone":"America/Puerto_Rico",
    "iso:country":"PR",
    "wof:name":"Barriada Monserrate",
    "wof:placetype":"locality"
},
  "geometry": {"coordinates":[-66.40628000000001,17.9658],"type":"Point"}
}