{
  "type": "Feature",
  "properties": {
    "gn:admin1_code":"093",
    "gn:admin2_code":"7268623",
    "gn:asciiname":"Hacienda Teresa",
    "gn:country_code":"PR",
    "gn:dem":365,
    "gn:elevation":"370.0",
    "gn:feature_class":"P",
    "gn:feature_code":"PPL",
    "gn:name":"Hacienda Teresa",
    "gn:population":0,
    "gn:timezone":"America/Puerto_Rico",
    "iso:country":"PR",
    "wof:name":"Hacienda Teresa",
    "wof:placetype":"locality"
},
  "geometry": {"coordinates":[-66.96768,18.19857],"type":"Point"}
}