{
  "type": "Feature",
  "properties": {
    "gn:admin1_code":"033",
    "gn:admin2_code":"7268723",
    "gn:asciiname":"Mansion del Rio",
    "gn:country_code":"PR",
    "gn:dem":4,
    "gn:elevation":"4.0",
    "gn:feature_class":"P",
    "gn:feature_code":"PPL",
    "gn:name":"Mansion del Rio",
    "gn:population":0,
    "gn:timezone":"America/Puerto_Rico",
    "iso:country":"PR",
    "wof:name":"Mansion del Rio",
    "wof:placetype":"locality"
},
  "geometry": {"coordinates":[-66.16322,18.43884],"type":"Point"}
}