{
  "type": "Feature",
  "properties": {
    "gn:admin1_code":"125",
    "gn:admin2_code":"7268970",
    "gn:asciiname":"Vivoni",
    "gn:country_code":"PR",
    "gn:dem":49,
    "gn:elevation":"46.0",
    "gn:feature_class":"P",
    "gn:feature_code":"PPL",
    "gn:name":"Vivoni",
    "gn:population":0,
    "gn:timezone":"America/Puerto_Rico",
    "iso:country":"PR",
    "wof:name":"Vivoni",
    "wof:placetype":"locality"
},
  "geometry": {"coordinates":[-67.03851,18.08191],"type":"Point"}
}