{
  "type": "Feature",
  "properties": {
    "gn:admin1_code":"027",
    "gn:admin2_code":"7268311",
    "gn:asciiname":"Linda Vista",
    "gn:country_code":"PR",
    "gn:dem":10,
    "gn:elevation":"7.0",
    "gn:feature_class":"P",
    "gn:feature_code":"PPL",
    "gn:name":"Linda Vista",
    "gn:population":0,
    "gn:timezone":"America/Puerto_Rico",
    "iso:country":"PR",
    "wof:name":"Linda Vista",
    "wof:placetype":"locality"
},
  "geometry": {"coordinates":[-66.85101,18.48633],"type":"Point"}
}