{
  "type": "Feature",
  "properties": {
    "gn:country":"PR",
    "iso:country":"PR",
    "qs_pg:aaroncc":"PR",
    "qs_pg:gn_country":"PR",
    "qs_pg:name":"Bajura",
    "qs_pg:name_adm0":"Puerto Rico",
    "qs_pg:name_adm1":"Isabela",
    "qs_pg:photos":352,
    "qs_pg:photos_1k":71,
    "qs_pg:photos_9k":2,
    "qs_pg:photos_9r":5,
    "qs_pg:photos_all":352,
    "qs_pg:photos_sr":6,
    "qs_pg:pop_sr":0,
    "qs_pg:qs_pg_placetype":"locality",
    "qs_pg:qs_pg_placetype_gp":"Town",
    "qs_pg:woe_adm0":23424935,
    "woe:adm0_id":23424935,
    "woe:name_adm0":"Puerto Rico",
    "woe:name_adm1":"Isabela",
    "woe:placetype":"Town",
    "wof:name":"Bajura",
    "wof:placetype":"locality"
},
  "geometry": {"coordinates":[-67.083364,18.514238],"type":"Point"}
}