{
  "type": "Feature",
  "properties": {
    "gn:admin1_code":"141",
    "gn:admin2_code":"7269060",
    "gn:asciiname":"Utuado Zona Urbana",
    "gn:country_code":"PR",
    "gn:dem":168,
    "gn:elevation":"153.0",
    "gn:feature_class":"P",
    "gn:feature_code":"PPL",
    "gn:name":"Utuado Zona Urbana",
    "gn:population":0,
    "gn:timezone":"America/Puerto_Rico",
    "iso:country":"PR",
    "wof:name":"Utuado Zona Urbana",
    "wof:placetype":"locality"
},
  "geometry": {"coordinates":[-66.70491,18.26973],"type":"Point"}
}