{
  "type": "Feature",
  "properties": {
    "gn:admin1_code":"097",
    "gn:admin2_code":"7268948",
    "gn:asciiname":"Mani",
    "gn:country_code":"PR",
    "gn:dem":6,
    "gn:elevation":"3.0",
    "gn:feature_class":"P",
    "gn:feature_code":"PPL",
    "gn:name":"Man\u00ed",
    "gn:population":0,
    "gn:timezone":"America/Puerto_Rico",
    "iso:country":"PR",
    "wof:name":"Mani",
    "wof:placetype":"locality"
},
  "geometry": {"coordinates":[-67.16961999999999,18.24079],"type":"Point"}
}