{
  "type": "Feature",
  "properties": {
    "gn:elevation":677,
    "iso:country":"PR",
    "name:spa_x_preferred":[
        "Villa Olga"
    ],
    "name:unk_x_variant":[
        "Villa Olga"
    ],
    "qs:gn_adm0_cc":"PR",
    "qs:gn_fcode":"PPL",
    "qs:gn_local":4568220,
    "qs:gn_nam_loc":"aguacate",
    "qs:gn_namadm1":"019",
    "qs:gn_name":"Villa Ronga",
    "qs:local_max":29505,
    "qs:local_sum":50313,
    "qs:localhoods":63,
    "qs:name":"Villa Olga",
    "qs:name_adm0":"Puerto Rico",
    "qs:name_adm1":"San Juan",
    "qs:name_adm2":"Cupey",
    "qs:name_local":"San Juan",
    "qs:photo_max":5,
    "qs:photo_sum":6,
    "qs:placetype":"Suburb",
    "qs:quad_count":2,
    "qs:woe_adm0":23424935,
    "qs:woe_adm1":2346815,
    "qs:woe_adm2":26806692,
    "qs:woe_lau":0,
    "qs:woe_local":161685,
    "qs:woe_ver":"7.10.0",
    "wof:lang":[
        "spa"
    ],
    "wof:name":"Villa Olga",
    "wof:placetype":"neighbourhood"
},
  "geometry": {"coordinates":[-66.047974,18.367559],"type":"Point"}
}