{
  "type": "Feature",
  "properties": {
    "gn:admin1_code":"153",
    "gn:admin2_code":"7268917",
    "gn:asciiname":"Hacienda Asuncion",
    "gn:country_code":"PR",
    "gn:dem":826,
    "gn:elevation":"830.0",
    "gn:feature_class":"P",
    "gn:feature_code":"PPL",
    "gn:name":"Hacienda Asunci\u00f3n",
    "gn:population":0,
    "gn:timezone":"America/Puerto_Rico",
    "iso:country":"PR",
    "wof:name":"Hacienda Asuncion",
    "wof:placetype":"locality"
},
  "geometry": {"coordinates":[-66.83156,18.16357],"type":"Point"}
}