{
  "type": "Feature",
  "properties": {
    "gn:admin1_code":"075",
    "gn:admin2_code":"7268574",
    "gn:asciiname":"Boqueron",
    "gn:country_code":"PR",
    "gn:dem":110,
    "gn:elevation":"94.0",
    "gn:feature_class":"P",
    "gn:feature_code":"PPL",
    "gn:name":"Boquer\u00f3n",
    "gn:population":0,
    "gn:timezone":"America/Puerto_Rico",
    "iso:country":"PR",
    "wof:name":"Boqueron",
    "wof:placetype":"locality"
},
  "geometry": {"coordinates":[-66.50406,18.06385],"type":"Point"}
}