{
  "type": "Feature",
  "properties": {
    "gn:gn_country":"PR",
    "iso:country":"PR",
    "qs_pg:aaroncc":"PR",
    "qs_pg:gn_country":"PR",
    "qs_pg:name":"Guzm\u00e1n Arriba",
    "qs_pg:name_adm0":"Puerto Rico",
    "qs_pg:name_adm1":"R\u00edo Grande",
    "qs_pg:photos":1357,
    "qs_pg:photos_1k":275,
    "qs_pg:photos_9k":6,
    "qs_pg:photos_9r":7,
    "qs_pg:photos_all":1357,
    "qs_pg:photos_sr":12,
    "qs_pg:pop_sr":0,
    "qs_pg:qs_pg_placetype":"locality",
    "qs_pg:qs_pg_placetype_gp":"Town",
    "qs_pg:woe_adm0":23424935,
    "woe:adm0_id":23424935,
    "woe:name_adm0":"Puerto Rico",
    "woe:name_adm1":"R\u00edo Grande",
    "woe:placetype":"Town",
    "wof:name":"Guzm\u00e1n Arriba",
    "wof:placetype":"locality"
},
  "geometry": {"coordinates":[-65.802268,18.309144],"type":"Point"}
}