{
  "type": "Feature",
  "properties": {
    "gn:admin1_code":"055",
    "gn:admin2_code":"7269018",
    "gn:asciiname":"Magueyes",
    "gn:country_code":"PR",
    "gn:dem":52,
    "gn:elevation":"48.0",
    "gn:feature_class":"P",
    "gn:feature_code":"PPL",
    "gn:name":"Magueyes",
    "gn:population":0,
    "gn:timezone":"America/Puerto_Rico",
    "iso:country":"PR",
    "wof:name":"Magueyes",
    "wof:placetype":"locality"
},
  "geometry": {"coordinates":[-66.88795,18.01969],"type":"Point"}
}