{
  "type": "Feature",
  "properties": {
    "gn:admin1_code":"057",
    "gn:admin2_code":"7268345",
    "gn:asciiname":"Carmen",
    "gn:country_code":"PR",
    "gn:dem":319,
    "gn:elevation":"323.0",
    "gn:feature_class":"P",
    "gn:feature_code":"PPL",
    "gn:name":"Carmen",
    "gn:population":0,
    "gn:timezone":"America/Puerto_Rico",
    "iso:country":"PR",
    "wof:name":"Carmen",
    "wof:placetype":"locality"
},
  "geometry": {"coordinates":[-66.16933,18.03163],"type":"Point"}
}