{
  "type": "Feature",
  "properties": {
    "gn:admin1_code":"069",
    "gn:admin2_code":"7268579",
    "gn:asciiname":"Fermina",
    "gn:country_code":"PR",
    "gn:dem":129,
    "gn:elevation":"135.0",
    "gn:feature_class":"P",
    "gn:feature_code":"PPL",
    "gn:name":"Fermina",
    "gn:population":0,
    "gn:timezone":"America/Puerto_Rico",
    "iso:country":"PR",
    "name:und_x_variant":[
        "La Permina"
    ],
    "wof:name":"Fermina",
    "wof:placetype":"locality"
},
  "geometry": {"coordinates":[-65.85405,18.17635],"type":"Point"}
}