{
  "type": "Feature",
  "properties": {
    "gn:country":"PR",
    "gn:elevation":77,
    "gn:fcode":"PPL",
    "gn:population":0,
    "iso:country":"PR",
    "name:spa_x_preferred":[
        "Residencial Interamericana"
    ],
    "qs:gn_adm0_cc":"PR",
    "qs:gn_fcode":"PPL",
    "qs:gn_local":4568220,
    "qs:gn_nam_loc":"aguacate",
    "qs:gn_namadm1":"139",
    "qs:gn_name":"Residencial Interamericana",
    "qs:local_max":29505,
    "qs:local_sum":50313,
    "qs:localhoods":63,
    "qs:name":"Residencial Interamericana",
    "qs:name_adm0":"Puerto Rico",
    "qs:name_adm1":"Trujillo Alto",
    "qs:name_adm2":"Cuevas",
    "qs:name_local":"San Juan",
    "qs:photo_max":28,
    "qs:photo_sum":29,
    "qs:placetype":"Suburb",
    "qs:quad_count":2,
    "qs:woe_adm0":23424935,
    "qs:woe_adm1":2346853,
    "qs:woe_adm2":26806767,
    "qs:woe_lau":0,
    "qs:woe_local":161685,
    "qs:woe_ver":"7.10.0",
    "qs_pg:aaroncc":"PR",
    "qs_pg:gn_country":"PR",
    "qs_pg:gn_fcode":"PPL",
    "qs_pg:gn_pop":0,
    "qs_pg:name":"Residencial Interamericana",
    "qs_pg:name_adm0":"Puerto Rico",
    "qs_pg:name_adm1":"Trujillo Alto",
    "qs_pg:photos":29,
    "qs_pg:photos_1k":6,
    "qs_pg:photos_9k":1,
    "qs_pg:photos_9r":2,
    "qs_pg:photos_all":29,
    "qs_pg:photos_sr":2,
    "qs_pg:pop_sr":0,
    "qs_pg:qs_pg_placetype":"neighbourhood",
    "qs_pg:qs_pg_placetype_gp":"Suburb",
    "qs_pg:woe_adm0":23424935,
    "wof:lang":[
        "spa"
    ],
    "wof:name":"Residencial Interamericana",
    "wof:placetype":"neighbourhood"
},
  "geometry": {"coordinates":[-66.030389,18.36756],"type":"Point"}
}