{
  "type": "Feature",
  "properties": {
    "gn:country":"PR",
    "gn:fcode":"PPL",
    "gn:population":1481,
    "iso:country":"PR",
    "qs_pg:aaroncc":"PR",
    "qs_pg:gn_country":"PR",
    "qs_pg:gn_fcode":"PPL",
    "qs_pg:gn_pop":1481,
    "qs_pg:name":"Pueblito del Rio",
    "qs_pg:name_adm0":"Puerto Rico",
    "qs_pg:name_adm1":"Las Piedras",
    "qs_pg:photos":1,
    "qs_pg:photos_1k":1,
    "qs_pg:photos_9k":1,
    "qs_pg:photos_9r":1,
    "qs_pg:photos_all":1,
    "qs_pg:photos_sr":1,
    "qs_pg:pop_sr":3,
    "qs_pg:qs_pg_placetype":"locality",
    "qs_pg:qs_pg_placetype_gp":"Town",
    "qs_pg:woe_adm0":23424935,
    "woe:adm0_id":23424935,
    "woe:name_adm0":"Puerto Rico",
    "woe:name_adm1":"Las Piedras",
    "woe:placetype":"Town",
    "wof:name":"Pueblito del Rio",
    "wof:placetype":"locality",
    "wof:population":1481
},
  "geometry": {"coordinates":[-65.86293999999999,18.22801],"type":"Point"}
}