{
  "type": "Feature",
  "properties": {
    "gn:admin1_code":"127",
    "gn:admin2_code":"7269050",
    "gn:asciiname":"Sierra Brava",
    "gn:country_code":"PR",
    "gn:dem":53,
    "gn:elevation":"50.0",
    "gn:feature_class":"P",
    "gn:feature_code":"PPL",
    "gn:name":"Sierra Brava",
    "gn:population":0,
    "gn:timezone":"America/Puerto_Rico",
    "iso:country":"PR",
    "wof:name":"Sierra Brava",
    "wof:placetype":"locality"
},
  "geometry": {"coordinates":[-66.09350000000001,18.34995],"type":"Point"}
}