{
  "type": "Feature",
  "properties": {
    "gn:admin1_code":"113",
    "gn:admin2_code":"7268612",
    "gn:asciiname":"Hacienda Santa Rita",
    "gn:country_code":"PR",
    "gn:dem":627,
    "gn:elevation":"620.0",
    "gn:feature_class":"P",
    "gn:feature_code":"PPL",
    "gn:name":"Hacienda Santa Rita",
    "gn:population":0,
    "gn:timezone":"America/Puerto_Rico",
    "iso:country":"PR",
    "wof:name":"Hacienda Santa Rita",
    "wof:placetype":"locality"
},
  "geometry": {"coordinates":[-66.59101,18.12718],"type":"Point"}
}