{
  "type": "Feature",
  "properties": {
    "gn:admin1_code":"021",
    "gn:admin2_code":"7268714",
    "gn:asciiname":"Montanez",
    "gn:country_code":"PR",
    "gn:dem":50,
    "gn:elevation":"51.0",
    "gn:feature_class":"P",
    "gn:feature_code":"PPL",
    "gn:name":"Montanez",
    "gn:population":0,
    "gn:timezone":"America/Puerto_Rico",
    "iso:country":"PR",
    "wof:name":"Montanez",
    "wof:placetype":"locality"
},
  "geometry": {"coordinates":[-66.18378,18.37051],"type":"Point"}
}