{
  "type": "Feature",
  "properties": {
    "gn:admin1_code":"127",
    "gn:admin2_code":"7268945",
    "gn:asciiname":"Cambridge Park",
    "gn:country_code":"PR",
    "gn:dem":61,
    "gn:elevation":"63.0",
    "gn:feature_class":"P",
    "gn:feature_code":"PPL",
    "gn:name":"Cambridge Park",
    "gn:population":0,
    "gn:timezone":"America/Puerto_Rico",
    "iso:country":"PR",
    "wof:name":"Cambridge Park",
    "wof:placetype":"locality"
},
  "geometry": {"coordinates":[-66.04904999999999,18.38523],"type":"Point"}
}