{
  "type": "Feature",
  "properties": {
    "gn:admin1_code":"097",
    "gn:admin2_code":"7268645",
    "gn:asciiname":"Columbus Landing",
    "gn:country_code":"PR",
    "gn:dem":3,
    "gn:elevation":"1.0",
    "gn:feature_class":"P",
    "gn:feature_code":"PPL",
    "gn:name":"Columbus Landing",
    "gn:population":0,
    "gn:timezone":"America/Puerto_Rico",
    "iso:country":"PR",
    "wof:name":"Columbus Landing",
    "wof:placetype":"locality"
},
  "geometry": {"coordinates":[-67.15156999999999,18.19857],"type":"Point"}
}