{
  "type": "Feature",
  "properties": {
    "gn:admin1_code":"101",
    "gn:admin2_code":"7268978",
    "gn:asciiname":"Hacienda Maria",
    "gn:country_code":"PR",
    "gn:dem":90,
    "gn:elevation":"89.0",
    "gn:feature_class":"P",
    "gn:feature_code":"PPL",
    "gn:name":"Hacienda Mar\u00eda",
    "gn:population":0,
    "gn:timezone":"America/Puerto_Rico",
    "iso:country":"PR",
    "wof:name":"Hacienda Maria",
    "wof:placetype":"locality"
},
  "geometry": {"coordinates":[-66.44462,18.31162],"type":"Point"}
}