{
  "type": "Feature",
  "properties": {
    "gn:admin1_code":"037",
    "gn:admin2_code":"7268054",
    "gn:asciiname":"Villa Penetro",
    "gn:country_code":"PR",
    "gn:dem":28,
    "gn:elevation":"25.0",
    "gn:feature_class":"P",
    "gn:feature_code":"PPL",
    "gn:name":"Villa Penetro",
    "gn:population":0,
    "gn:timezone":"America/Puerto_Rico",
    "iso:country":"PR",
    "wof:name":"Villa Penetro",
    "wof:placetype":"locality"
},
  "geometry": {"coordinates":[-65.64877,18.26218],"type":"Point"}
}