{
  "type": "Feature",
  "properties": {
    "gn:admin1_code":"021",
    "gn:admin2_code":"7268246",
    "gn:asciiname":"Santa Cruz",
    "gn:country_code":"PR",
    "gn:dem":13,
    "gn:elevation":"10.0",
    "gn:feature_class":"P",
    "gn:feature_code":"PPL",
    "gn:name":"Santa Cruz",
    "gn:population":0,
    "gn:timezone":"America/Puerto_Rico",
    "iso:country":"PR",
    "wof:name":"Santa Cruz",
    "wof:placetype":"locality"
},
  "geometry": {"coordinates":[-66.14655999999999,18.39606],"type":"Point"}
}