{
  "type": "Feature",
  "properties": {
    "gn:admin1_code":"009",
    "gn:admin2_code":"7268178",
    "gn:asciiname":"Aibonito Zona Urbana",
    "gn:country_code":"PR",
    "gn:dem":607,
    "gn:elevation":"603.0",
    "gn:feature_class":"P",
    "gn:feature_code":"PPL",
    "gn:name":"Aibonito Zona Urbana",
    "gn:population":0,
    "gn:timezone":"America/Puerto_Rico",
    "iso:country":"PR",
    "wof:name":"Aibonito Zona Urbana",
    "wof:placetype":"locality"
},
  "geometry": {"coordinates":[-66.26581999999999,18.13983],"type":"Point"}
}