{
  "type": "Feature",
  "properties": {
    "gn:admin1_code":"061",
    "gn:admin2_code":"7268895",
    "gn:asciiname":"Beverly Hills",
    "gn:country_code":"PR",
    "gn:dem":106,
    "gn:elevation":"113.0",
    "gn:feature_class":"P",
    "gn:feature_code":"PPL",
    "gn:name":"Beverly Hills",
    "gn:population":0,
    "gn:timezone":"America/Puerto_Rico",
    "iso:country":"PR",
    "wof:name":"Beverly Hills",
    "wof:placetype":"locality"
},
  "geometry": {"coordinates":[-66.09517,18.33301],"type":"Point"}
}