{
  "type": "Feature",
  "properties": {
    "gn:admin1_code":"119",
    "gn:admin2_code":"7268524",
    "gn:asciiname":"Blasina",
    "gn:country_code":"PR",
    "gn:dem":9,
    "gn:elevation":"9.0",
    "gn:feature_class":"P",
    "gn:feature_code":"PPL",
    "gn:name":"Blasina",
    "gn:population":0,
    "gn:timezone":"America/Puerto_Rico",
    "iso:country":"PR",
    "name:und_x_variant":[
        "Colonia Blasina"
    ],
    "wof:name":"Blasina",
    "wof:placetype":"locality"
},
  "geometry": {"coordinates":[-65.81739,18.37523],"type":"Point"}
}