{
  "type": "Feature",
  "properties": {
    "gn:admin1_code":"081",
    "gn:admin2_code":"7268752",
    "gn:asciiname":"Hacienda Lealtad",
    "gn:country_code":"PR",
    "gn:dem":265,
    "gn:elevation":"260.0",
    "gn:feature_class":"P",
    "gn:feature_code":"PPL",
    "gn:name":"Hacienda Lealtad",
    "gn:population":0,
    "gn:timezone":"America/Puerto_Rico",
    "iso:country":"PR",
    "wof:name":"Hacienda Lealtad",
    "wof:placetype":"locality"
},
  "geometry": {"coordinates":[-66.88406999999999,18.23329],"type":"Point"}
}