{
  "type": "Feature",
  "properties": {
    "gn:admin1_code":"097",
    "gn:admin2_code":"7268933",
    "gn:asciiname":"Cuesta de las Piedras",
    "gn:country_code":"PR",
    "gn:dem":21,
    "gn:elevation":"15.0",
    "gn:feature_class":"P",
    "gn:feature_code":"PPL",
    "gn:name":"Cuesta de las Piedras",
    "gn:population":0,
    "gn:timezone":"America/Puerto_Rico",
    "iso:country":"PR",
    "name:und_x_variant":[
        "Cuesta Las Piedras"
    ],
    "wof:name":"Cuesta de las Piedras",
    "wof:placetype":"locality"
},
  "geometry": {"coordinates":[-67.14296,18.18301],"type":"Point"}
}