{
  "type": "Feature",
  "properties": {
    "gn:admin1_code":"127",
    "gn:admin2_code":"7268463",
    "gn:asciiname":"Hector A Pinero",
    "gn:country_code":"PR",
    "gn:dem":6,
    "gn:elevation":"7.0",
    "gn:feature_class":"P",
    "gn:feature_code":"PPL",
    "gn:name":"Hector A Pi\u00f1ero",
    "gn:population":0,
    "gn:timezone":"America/Puerto_Rico",
    "iso:country":"PR",
    "wof:name":"Hector A Pinero",
    "wof:placetype":"locality"
},
  "geometry": {"coordinates":[-66.05378,18.42356],"type":"Point"}
}