{
  "type": "Feature",
  "properties": {
    "gn:country":"PR",
    "gn:fcode":"PPL",
    "gn:population":2379,
    "iso:country":"PR",
    "qs_pg:aaroncc":"PR",
    "qs_pg:gn_country":"PR",
    "qs_pg:gn_fcode":"PPL",
    "qs_pg:gn_pop":2379,
    "qs_pg:name":"H. Rivera Colin",
    "qs_pg:name_adm0":"Puerto Rico",
    "qs_pg:name_adm1":"Toa Alta",
    "qs_pg:photos_9r":0,
    "qs_pg:photos_sr":0,
    "qs_pg:pop_sr":4,
    "qs_pg:qs_pg_placetype":"locality",
    "qs_pg:qs_pg_placetype_gp":"Town",
    "qs_pg:woe_adm0":23424935,
    "woe:adm0_id":23424935,
    "woe:name_adm0":"Puerto Rico",
    "woe:name_adm1":"Toa Alta",
    "woe:placetype":"Town",
    "wof:name":"H. Rivera Colin",
    "wof:placetype":"locality",
    "wof:population":2379
},
  "geometry": {"coordinates":[-66.27378,18.34773],"type":"Point"}
}