{
  "type": "Feature",
  "properties": {
    "gn:admin1_code":"043",
    "gn:admin2_code":"7268577",
    "gn:asciiname":"Los Puertos",
    "gn:country_code":"PR",
    "gn:dem":118,
    "gn:elevation":"118.0",
    "gn:feature_class":"P",
    "gn:feature_code":"PPL",
    "gn:name":"Los Puertos",
    "gn:population":0,
    "gn:timezone":"America/Puerto_Rico",
    "iso:country":"PR",
    "wof:name":"Los Puertos",
    "wof:placetype":"locality"
},
  "geometry": {"coordinates":[-66.39489,18.04163],"type":"Point"}
}