{
  "type": "Feature",
  "properties": {
    "gn:admin1_code":"009",
    "gn:admin2_code":"7268566",
    "gn:asciiname":"Santa Ana",
    "gn:country_code":"PR",
    "gn:dem":630,
    "gn:elevation":"630.0",
    "gn:feature_class":"P",
    "gn:feature_code":"PPL",
    "gn:name":"Santa Ana",
    "gn:population":0,
    "gn:timezone":"America/Puerto_Rico",
    "iso:country":"PR",
    "wof:name":"Santa Ana",
    "wof:placetype":"locality"
},
  "geometry": {"coordinates":[-66.26822,18.14607],"type":"Point"}
}