{
  "type": "Feature",
  "properties": {
    "gn:country":"PR",
    "gn:elevation":2,
    "gn:fcode":"PPL",
    "gn:population":0,
    "iso:country":"PR",
    "name:deu_x_preferred":[
        "Mart\u00edn Pe\u00f1a"
    ],
    "name:spa_x_preferred":[
        "Martin Pena"
    ],
    "qs_pg:aaroncc":"PR",
    "qs_pg:gn_country":"PR",
    "qs_pg:gn_fcode":"PPL",
    "qs_pg:gn_pop":0,
    "qs_pg:name":"Martin Pena",
    "qs_pg:name_adm0":"Puerto Rico",
    "qs_pg:name_adm1":"San Juan",
    "qs_pg:photos":39,
    "qs_pg:photos_1k":8,
    "qs_pg:photos_9k":1,
    "qs_pg:photos_9r":2,
    "qs_pg:photos_all":39,
    "qs_pg:photos_sr":2,
    "qs_pg:pop_sr":0,
    "qs_pg:qs_pg_placetype":"neighbourhood",
    "qs_pg:qs_pg_placetype_gp":"Suburb",
    "qs_pg:woe_adm0":23424935,
    "woe:adm0_id":23424935,
    "woe:name_adm0":"Puerto Rico",
    "woe:name_adm1":"San Juan",
    "woe:placetype":"Suburb",
    "wof:name":"Martin Pena",
    "wof:placetype":"neighbourhood"
},
  "geometry": {"coordinates":[-66.05267000000001,18.42717],"type":"Point"}
}