{
  "type": "Feature",
  "properties": {
    "gn:admin1_code":"035",
    "gn:admin2_code":"7269072",
    "gn:asciiname":"Vegas",
    "gn:country_code":"PR",
    "gn:dem":392,
    "gn:elevation":"397.0",
    "gn:feature_class":"P",
    "gn:feature_code":"PPL",
    "gn:name":"Vegas",
    "gn:population":0,
    "gn:timezone":"America/Puerto_Rico",
    "iso:country":"PR",
    "wof:name":"Vegas",
    "wof:placetype":"locality"
},
  "geometry": {"coordinates":[-66.10961,18.12857],"type":"Point"}
}