{
  "type": "Feature",
  "properties": {
    "gn:admin1_code":"069",
    "gn:admin2_code":"7268579",
    "gn:asciiname":"San Antonio",
    "gn:country_code":"PR",
    "gn:dem":36,
    "gn:elevation":"29.0",
    "gn:feature_class":"P",
    "gn:feature_code":"PPL",
    "gn:name":"San Antonio",
    "gn:population":0,
    "gn:timezone":"America/Puerto_Rico",
    "iso:country":"PR",
    "wof:name":"San Antonio",
    "wof:placetype":"locality"
},
  "geometry": {"coordinates":[-65.82266,18.15746],"type":"Point"}
}