{
  "type": "Feature",
  "properties": {
    "gn:admin1_code":"087",
    "gn:admin2_code":"7268648",
    "gn:asciiname":"Palmarenas",
    "gn:country_code":"PR",
    "gn:dem":3,
    "gn:elevation":"3.0",
    "gn:feature_class":"P",
    "gn:feature_code":"PPL",
    "gn:name":"Palmarenas",
    "gn:population":0,
    "gn:timezone":"America/Puerto_Rico",
    "iso:country":"PR",
    "wof:name":"Palmarenas",
    "wof:placetype":"locality"
},
  "geometry": {"coordinates":[-65.87515999999999,18.42856],"type":"Point"}
}