{
  "type": "Feature",
  "properties": {
    "gn:admin1_code":"011",
    "gn:admin2_code":"7268451",
    "gn:asciiname":"Hacienda Eugenia",
    "gn:country_code":"PR",
    "gn:dem":9,
    "gn:elevation":"5.0",
    "gn:feature_class":"P",
    "gn:feature_code":"PPL",
    "gn:name":"Hacienda Eugenia",
    "gn:population":0,
    "gn:timezone":"America/Puerto_Rico",
    "iso:country":"PR",
    "wof:name":"Hacienda Eugenia",
    "wof:placetype":"locality"
},
  "geometry": {"coordinates":[-67.18768,18.29773],"type":"Point"}
}