{
  "type": "Feature",
  "properties": {
    "gn:admin1_code":"083",
    "gn:admin2_code":"7268201",
    "gn:asciiname":"Hacienda Casey",
    "gn:country_code":"PR",
    "gn:dem":111,
    "gn:elevation":"104.0",
    "gn:feature_class":"P",
    "gn:feature_code":"PPL",
    "gn:name":"Hacienda Casey",
    "gn:population":0,
    "gn:timezone":"America/Puerto_Rico",
    "iso:country":"PR",
    "wof:name":"Hacienda Casey",
    "wof:placetype":"locality"
},
  "geometry": {"coordinates":[-67.07601,18.25023],"type":"Point"}
}