{
  "type": "Feature",
  "properties": {
    "gn:admin1_code":"111",
    "gn:admin2_code":"7268850",
    "gn:asciiname":"Comunidad Caracoles",
    "gn:country_code":"PR",
    "gn:dem":52,
    "gn:elevation":"49.0",
    "gn:feature_class":"P",
    "gn:feature_code":"PPL",
    "gn:name":"Comunidad Caracoles",
    "gn:population":0,
    "gn:timezone":"America/Puerto_Rico",
    "iso:country":"PR",
    "wof:name":"Comunidad Caracoles",
    "wof:placetype":"locality"
},
  "geometry": {"coordinates":[-66.71184000000001,18.0533],"type":"Point"}
}