{
  "type": "Feature",
  "properties": {
    "gn:admin1_code":"085",
    "gn:admin2_code":"7269030",
    "gn:asciiname":"Las Mercedes",
    "gn:country_code":"PR",
    "gn:dem":122,
    "gn:elevation":"121.0",
    "gn:feature_class":"P",
    "gn:feature_code":"PPL",
    "gn:name":"Las Mercedes",
    "gn:population":0,
    "gn:timezone":"America/Puerto_Rico",
    "iso:country":"PR",
    "wof:name":"Las Mercedes",
    "wof:placetype":"locality"
},
  "geometry": {"coordinates":[-65.86711,18.17524],"type":"Point"}
}