{
  "type": "Feature",
  "properties": {
    "gn:gn_country":"PR",
    "gn:gn_fcode":"PPL",
    "gn:gn_pop":0,
    "iso:country":"PR",
    "name:ceb_x_preferred":[
        "Mercedita"
    ],
    "name:swe_x_preferred":[
        "Mercedita"
    ],
    "qs_pg:aaroncc":"PR",
    "qs_pg:gn_country":"PR",
    "qs_pg:gn_fcode":"PPL",
    "qs_pg:gn_pop":0,
    "qs_pg:name":"Mercedita",
    "qs_pg:name_adm0":"Puerto Rico",
    "qs_pg:name_adm1":"Ponce",
    "qs_pg:photos":83,
    "qs_pg:photos_1k":17,
    "qs_pg:photos_9k":1,
    "qs_pg:photos_9r":3,
    "qs_pg:photos_all":83,
    "qs_pg:photos_sr":3,
    "qs_pg:pop_sr":0,
    "qs_pg:qs_pg_placetype":"locality",
    "qs_pg:qs_pg_placetype_gp":"Town",
    "qs_pg:woe_adm0":23424935,
    "woe:adm0_id":23424935,
    "woe:name_adm0":"Puerto Rico",
    "woe:name_adm1":"Ponce",
    "woe:placetype":"Town",
    "wof:name":"Mercedita",
    "wof:placetype":"locality"
},
  "geometry": {"coordinates":[-66.56316,18.01098],"type":"Point"}
}