{
  "type": "Feature",
  "properties": {
    "gn:admin1_code":"131",
    "gn:admin2_code":"7268220",
    "gn:asciiname":"Pedro Tomas La Valle",
    "gn:country_code":"PR",
    "gn:dem":73,
    "gn:elevation":"73.0",
    "gn:feature_class":"P",
    "gn:feature_code":"PPL",
    "gn:name":"Pedro Tomas La Valle",
    "gn:population":0,
    "gn:timezone":"America/Puerto_Rico",
    "iso:country":"PR",
    "wof:name":"Pedro Tomas La Valle",
    "wof:placetype":"locality"
},
  "geometry": {"coordinates":[-66.99351,18.33884],"type":"Point"}
}