{
  "type": "Feature",
  "properties": {
    "gn:admin1_code":"123",
    "gn:admin2_code":"7268912",
    "gn:asciiname":"Las Ochenta Comunidad",
    "gn:country_code":"PR",
    "gn:dem":8,
    "gn:elevation":"7.0",
    "gn:feature_class":"P",
    "gn:feature_code":"PPL",
    "gn:name":"Las Ochenta Comunidad",
    "gn:population":0,
    "gn:timezone":"America/Puerto_Rico",
    "iso:country":"PR",
    "wof:name":"Las Ochenta Comunidad",
    "wof:placetype":"locality"
},
  "geometry": {"coordinates":[-66.31737,17.98411],"type":"Point"}
}