{
  "type": "Feature",
  "properties": {
    "gn:admin1_code":"147",
    "gn:admin2_code":"7268825",
    "gn:asciiname":"Santa Maria",
    "gn:country_code":"PR",
    "gn:dem":21,
    "gn:elevation":"29.0",
    "gn:feature_class":"P",
    "gn:feature_code":"PPL",
    "gn:name":"Santa Mar\u00eda",
    "gn:population":0,
    "gn:timezone":"America/Puerto_Rico",
    "iso:country":"PR",
    "wof:name":"Santa Maria",
    "wof:placetype":"locality"
},
  "geometry": {"coordinates":[-65.43210000000001,18.15218],"type":"Point"}
}