{
  "type": "Feature",
  "properties": {
    "gn:admin1_code":"143",
    "gn:admin2_code":"7268383",
    "gn:asciiname":"Comunidad La Ponderosa",
    "gn:country_code":"PR",
    "gn:dem":29,
    "gn:elevation":"30.0",
    "gn:feature_class":"P",
    "gn:feature_code":"PPL",
    "gn:name":"Comunidad La Ponderosa",
    "gn:population":0,
    "gn:timezone":"America/Puerto_Rico",
    "iso:country":"PR",
    "wof:name":"Comunidad La Ponderosa",
    "wof:placetype":"locality"
},
  "geometry": {"coordinates":[-66.32489,18.41661],"type":"Point"}
}