{
  "type": "Feature",
  "properties": {
    "gn:gn_country":"PR",
    "gn:gn_fcode":"PPL",
    "gn:gn_pop":0,
    "iso:country":"PR",
    "qs_pg:aaroncc":"PR",
    "qs_pg:gn_country":"PR",
    "qs_pg:gn_fcode":"PPL",
    "qs_pg:gn_pop":0,
    "qs_pg:name":"Villa Nevarez",
    "qs_pg:name_adm0":"Puerto Rico",
    "qs_pg:name_adm1":"San Juan",
    "qs_pg:photos":2,
    "qs_pg:photos_1k":1,
    "qs_pg:photos_9k":1,
    "qs_pg:photos_9r":1,
    "qs_pg:photos_all":2,
    "qs_pg:photos_sr":1,
    "qs_pg:pop_sr":0,
    "qs_pg:qs_pg_placetype":"neighbourhood",
    "qs_pg:qs_pg_placetype_gp":"Suburb",
    "qs_pg:woe_adm0":23424935,
    "woe:adm0_id":23424935,
    "woe:name_adm0":"Puerto Rico",
    "woe:name_adm1":"San Juan",
    "woe:placetype":"Suburb",
    "wof:name":"Villa Nevarez",
    "wof:placetype":"neighbourhood"
},
  "geometry": {"coordinates":[-66.06932999999999,18.39189],"type":"Point"}
}