{
  "type": "Feature",
  "properties": {
    "gn:admin1_code":"065",
    "gn:admin2_code":"7268693",
    "gn:asciiname":"Paloma",
    "gn:country_code":"PR",
    "gn:dem":130,
    "gn:elevation":"125.0",
    "gn:feature_class":"P",
    "gn:feature_code":"PPL",
    "gn:name":"Paloma",
    "gn:population":0,
    "gn:timezone":"America/Puerto_Rico",
    "iso:country":"PR",
    "name:bre_x_preferred":[
        "Paloma"
    ],
    "name:ceb_x_preferred":[
        "Paloma"
    ],
    "name:deu_x_preferred":[
        "Paloma"
    ],
    "name:fra_x_preferred":[
        "Paloma"
    ],
    "name:hun_x_preferred":[
        "Paloma"
    ],
    "name:ita_x_preferred":[
        "Paloma"
    ],
    "name:jpn_x_preferred":[
        "\u30d1\u30ed\u30de"
    ],
    "name:kor_x_preferred":[
        "\ud314\ub85c\ub9c8"
    ],
    "name:por_x_preferred":[
        "Paloma"
    ],
    "name:rus_x_preferred":[
        "\u041f\u0430\u043b\u043e\u043c\u0430"
    ],
    "name:spa_x_preferred":[
        "Paloma"
    ],
    "name:swe_x_preferred":[
        "Paloma"
    ],
    "name:ukr_x_preferred":[
        "\u041f\u0430\u043b\u043e\u043c\u0430"
    ],
    "name:vol_x_preferred":[
        "Paloma"
    ],
    "wof:name":"Paloma",
    "wof:placetype":"locality"
},
  "geometry": {"coordinates":[-66.80462,18.43661],"type":"Point"}
}