{
  "type": "Feature",
  "properties": {
    "gn:admin1_code":"065",
    "gn:admin2_code":"7268693",
    "gn:asciiname":"Paloma",
    "gn:country_code":"PR",
    "gn:dem":130,
    "gn:elevation":"125.0",
    "gn:feature_class":"P",
    "gn:feature_code":"PPL",
    "gn:name":"Paloma",
    "gn:population":0,
    "gn:timezone":"America/Puerto_Rico",
    "iso:country":"PR",
    "wof:name":"Paloma",
    "wof:placetype":"locality"
},
  "geometry": {"coordinates":[-66.80462,18.43661],"type":"Point"}
}