{
  "type": "Feature",
  "properties": {
    "gn:admin1_code":"031",
    "gn:admin2_code":"7268484",
    "gn:asciiname":"Villa Carolina",
    "gn:country_code":"PR",
    "gn:dem":5,
    "gn:elevation":"3.0",
    "gn:feature_class":"P",
    "gn:feature_code":"PPL",
    "gn:name":"Villa Carolina",
    "gn:population":0,
    "gn:timezone":"America/Puerto_Rico",
    "iso:country":"PR",
    "wof:name":"Villa Carolina",
    "wof:placetype":"locality"
},
  "geometry": {"coordinates":[-65.96211,18.39773],"type":"Point"}
}