{
  "type": "Feature",
  "properties": {
    "gn:admin1_code":"113",
    "gn:admin2_code":"7269035",
    "gn:asciiname":"Hacienda Molina",
    "gn:country_code":"PR",
    "gn:dem":427,
    "gn:elevation":"432.0",
    "gn:feature_class":"P",
    "gn:feature_code":"PPL",
    "gn:name":"Hacienda Molina",
    "gn:population":0,
    "gn:timezone":"America/Puerto_Rico",
    "iso:country":"PR",
    "wof:name":"Hacienda Molina",
    "wof:placetype":"locality"
},
  "geometry": {"coordinates":[-66.63434000000001,18.09468],"type":"Point"}
}