{
  "type": "Feature",
  "properties": {
    "gn:admin1_code":"005",
    "gn:admin2_code":"7268171",
    "gn:asciiname":"Tamarindo",
    "gn:country_code":"PR",
    "gn:dem":13,
    "gn:elevation":"5.0",
    "gn:feature_class":"P",
    "gn:feature_code":"PPL",
    "gn:name":"Tamarindo",
    "gn:population":0,
    "gn:timezone":"America/Puerto_Rico",
    "iso:country":"PR",
    "wof:name":"Tamarindo",
    "wof:placetype":"locality"
},
  "geometry": {"coordinates":[-67.15518,18.4355],"type":"Point"}
}