{
  "type": "Feature",
  "properties": {
    "gn:admin1_code":"153",
    "gn:admin2_code":"7268172",
    "gn:asciiname":"Hacienda Pietri",
    "gn:country_code":"PR",
    "gn:dem":475,
    "gn:elevation":"462.0",
    "gn:feature_class":"P",
    "gn:feature_code":"PPL",
    "gn:name":"Hacienda Pietri",
    "gn:population":0,
    "gn:timezone":"America/Puerto_Rico",
    "iso:country":"PR",
    "wof:name":"Hacienda Pietri",
    "wof:placetype":"locality"
},
  "geometry": {"coordinates":[-66.83851,18.11635],"type":"Point"}
}