{
  "type": "Feature",
  "properties": {
    "gn:admin1_code":"067",
    "gn:admin2_code":"7268420",
    "gn:asciiname":"Guanaiibo",
    "gn:country_code":"PR",
    "gn:dem":41,
    "gn:elevation":"35.0",
    "gn:feature_class":"P",
    "gn:feature_code":"PPL",
    "gn:name":"Guanaiibo",
    "gn:population":0,
    "gn:timezone":"America/Puerto_Rico",
    "iso:country":"PR",
    "wof:name":"Guanaiibo",
    "wof:placetype":"locality"
},
  "geometry": {"coordinates":[-67.13768,18.14329],"type":"Point"}
}