{
  "type": "Feature",
  "properties": {
    "gn:admin1_code":"017",
    "gn:admin2_code":"7268394",
    "gn:asciiname":"Cruce Davila",
    "gn:country_code":"PR",
    "gn:dem":83,
    "gn:elevation":"79.0",
    "gn:feature_class":"P",
    "gn:feature_code":"PPL",
    "gn:name":"Cruce D\u00e1vila",
    "gn:population":0,
    "gn:timezone":"America/Puerto_Rico",
    "iso:country":"PR",
    "wof:name":"Cruce Davila",
    "wof:placetype":"locality"
},
  "geometry": {"coordinates":[-66.56545,18.43078],"type":"Point"}
}