{
  "type": "Feature",
  "properties": {
    "gn:admin1_code":"037",
    "gn:admin2_code":"7268054",
    "gn:asciiname":"Jardines de Ceiba I",
    "gn:country_code":"PR",
    "gn:dem":33,
    "gn:elevation":"32.0",
    "gn:feature_class":"P",
    "gn:feature_code":"PPL",
    "gn:name":"Jardines de Ceiba I",
    "gn:population":0,
    "gn:timezone":"America/Puerto_Rico",
    "iso:country":"PR",
    "wof:name":"Jardines de Ceiba I",
    "wof:placetype":"locality"
},
  "geometry": {"coordinates":[-65.65100000000001,18.25996],"type":"Point"}
}