{
  "type": "Feature",
  "properties": {
    "gn:admin1_code":"085",
    "gn:admin2_code":"7268840",
    "gn:asciiname":"Reparto Arenales",
    "gn:country_code":"PR",
    "gn:dem":126,
    "gn:elevation":"121.0",
    "gn:feature_class":"P",
    "gn:feature_code":"PPL",
    "gn:name":"Reparto Arenales",
    "gn:population":0,
    "gn:timezone":"America/Puerto_Rico",
    "iso:country":"PR",
    "wof:name":"Reparto Arenales",
    "wof:placetype":"locality"
},
  "geometry": {"coordinates":[-65.87016,18.18551],"type":"Point"}
}