{
  "type": "Feature",
  "properties": {
    "gn:admin1_code":"053",
    "gn:admin2_code":"7268891",
    "gn:asciiname":"Saldana",
    "gn:country_code":"PR",
    "gn:dem":91,
    "gn:elevation":"85.0",
    "gn:feature_class":"P",
    "gn:feature_code":"PPL",
    "gn:name":"Salda\u00f1a",
    "gn:population":0,
    "gn:timezone":"America/Puerto_Rico",
    "iso:country":"PR",
    "wof:name":"Saldana",
    "wof:placetype":"locality"
},
  "geometry": {"coordinates":[-65.70488,18.29107],"type":"Point"}
}