{
  "type": "Feature",
  "properties": {
    "gn:admin1_code":"139",
    "gn:admin2_code":"7268133",
    "gn:asciiname":"Rincon Espanol",
    "gn:country_code":"PR",
    "gn:dem":57,
    "gn:elevation":"50.0",
    "gn:feature_class":"P",
    "gn:feature_code":"PPL",
    "gn:name":"Rincon Espanol",
    "gn:population":0,
    "gn:timezone":"America/Puerto_Rico",
    "iso:country":"PR",
    "wof:name":"Rincon Espanol",
    "wof:placetype":"locality"
},
  "geometry": {"coordinates":[-66.01904999999999,18.35578],"type":"Point"}
}