{
  "type": "Feature",
  "properties": {
    "gn:country":"PR",
    "iso:country":"PR",
    "name:ceb_x_preferred":[
        "R\u00edo Grande Barrio"
    ],
    "name:eng_x_preferred":[
        "R\u00edo Grande"
    ],
    "name:fra_x_preferred":[
        "R\u00edo Grande"
    ],
    "name:nld_x_preferred":[
        "R\u00edo Grande"
    ],
    "name:spa_x_preferred":[
        "R\u00edo Grande"
    ],
    "qs_pg:aaroncc":"PR",
    "qs_pg:gn_country":"PR",
    "qs_pg:name":"R\u00edo Grande",
    "qs_pg:name_adm0":"Puerto Rico",
    "qs_pg:name_adm1":"Aguada",
    "qs_pg:photos":74,
    "qs_pg:photos_1k":15,
    "qs_pg:photos_9k":1,
    "qs_pg:photos_9r":2,
    "qs_pg:photos_all":74,
    "qs_pg:photos_sr":2,
    "qs_pg:pop_sr":0,
    "qs_pg:qs_pg_placetype":"locality",
    "qs_pg:qs_pg_placetype_gp":"Town",
    "qs_pg:woe_adm0":23424935,
    "woe:adm0_id":23424935,
    "woe:name_adm0":"Puerto Rico",
    "woe:name_adm1":"Aguada",
    "woe:placetype":"Town",
    "wof:name":"R\u00edo Grande",
    "wof:placetype":"locality"
},
  "geometry": {"coordinates":[-67.253601,18.37183],"type":"Point"}
}