{
  "type": "Feature",
  "properties": {
    "gn:admin1_code":"087",
    "gn:asciiname":"Jose S Quinones",
    "gn:country_code":"PR",
    "gn:dem":12,
    "gn:elevation":"12.0",
    "gn:feature_class":"P",
    "gn:feature_code":"PPL",
    "gn:name":"Jose S Quinones",
    "gn:population":0,
    "gn:timezone":"America/Puerto_Rico",
    "iso:country":"PR",
    "wof:name":"Jose S Quinones",
    "wof:placetype":"locality"
},
  "geometry": {"coordinates":[-65.96155,18.38495],"type":"Point"}
}