{
  "type": "Feature",
  "properties": {
    "gn:admin1_code":"089",
    "gn:admin2_code":"7268763",
    "gn:asciiname":"Pitahaya",
    "gn:country_code":"PR",
    "gn:dem":33,
    "gn:elevation":"35.0",
    "gn:feature_class":"P",
    "gn:feature_code":"PPL",
    "gn:name":"Pitahaya",
    "gn:population":0,
    "gn:timezone":"America/Puerto_Rico",
    "iso:country":"PR",
    "wof:name":"Pitahaya",
    "wof:placetype":"locality"
},
  "geometry": {"coordinates":[-65.71655,18.34217],"type":"Point"}
}