{
  "type": "Feature",
  "properties": {
    "gn:admin1_code":"131",
    "gn:admin2_code":"7268749",
    "gn:asciiname":"Hacienda San Pedro",
    "gn:country_code":"PR",
    "gn:dem":233,
    "gn:elevation":"240.0",
    "gn:feature_class":"P",
    "gn:feature_code":"PPL",
    "gn:name":"Hacienda San Pedro",
    "gn:population":0,
    "gn:timezone":"America/Puerto_Rico",
    "iso:country":"PR",
    "name:spa_x_preferred":[
        "Hacienda San Pedro"
    ],
    "wof:name":"Hacienda San Pedro",
    "wof:placetype":"locality"
},
  "geometry": {"coordinates":[-66.93351,18.27301],"type":"Point"}
}