{
  "type": "Feature",
  "properties": {
    "gn:admin1_code":"067",
    "gn:admin2_code":"7268556",
    "gn:asciiname":"Lavadero",
    "gn:country_code":"PR",
    "gn:dem":39,
    "gn:elevation":"27.0",
    "gn:feature_class":"P",
    "gn:feature_code":"PPL",
    "gn:name":"Lavadero",
    "gn:population":0,
    "gn:timezone":"America/Puerto_Rico",
    "iso:country":"PR",
    "name:spa_x_preferred":[
        "Lavadero"
    ],
    "wof:name":"Lavadero",
    "wof:placetype":"locality"
},
  "geometry": {"coordinates":[-67.09990000000001,18.12996],"type":"Point"}
}