{
  "type": "Feature",
  "properties": {
    "gn:admin1_code":"015",
    "gn:admin2_code":"7268430",
    "gn:asciiname":"La Riviera",
    "gn:country_code":"PR",
    "gn:dem":5,
    "gn:elevation":"3.0",
    "gn:feature_class":"P",
    "gn:feature_code":"PPL",
    "gn:name":"La Riviera",
    "gn:population":0,
    "gn:timezone":"America/Puerto_Rico",
    "iso:country":"PR",
    "wof:name":"La Riviera",
    "wof:placetype":"locality"
},
  "geometry": {"coordinates":[-66.06544,17.96523999999999],"type":"Point"}
}