{
  "type": "Feature",
  "properties": {
    "gn:gn_country":"PR",
    "gn:gn_fcode":"PPL",
    "gn:gn_pop":8437,
    "gn:population":8437,
    "iso:country":"PR",
    "name:bpy_x_preferred":[
        "\u0995\u09be\u09a8\u09cb\u09ad\u09be\u09a8\u09be\u09b8"
    ],
    "name:cat_x_preferred":[
        "Can\u00f3vanas"
    ],
    "name:ceb_x_preferred":[
        "Canovanas"
    ],
    "name:eng_x_preferred":[
        "Can\u00f3vanas"
    ],
    "name:fra_x_preferred":[
        "Can\u00f3vanas"
    ],
    "name:ita_x_preferred":[
        "Can\u00f3vanas"
    ],
    "name:jpn_x_preferred":[
        "\u30ab\u30ce\u30d0\u30ca\u30b9"
    ],
    "name:nld_x_preferred":[
        "Can\u00f3vanas"
    ],
    "name:pol_x_preferred":[
        "Can\u00f3vanas"
    ],
    "name:por_x_preferred":[
        "Can\u00f3vanas"
    ],
    "name:rus_x_preferred":[
        "\u041a\u0430\u043d\u043e\u0432\u0430\u043d\u0430\u0441"
    ],
    "name:spa_x_preferred":[
        "Can\u00f3vanas"
    ],
    "name:srp_x_preferred":[
        "\u041a\u0430\u043d\u043e\u0432\u0430\u043d\u0430\u0441"
    ],
    "name:ukr_x_preferred":[
        "\u041a\u0430\u043d\u043e\u0432\u0430\u043d\u0430\u0441"
    ],
    "name:urd_x_preferred":[
        "\u06a9\u0627\u0646\u0648\u0628\u0627\u0646\u0627\u0633\u060c \u067e\u0648\u0631\u0679\u0648 \u0631\u06cc\u06a9\u0648"
    ],
    "name:urd_x_variant":[
        "\u06a9\u0627\u0646\u0648\u0628\u0627\u0646\u0627\u0633"
    ],
    "name:war_x_preferred":[
        "Canovanas"
    ],
    "name:zho_x_preferred":[
        "\u5361\u8afe\u74e6\u8afe\u65af"
    ],
    "qs_pg:aaroncc":"PR",
    "qs_pg:gn_country":"PR",
    "qs_pg:gn_fcode":"PPL",
    "qs_pg:gn_pop":8437,
    "qs_pg:name":"Canovanas",
    "qs_pg:name_adm0":"Puerto Rico",
    "qs_pg:name_adm1":"Can\u00f3vanas",
    "qs_pg:photos":91,
    "qs_pg:photos_1k":18,
    "qs_pg:photos_9k":1,
    "qs_pg:photos_9r":0,
    "qs_pg:photos_all":91,
    "qs_pg:photos_sr":0,
    "qs_pg:pop_sr":5,
    "qs_pg:qs_pg_placetype":"locality",
    "qs_pg:qs_pg_placetype_gp":"Town",
    "qs_pg:woe_adm0":23424935,
    "wof:name":"Canovanas",
    "wof:placetype":"locality",
    "wof:population":8437
},
  "geometry": {"coordinates":[-65.90628,18.37773],"type":"Point"}
}