{
  "type": "Feature",
  "properties": {
    "gn:admin1_code":"059",
    "gn:admin2_code":"7268504",
    "gn:asciiname":"Hacienda Catalina",
    "gn:country_code":"PR",
    "gn:dem":273,
    "gn:elevation":"269.0",
    "gn:feature_class":"P",
    "gn:feature_code":"PPL",
    "gn:name":"Hacienda Catalina",
    "gn:population":0,
    "gn:timezone":"America/Puerto_Rico",
    "iso:country":"PR",
    "wof:name":"Hacienda Catalina",
    "wof:placetype":"locality"
},
  "geometry": {"coordinates":[-66.79351,18.09468],"type":"Point"}
}