{
  "type": "Feature",
  "properties": {
    "gn:admin1_code":"139",
    "gn:admin2_code":"7268156",
    "gn:asciiname":"La Antigua",
    "gn:country_code":"PR",
    "gn:dem":26,
    "gn:elevation":"18.0",
    "gn:feature_class":"P",
    "gn:feature_code":"PPL",
    "gn:name":"La Antigua",
    "gn:population":0,
    "gn:timezone":"America/Puerto_Rico",
    "iso:country":"PR",
    "name:ceb_x_preferred":[
        "La Antigua"
    ],
    "name:deu_x_preferred":[
        "La Antigua"
    ],
    "name:swe_x_preferred":[
        "La Antigua"
    ],
    "wof:name":"La Antigua",
    "wof:placetype":"locality"
},
  "geometry": {"coordinates":[-65.98961,18.34523],"type":"Point"}
}