{
  "type": "Feature",
  "properties": {
    "gn:admin1_code":"113",
    "gn:admin2_code":"7268949",
    "gn:asciiname":"Hacienda Cano Verde",
    "gn:country_code":"PR",
    "gn:dem":37,
    "gn:elevation":"30.0",
    "gn:feature_class":"P",
    "gn:feature_code":"PPL",
    "gn:name":"Hacienda Ca\u00f1o Verde",
    "gn:population":0,
    "gn:timezone":"America/Puerto_Rico",
    "iso:country":"PR",
    "wof:name":"Hacienda Cano Verde",
    "wof:placetype":"locality"
},
  "geometry": {"coordinates":[-66.58462,18.01469],"type":"Point"}
}