{
  "type": "Feature",
  "properties": {
    "gn:admin1_code":"017",
    "gn:asciiname":"Sector Las Parcelas",
    "gn:country_code":"PR",
    "gn:dem":243,
    "gn:elevation":"264.0",
    "gn:feature_class":"P",
    "gn:feature_code":"PPL",
    "gn:name":"Sector Las Parcelas",
    "gn:population":0,
    "gn:timezone":"America/Puerto_Rico",
    "iso:country":"PR",
    "wof:name":"Sector Las Parcelas",
    "wof:placetype":"locality"
},
  "geometry": {"coordinates":[-66.54850999999999,18.35912],"type":"Point"}
}