{
  "type": "Feature",
  "properties": {
    "gn:admin1_code":"031",
    "gn:admin2_code":"7268934",
    "gn:asciiname":"Vista Mar Marina Oeste",
    "gn:country_code":"PR",
    "gn:dem":4,
    "gn:elevation":"0.0",
    "gn:feature_class":"P",
    "gn:feature_code":"PPL",
    "gn:name":"Vista Mar Marina Oeste",
    "gn:population":0,
    "gn:timezone":"America/Puerto_Rico",
    "iso:country":"PR",
    "wof:name":"Vista Mar Marina Oeste",
    "wof:placetype":"locality"
},
  "geometry": {"coordinates":[-65.98155,18.43495],"type":"Point"}
}