{
  "type": "Feature",
  "properties": {
    "gn:admin1_code":"005",
    "gn:admin2_code":"7268290",
    "gn:asciiname":"Monte Real",
    "gn:country_code":"PR",
    "gn:dem":37,
    "gn:elevation":"38.0",
    "gn:feature_class":"P",
    "gn:feature_code":"PPL",
    "gn:name":"Monte Real",
    "gn:population":0,
    "gn:timezone":"America/Puerto_Rico",
    "iso:country":"PR",
    "wof:name":"Monte Real",
    "wof:placetype":"locality"
},
  "geometry": {"coordinates":[-67.15129,18.43272],"type":"Point"}
}