{
  "type": "Feature",
  "properties": {
    "gn:admin1_code":"139",
    "gn:admin2_code":"7268133",
    "gn:asciiname":"Saint Just",
    "gn:country_code":"PR",
    "gn:dem":55,
    "gn:elevation":"58.0",
    "gn:feature_class":"P",
    "gn:feature_code":"PPL",
    "gn:name":"Saint Just",
    "gn:population":0,
    "gn:timezone":"America/Puerto_Rico",
    "iso:country":"PR",
    "wof:name":"Saint Just",
    "wof:placetype":"locality"
},
  "geometry": {"coordinates":[-66.01183,18.368],"type":"Point"}
}