{
  "type": "Feature",
  "properties": {
    "gn:admin1_code":"133",
    "gn:admin2_code":"7268387",
    "gn:asciiname":"Hacienda Alomar",
    "gn:country_code":"PR",
    "gn:dem":4,
    "gn:elevation":"7.0",
    "gn:feature_class":"P",
    "gn:feature_code":"PPL",
    "gn:name":"Hacienda Alomar",
    "gn:population":0,
    "gn:timezone":"America/Puerto_Rico",
    "iso:country":"PR",
    "wof:name":"Hacienda Alomar",
    "wof:placetype":"locality"
},
  "geometry": {"coordinates":[-66.39211,17.95802],"type":"Point"}
}