{
  "type": "Feature",
  "properties": {
    "gn:admin1_code":"127",
    "gn:admin2_code":"7268465",
    "gn:asciiname":"Santa Rita",
    "gn:country_code":"PR",
    "gn:dem":16,
    "gn:elevation":"13.0",
    "gn:feature_class":"P",
    "gn:feature_code":"PPL",
    "gn:name":"Santa Rita",
    "gn:population":0,
    "gn:timezone":"America/Puerto_Rico",
    "iso:country":"PR",
    "name:ceb_x_preferred":[
        "Santa Rita"
    ],
    "wof:name":"Santa Rita",
    "wof:placetype":"locality"
},
  "geometry": {"coordinates":[-66.05628,18.40245],"type":"Point"}
}