{
  "type": "Feature",
  "properties": {
    "gn:admin1_code":"145",
    "gn:admin2_code":"7268888",
    "gn:asciiname":"La Trocha",
    "gn:country_code":"PR",
    "gn:dem":42,
    "gn:elevation":"32.0",
    "gn:feature_class":"P",
    "gn:feature_code":"PPL",
    "gn:name":"La Trocha",
    "gn:population":0,
    "gn:timezone":"America/Puerto_Rico",
    "iso:country":"PR",
    "wof:name":"La Trocha",
    "wof:placetype":"locality"
},
  "geometry": {"coordinates":[-66.38155999999999,18.44106],"type":"Point"}
}