{
  "type": "Feature",
  "properties": {
    "gn:admin1_code":"021",
    "gn:admin2_code":"7268653",
    "gn:asciiname":"Lomas Verdes",
    "gn:country_code":"PR",
    "gn:dem":34,
    "gn:elevation":"33.0",
    "gn:feature_class":"P",
    "gn:feature_code":"PPL",
    "gn:name":"Lomas Verdes",
    "gn:population":0,
    "gn:timezone":"America/Puerto_Rico",
    "iso:country":"PR",
    "name:spa_x_preferred":[
        "Lomas Verdes"
    ],
    "wof:name":"Lomas Verdes",
    "wof:placetype":"locality"
},
  "geometry": {"coordinates":[-66.14933000000001,18.37467],"type":"Point"}
}