{
  "type": "Feature",
  "properties": {
    "gn:admin1_code":"089",
    "gn:admin2_code":"7268637",
    "gn:asciiname":"Luquillo Lomas",
    "gn:country_code":"PR",
    "gn:dem":35,
    "gn:elevation":"30.0",
    "gn:feature_class":"P",
    "gn:feature_code":"PPL",
    "gn:name":"Luquillo Lomas",
    "gn:population":0,
    "gn:timezone":"America/Puerto_Rico",
    "iso:country":"PR",
    "wof:name":"Luquillo Lomas",
    "wof:placetype":"locality"
},
  "geometry": {"coordinates":[-65.72627,18.3669],"type":"Point"}
}