{
  "type": "Feature",
  "properties": {
    "gn:admin1_code":"023",
    "gn:admin2_code":"7268568",
    "gn:asciiname":"Pole Ojea Comunidad",
    "gn:country_code":"PR",
    "gn:dem":12,
    "gn:elevation":"5.0",
    "gn:feature_class":"P",
    "gn:feature_code":"PPL",
    "gn:name":"Pole Ojea Comunidad",
    "gn:population":0,
    "gn:timezone":"America/Puerto_Rico",
    "iso:country":"PR",
    "wof:name":"Pole Ojea Comunidad",
    "wof:placetype":"locality"
},
  "geometry": {"coordinates":[-67.18321999999999,17.97429],"type":"Point"}
}