{
  "type": "Feature",
  "properties": {
    "gn:admin1_code":"097",
    "gn:admin2_code":"7268679",
    "gn:asciiname":"Hacienda Retiro",
    "gn:country_code":"PR",
    "gn:dem":376,
    "gn:elevation":"373.0",
    "gn:feature_class":"P",
    "gn:feature_code":"PPL",
    "gn:name":"Hacienda Retiro",
    "gn:population":0,
    "gn:timezone":"America/Puerto_Rico",
    "iso:country":"PR",
    "wof:name":"Hacienda Retiro",
    "wof:placetype":"locality"
},
  "geometry": {"coordinates":[-67.02101,18.19551],"type":"Point"}
}