{
  "type": "Feature",
  "properties": {
    "gn:admin1_code":"079",
    "gn:admin2_code":"7268317",
    "gn:asciiname":"Palmarejo Comunidad",
    "gn:country_code":"PR",
    "gn:dem":49,
    "gn:elevation":"43.0",
    "gn:feature_class":"P",
    "gn:feature_code":"PPL",
    "gn:name":"Palmarejo Comunidad",
    "gn:population":0,
    "gn:timezone":"America/Puerto_Rico",
    "iso:country":"PR",
    "wof:name":"Palmarejo Comunidad",
    "wof:placetype":"locality"
},
  "geometry": {"coordinates":[-67.07637,18.04117],"type":"Point"}
}