{
  "type": "Feature",
  "properties": {
    "gn:admin1_code":"077",
    "gn:admin2_code":"7268056",
    "gn:asciiname":"Jardines de Juncos",
    "gn:country_code":"PR",
    "gn:dem":143,
    "gn:elevation":"146.0",
    "gn:feature_class":"P",
    "gn:feature_code":"PPL",
    "gn:name":"Jardines de Juncos",
    "gn:population":0,
    "gn:timezone":"America/Puerto_Rico",
    "iso:country":"PR",
    "wof:name":"Jardines de Juncos",
    "wof:placetype":"locality"
},
  "geometry": {"coordinates":[-65.91377,18.21523],"type":"Point"}
}