{
  "type": "Feature",
  "properties": {
    "gn:admin1_code":"031",
    "gn:admin2_code":"7268934",
    "gn:asciiname":"Villa Vencia",
    "gn:country_code":"PR",
    "gn:dem":8,
    "gn:elevation":"3.0",
    "gn:feature_class":"P",
    "gn:feature_code":"PPL",
    "gn:name":"Villa Vencia",
    "gn:population":0,
    "gn:timezone":"America/Puerto_Rico",
    "iso:country":"PR",
    "wof:name":"Villa Vencia",
    "wof:placetype":"locality"
},
  "geometry": {"coordinates":[-65.98071999999999,18.43717],"type":"Point"}
}