{
  "type": "Feature",
  "properties": {
    "gn:admin1_code":"097",
    "gn:admin2_code":"7268933",
    "gn:asciiname":"San Miguel",
    "gn:country_code":"PR",
    "gn:dem":35,
    "gn:elevation":"35.0",
    "gn:feature_class":"P",
    "gn:feature_code":"PPL",
    "gn:name":"San Miguel",
    "gn:population":0,
    "gn:timezone":"America/Puerto_Rico",
    "iso:country":"PR",
    "wof:name":"San Miguel",
    "wof:placetype":"locality"
},
  "geometry": {"coordinates":[-67.14768000000001,18.18468],"type":"Point"}
}