{
  "type": "Feature",
  "properties": {
    "gn:admin1_code":"153",
    "gn:admin2_code":"7268233",
    "gn:asciiname":"Limas",
    "gn:country_code":"PR",
    "gn:dem":33,
    "gn:elevation":"16.0",
    "gn:feature_class":"P",
    "gn:feature_code":"PPL",
    "gn:name":"Limas",
    "gn:population":0,
    "gn:timezone":"America/Puerto_Rico",
    "iso:country":"PR",
    "wof:name":"Limas",
    "wof:placetype":"locality"
},
  "geometry": {"coordinates":[-66.83268000000001,18.00191000000001],"type":"Point"}
}