{
  "type": "Feature",
  "properties": {
    "gn:admin1_code":"153",
    "gn:admin2_code":"7268233",
    "gn:asciiname":"Limas",
    "gn:country_code":"PR",
    "gn:dem":33,
    "gn:elevation":"16.0",
    "gn:feature_class":"P",
    "gn:feature_code":"PPL",
    "gn:name":"Limas",
    "gn:population":0,
    "gn:timezone":"America/Puerto_Rico",
    "iso:country":"PR",
    "name:cat_x_preferred":[
        "Limas"
    ],
    "name:ceb_x_preferred":[
        "Limas"
    ],
    "name:deu_x_preferred":[
        "Limas"
    ],
    "name:eus_x_preferred":[
        "Limas"
    ],
    "name:fra_x_preferred":[
        "Limas"
    ],
    "name:hun_x_preferred":[
        "Limas"
    ],
    "name:ind_x_preferred":[
        "Limas"
    ],
    "name:ita_x_preferred":[
        "Limas"
    ],
    "name:lat_x_preferred":[
        "Limas"
    ],
    "name:lmo_x_preferred":[
        "Limas"
    ],
    "name:msa_x_preferred":[
        "Limas"
    ],
    "name:nld_x_preferred":[
        "Limas"
    ],
    "name:oci_x_preferred":[
        "Limas"
    ],
    "name:pms_x_preferred":[
        "Limas"
    ],
    "name:pol_x_preferred":[
        "Limas"
    ],
    "name:por_x_preferred":[
        "Limas"
    ],
    "name:ron_x_preferred":[
        "Limas"
    ],
    "name:slk_x_preferred":[
        "Limas"
    ],
    "name:spa_x_preferred":[
        "Limas"
    ],
    "name:swe_x_preferred":[
        "Limas"
    ],
    "name:ukr_x_preferred":[
        "\u041b\u0456\u043c\u0430"
    ],
    "name:uzb_x_preferred":[
        "Limas"
    ],
    "name:vol_x_preferred":[
        "Limas"
    ],
    "name:war_x_preferred":[
        "Limas"
    ],
    "wof:name":"Limas",
    "wof:placetype":"locality"
},
  "geometry": {"coordinates":[-66.83268000000001,18.00191000000001],"type":"Point"}
}