{
  "type": "Feature",
  "properties": {
    "gn:admin1_code":"061",
    "gn:admin2_code":"7268398",
    "gn:asciiname":"Residencial Los Alamos",
    "gn:country_code":"PR",
    "gn:dem":38,
    "gn:elevation":"30.0",
    "gn:feature_class":"P",
    "gn:feature_code":"PPL",
    "gn:name":"Residencial Los Alamos",
    "gn:population":0,
    "gn:timezone":"America/Puerto_Rico",
    "iso:country":"PR",
    "wof:name":"Residencial Los Alamos",
    "wof:placetype":"locality"
},
  "geometry": {"coordinates":[-66.10489,18.36301],"type":"Point"}
}