{
  "type": "Feature",
  "properties": {
    "gn:admin1_code":"073",
    "gn:admin2_code":"7268523",
    "gn:asciiname":"Residencial Mattei",
    "gn:country_code":"PR",
    "gn:dem":443,
    "gn:elevation":"436.0",
    "gn:feature_class":"P",
    "gn:feature_code":"PPL",
    "gn:name":"Residencial Mattei",
    "gn:population":0,
    "gn:timezone":"America/Puerto_Rico",
    "iso:country":"PR",
    "wof:name":"Residencial Mattei",
    "wof:placetype":"locality"
},
  "geometry": {"coordinates":[-66.58962,18.21968],"type":"Point"}
}