{
  "type": "Feature",
  "properties": {
    "gn:admin1_code":"075",
    "gn:admin2_code":"7268096",
    "gn:asciiname":"Hacienda Guayo",
    "gn:country_code":"PR",
    "gn:dem":254,
    "gn:elevation":"244.0",
    "gn:feature_class":"P",
    "gn:feature_code":"PPL",
    "gn:name":"Hacienda Guayo",
    "gn:population":0,
    "gn:timezone":"America/Puerto_Rico",
    "iso:country":"PR",
    "wof:name":"Hacienda Guayo",
    "wof:placetype":"locality"
},
  "geometry": {"coordinates":[-66.53350999999999,18.11191],"type":"Point"}
}