{
  "type": "Feature",
  "properties": {
    "gn:admin1_code":"031",
    "gn:admin2_code":"7268484",
    "gn:asciiname":"Monserrate",
    "gn:country_code":"PR",
    "gn:dem":8,
    "gn:elevation":"7.0",
    "gn:feature_class":"P",
    "gn:feature_code":"PPL",
    "gn:name":"Monserrate",
    "gn:population":0,
    "gn:timezone":"America/Puerto_Rico",
    "iso:country":"PR",
    "name:cat_x_preferred":[
        "Monserrate"
    ],
    "name:ceb_x_preferred":[
        "Monserrate"
    ],
    "name:deu_x_preferred":[
        "Monserrate"
    ],
    "name:epo_x_preferred":[
        "Monserrate"
    ],
    "name:glg_x_preferred":[
        "Monserrate"
    ],
    "name:ita_x_preferred":[
        "Monserrate"
    ],
    "name:nld_x_preferred":[
        "Monserrate"
    ],
    "name:nor_x_preferred":[
        "Monserrate"
    ],
    "name:spa_x_preferred":[
        "Monserrate"
    ],
    "name:swe_x_preferred":[
        "Monserrate"
    ],
    "name:und_x_variant":[
        "Colonia Monserrate"
    ],
    "wof:name":"Monserrate",
    "wof:placetype":"locality"
},
  "geometry": {"coordinates":[-65.94878,18.40495],"type":"Point"}
}