{
  "type": "Feature",
  "properties": {
    "gn:admin1_code":"009",
    "gn:asciiname":"Alamar",
    "gn:country_code":"PR",
    "gn:dem":7,
    "gn:elevation":"6.0",
    "gn:feature_class":"P",
    "gn:feature_code":"PPL",
    "gn:name":"Alamar",
    "gn:population":0,
    "gn:timezone":"America/Puerto_Rico",
    "iso:country":"PR",
    "name:ceb_x_preferred":[
        "Alamar"
    ],
    "name:spa_x_preferred":[
        "Alamar"
    ],
    "name:swe_x_preferred":[
        "Alamar"
    ],
    "wof:name":"Alamar",
    "wof:placetype":"locality"
},
  "geometry": {"coordinates":[-65.721,18.36523],"type":"Point"}
}