{
  "type": "Feature",
  "properties": {
    "gn:admin1_code":"139",
    "gn:admin2_code":"7268156",
    "gn:asciiname":"Corrientes",
    "gn:country_code":"PR",
    "gn:dem":73,
    "gn:elevation":"81.0",
    "gn:feature_class":"P",
    "gn:feature_code":"PPL",
    "gn:name":"Corrientes",
    "gn:population":0,
    "gn:timezone":"America/Puerto_Rico",
    "iso:country":"PR",
    "wof:name":"Corrientes",
    "wof:placetype":"locality"
},
  "geometry": {"coordinates":[-65.98239000000001,18.35273],"type":"Point"}
}