{
  "type": "Feature",
  "properties": {
    "gn:country":"PR",
    "gn:elevation":36,
    "gn:fcode":"PPL",
    "gn:population":0,
    "iso:country":"PR",
    "name:spa_x_preferred":[
        "La Riviera"
    ],
    "qs:gn_adm0_cc":"PR",
    "qs:gn_fcode":"PPL",
    "qs:gn_local":4568220,
    "qs:gn_nam_loc":"aguacate",
    "qs:gn_namadm1":"127",
    "qs:gn_name":"La Riviera",
    "qs:local_max":29505,
    "qs:local_sum":50313,
    "qs:localhoods":63,
    "qs:name":"La Riviera",
    "qs:name_adm0":"Puerto Rico",
    "qs:name_adm1":"San Juan",
    "qs:name_adm2":"Gobernador Pinero",
    "qs:name_local":"San Juan",
    "qs:photo_max":10,
    "qs:photo_sum":26,
    "qs:placetype":"Suburb",
    "qs:quad_count":5,
    "qs:woe_adm0":23424935,
    "qs:woe_adm1":2346815,
    "qs:woe_adm2":26806694,
    "qs:woe_lau":0,
    "qs:woe_local":161685,
    "qs:woe_ver":"7.10.0",
    "qs_pg:aaroncc":"PR",
    "qs_pg:gn_country":"PR",
    "qs_pg:gn_fcode":"PPL",
    "qs_pg:gn_pop":0,
    "qs_pg:name":"La Riviera",
    "qs_pg:name_adm0":"Puerto Rico",
    "qs_pg:name_adm1":"San Juan",
    "qs_pg:photos":8,
    "qs_pg:photos_1k":2,
    "qs_pg:photos_9k":1,
    "qs_pg:photos_9r":1,
    "qs_pg:photos_all":8,
    "qs_pg:photos_sr":1,
    "qs_pg:pop_sr":0,
    "qs_pg:qs_pg_placetype":"neighbourhood",
    "qs_pg:qs_pg_placetype_gp":"Suburb",
    "qs_pg:woe_adm0":23424935,
    "wof:lang":[
        "spa"
    ],
    "wof:name":"La Riviera",
    "wof:placetype":"neighbourhood"
},
  "geometry": {"coordinates":[-66.08445399999999,18.394826],"type":"Point"}
}