{
  "type": "Feature",
  "properties": {
    "gn:admin1_code":"021",
    "gn:admin2_code":"7268466",
    "gn:asciiname":"Campo Verde",
    "gn:country_code":"PR",
    "gn:dem":15,
    "gn:elevation":"28.0",
    "gn:feature_class":"P",
    "gn:feature_code":"PPL",
    "gn:name":"Campo Verde",
    "gn:population":0,
    "gn:timezone":"America/Puerto_Rico",
    "iso:country":"PR",
    "wof:name":"Campo Verde",
    "wof:placetype":"locality"
},
  "geometry": {"coordinates":[-66.15767,18.40939],"type":"Point"}
}