{
  "type": "Feature",
  "properties": {
    "gn:admin1_code":"023",
    "gn:admin2_code":"7268657",
    "gn:asciiname":"Elizabeth",
    "gn:country_code":"PR",
    "gn:dem":31,
    "gn:elevation":"26.0",
    "gn:feature_class":"P",
    "gn:feature_code":"PPL",
    "gn:name":"Elizabeth",
    "gn:population":0,
    "gn:timezone":"America/Puerto_Rico",
    "iso:country":"PR",
    "name:bul_x_preferred":[
        "\u0415\u043b\u0438\u0437\u0430\u0431\u0435\u0442"
    ],
    "name:cat_x_preferred":[
        "Elizabeth"
    ],
    "name:ceb_x_preferred":[
        "Elizabeth"
    ],
    "name:ces_x_preferred":[
        "Al\u017eb\u011bta"
    ],
    "name:deu_x_preferred":[
        "Elizabeth"
    ],
    "name:epo_x_preferred":[
        "Elizabeto"
    ],
    "name:fas_x_preferred":[
        "\u0627\u0644\u06cc\u0632\u0627\u0628\u062a"
    ],
    "name:fra_x_preferred":[
        "\u00c9lisabeth"
    ],
    "name:fry_x_preferred":[
        "Elizabeth"
    ],
    "name:heb_x_preferred":[
        "\u05d0\u05dc\u05d9\u05d6\u05d1\u05ea"
    ],
    "name:hun_x_preferred":[
        "Elizabeth"
    ],
    "name:ita_x_preferred":[
        "Elizabeth"
    ],
    "name:jpn_x_preferred":[
        "\u30a8\u30ea\u30b6\u30d9\u30b9"
    ],
    "name:kor_x_preferred":[
        "\uc5d8\ub9ac\uc790\ubca0\uc2a4"
    ],
    "name:lim_x_preferred":[
        "Elisabeth"
    ],
    "name:mlg_x_preferred":[
        "Elizabeth"
    ],
    "name:nld_x_preferred":[
        "Elizabeth"
    ],
    "name:pol_x_preferred":[
        "Elizabeth"
    ],
    "name:por_x_preferred":[
        "Elizabeth"
    ],
    "name:rus_x_preferred":[
        "\u042d\u043b\u0438\u0437\u0430\u0431\u0435\u0442"
    ],
    "name:san_x_preferred":[
        "\u090f\u0932\u093f\u091c\u093e\u092c\u0947\u0925"
    ],
    "name:slk_x_preferred":[
        "Al\u017ebeta"
    ],
    "name:spa_x_preferred":[
        "Elizabeth"
    ],
    "name:srp_x_preferred":[
        "\u0415\u043b\u0438\u0437\u0430\u0431\u0435\u0442"
    ],
    "name:swa_x_preferred":[
        "Elizabeti"
    ],
    "name:swe_x_preferred":[
        "Elizabeth"
    ],
    "name:ukr_x_preferred":[
        "\u0415\u043b\u0456\u0437\u0430\u0431\u0435\u0442"
    ],
    "name:urd_x_preferred":[
        "\u0627\u06cc\u0644\u0632\u0628\u062a\u06be"
    ],
    "name:vie_x_preferred":[
        "Elizabeth"
    ],
    "name:vol_x_preferred":[
        "Elizabeth"
    ],
    "wof:name":"Elizabeth",
    "wof:placetype":"locality"
},
  "geometry": {"coordinates":[-67.18351,18.07885],"type":"Point"}
}