{
  "type": "Feature",
  "properties": {
    "gn:admin1_code":"023",
    "gn:admin2_code":"7268657",
    "gn:asciiname":"Elizabeth",
    "gn:country_code":"PR",
    "gn:dem":31,
    "gn:elevation":"26.0",
    "gn:feature_class":"P",
    "gn:feature_code":"PPL",
    "gn:name":"Elizabeth",
    "gn:population":0,
    "gn:timezone":"America/Puerto_Rico",
    "iso:country":"PR",
    "wof:name":"Elizabeth",
    "wof:placetype":"locality"
},
  "geometry": {"coordinates":[-67.18351,18.07885],"type":"Point"}
}