{
  "type": "Feature",
  "properties": {
    "gn:admin1_code":"037",
    "gn:admin2_code":"7268862",
    "gn:asciiname":"Aguas Claras Comunidad",
    "gn:country_code":"PR",
    "gn:dem":127,
    "gn:elevation":"104.0",
    "gn:feature_class":"P",
    "gn:feature_code":"PPL",
    "gn:name":"Aguas Claras Comunidad",
    "gn:population":0,
    "gn:timezone":"America/Puerto_Rico",
    "iso:country":"PR",
    "wof:name":"Aguas Claras Comunidad",
    "wof:placetype":"locality"
},
  "geometry": {"coordinates":[-65.6662,18.24468],"type":"Point"}
}