{
  "type": "Feature",
  "properties": {
    "gn:admin1_code":"021",
    "gn:admin2_code":"7268270",
    "gn:asciiname":"Bella Vista Height",
    "gn:country_code":"PR",
    "gn:dem":117,
    "gn:elevation":"111.0",
    "gn:feature_class":"P",
    "gn:feature_code":"PPL",
    "gn:name":"Bella Vista Height",
    "gn:population":0,
    "gn:timezone":"America/Puerto_Rico",
    "iso:country":"PR",
    "wof:name":"Bella Vista Height",
    "wof:placetype":"locality"
},
  "geometry": {"coordinates":[-66.18878000000001,18.34912000000001],"type":"Point"}
}