{
  "type": "Feature",
  "properties": {
    "gn:admin1_code":"127",
    "gn:admin2_code":"7268708",
    "gn:asciiname":"Ramos Antonini",
    "gn:country_code":"PR",
    "gn:dem":11,
    "gn:elevation":"9.0",
    "gn:feature_class":"P",
    "gn:feature_code":"PPL",
    "gn:name":"Ramos Antonini",
    "gn:population":0,
    "gn:timezone":"America/Puerto_Rico",
    "iso:country":"PR",
    "wof:name":"Ramos Antonini",
    "wof:placetype":"locality"
},
  "geometry": {"coordinates":[-66.02710999999999,18.41023],"type":"Point"}
}