{
  "type": "Feature",
  "properties": {
    "gn:admin1_code":"059",
    "gn:admin2_code":"7268440",
    "gn:asciiname":"San Agusto",
    "gn:country_code":"PR",
    "gn:dem":27,
    "gn:elevation":"20.0",
    "gn:feature_class":"P",
    "gn:feature_code":"PPL",
    "gn:name":"San Agusto",
    "gn:population":0,
    "gn:timezone":"America/Puerto_Rico",
    "iso:country":"PR",
    "wof:name":"San Agusto",
    "wof:placetype":"locality"
},
  "geometry": {"coordinates":[-66.79434000000001,18.0308],"type":"Point"}
}