{
  "type": "Feature",
  "properties": {
    "gn:gn_country":"PR",
    "gn:gn_fcode":"PPL",
    "gn:gn_pop":0,
    "iso:country":"PR",
    "name:cat_x_preferred":[
        "Ensenada"
    ],
    "name:ceb_x_preferred":[
        "Ensenada"
    ],
    "name:deu_x_preferred":[
        "Ensenada"
    ],
    "name:fra_x_preferred":[
        "Ensenada"
    ],
    "name:ita_x_preferred":[
        "Ensenada"
    ],
    "name:nds_x_preferred":[
        "Ensenada"
    ],
    "name:nld_x_preferred":[
        "Ensenada"
    ],
    "name:pol_x_preferred":[
        "Ensenada"
    ],
    "name:rus_x_preferred":[
        "\u042d\u043d\u0441\u0435\u043d\u0430\u0434\u0430"
    ],
    "name:sco_x_preferred":[
        "Ensenada"
    ],
    "name:spa_x_preferred":[
        "Ensenada"
    ],
    "name:srp_x_preferred":[
        "\u0415\u043d\u0441\u0435\u043d\u0430\u0434\u0430"
    ],
    "name:swe_x_preferred":[
        "Ensenada"
    ],
    "name:tur_x_preferred":[
        "Ensenada"
    ],
    "name:ukr_x_preferred":[
        "\u0415\u043d\u0441\u0435\u043d\u0430\u0434\u0430"
    ],
    "qs_pg:aaroncc":"PR",
    "qs_pg:gn_country":"PR",
    "qs_pg:gn_fcode":"PPL",
    "qs_pg:gn_pop":0,
    "qs_pg:name":"Ensenada",
    "qs_pg:name_adm0":"Puerto Rico",
    "qs_pg:name_adm1":"Gu\u00e1nica",
    "qs_pg:photos":295,
    "qs_pg:photos_1k":60,
    "qs_pg:photos_9k":1,
    "qs_pg:photos_9r":4,
    "qs_pg:photos_all":295,
    "qs_pg:photos_sr":5,
    "qs_pg:pop_sr":5,
    "qs_pg:qs_pg_placetype":"locality",
    "qs_pg:qs_pg_placetype_gp":"Town",
    "qs_pg:woe_adm0":23424935,
    "woe:adm0_id":23424935,
    "woe:name_adm0":"Puerto Rico",
    "woe:name_adm1":"Gu\u00e1nica",
    "woe:placetype":"Town",
    "wof:name":"Ensenada",
    "wof:placetype":"locality"
},
  "geometry": {"coordinates":[-66.93351,17.96886],"type":"Point"}
}