{
  "type": "Feature",
  "properties": {
    "gn:admin1_code":"133",
    "gn:admin2_code":"7268520",
    "gn:asciiname":"Hacienda Esmeralda",
    "gn:country_code":"PR",
    "gn:dem":67,
    "gn:elevation":"68.0",
    "gn:feature_class":"P",
    "gn:feature_code":"PPL",
    "gn:name":"Hacienda Esmeralda",
    "gn:population":0,
    "gn:timezone":"America/Puerto_Rico",
    "iso:country":"PR",
    "wof:name":"Hacienda Esmeralda",
    "wof:placetype":"locality"
},
  "geometry": {"coordinates":[-66.37321999999999,18.01719],"type":"Point"}
}