{
  "type": "Feature",
  "properties": {
    "gn:admin1_code":"031",
    "gn:admin2_code":"7268934",
    "gn:asciiname":"Valle Arriba Heights",
    "gn:country_code":"PR",
    "gn:dem":7,
    "gn:elevation":"3.0",
    "gn:feature_class":"P",
    "gn:feature_code":"PPL",
    "gn:name":"Valle Arriba Heights",
    "gn:population":0,
    "gn:timezone":"America/Puerto_Rico",
    "iso:country":"PR",
    "wof:name":"Valle Arriba Heights",
    "wof:placetype":"locality"
},
  "geometry": {"coordinates":[-65.97378,18.40911],"type":"Point"}
}