{
  "type": "Feature",
  "properties": {
    "gn:admin1_code":"123",
    "gn:admin2_code":"7268174",
    "gn:asciiname":"Las Mercedes",
    "gn:country_code":"PR",
    "gn:dem":10,
    "gn:elevation":"10.0",
    "gn:feature_class":"P",
    "gn:feature_code":"PPL",
    "gn:name":"Las Mercedes",
    "gn:population":0,
    "gn:timezone":"America/Puerto_Rico",
    "iso:country":"PR",
    "name:ceb_x_preferred":[
        "Las Mercedes"
    ],
    "name:deu_x_preferred":[
        "Las Mercedes"
    ],
    "name:spa_x_preferred":[
        "Las Mercedes"
    ],
    "name:swe_x_preferred":[
        "Las Mercedes"
    ],
    "wof:name":"Las Mercedes",
    "wof:placetype":"locality"
},
  "geometry": {"coordinates":[-66.29071999999999,17.98108],"type":"Point"}
}