{
  "type": "Feature",
  "properties": {
    "gn:admin1_code":"071",
    "gn:admin2_code":"7268564",
    "gn:asciiname":"Pueblito de Ponce",
    "gn:country_code":"PR",
    "gn:dem":190,
    "gn:elevation":"187.0",
    "gn:feature_class":"P",
    "gn:feature_code":"PPL",
    "gn:name":"Pueblito de Ponce",
    "gn:population":0,
    "gn:timezone":"America/Puerto_Rico",
    "iso:country":"PR",
    "name:und_x_variant":[
        "Villa de Ponce"
    ],
    "wof:name":"Pueblito de Ponce",
    "wof:placetype":"locality"
},
  "geometry": {"coordinates":[-66.9674,18.43383],"type":"Point"}
}