{
  "type": "Feature",
  "properties": {
    "gn:gn_country":"PR",
    "gn:gn_fcode":"PPL",
    "gn:gn_pop":1823,
    "gn:population":1823,
    "iso:country":"PR",
    "name:bpy_x_preferred":[
        "\u09b2\u09be\u09b8 \u09ae\u09be\u09b0\u09bf\u09af\u09bc\u09be\u09b8"
    ],
    "name:cat_x_preferred":[
        "Las Mar\u00edas"
    ],
    "name:ceb_x_preferred":[
        "Las Mar\u00edas"
    ],
    "name:eng_x_preferred":[
        "Las Mar\u00edas"
    ],
    "name:fra_x_preferred":[
        "Las Mar\u00edas"
    ],
    "name:ita_x_preferred":[
        "Las Mar\u00edas"
    ],
    "name:jpn_x_preferred":[
        "\u30e9\u30b9\u30de\u30ea\u30a2\u30b9"
    ],
    "name:nld_x_preferred":[
        "Las Mar\u00edas"
    ],
    "name:por_x_preferred":[
        "Las Mar\u00edas"
    ],
    "name:spa_x_preferred":[
        "Las Mar\u00edas"
    ],
    "name:srp_x_preferred":[
        "Las Mar\u00edas"
    ],
    "name:ukr_x_preferred":[
        "\u041b\u0430\u0441-\u041c\u0430\u0440\u0456\u0430\u0441"
    ],
    "name:unk_x_variant":[
        "Comunidad Marias"
    ],
    "name:urd_x_preferred":[
        "\u0644\u0627\u0633 \u0645\u0627\u0631\u06cc\u0627\u0633\u060c \u067e\u0648\u06cc\u0631\u0679\u0648 \u0631\u06cc\u06a9\u0648"
    ],
    "name:urd_x_variant":[
        "\u0644\u0627\u0633 \u0645\u0627\u0631\u06cc\u0627\u0633"
    ],
    "name:war_x_preferred":[
        "Las Mar\u00edas"
    ],
    "name:zho_x_preferred":[
        "\u62c9\u65af\u746a\u9e97\u4e9e\u65af"
    ],
    "qs_pg:aaroncc":"PR",
    "qs_pg:gn_country":"PR",
    "qs_pg:gn_fcode":"PPL",
    "qs_pg:gn_pop":1823,
    "qs_pg:name":"Las Marias",
    "qs_pg:name_adm0":"Puerto Rico",
    "qs_pg:name_adm1":"Las Mar\u00edas",
    "qs_pg:photos_9k":1,
    "qs_pg:photos_9r":1,
    "qs_pg:photos_all":2,
    "qs_pg:photos_sr":0,
    "qs_pg:pop_sr":3,
    "qs_pg:qs_pg_placetype":"locality",
    "qs_pg:qs_pg_placetype_gp":"Town",
    "qs_pg:woe_adm0":23424935,
    "woe:adm0_id":23424935,
    "woe:name_adm0":"Puerto Rico",
    "woe:name_adm1":"Las Mar\u00edas",
    "woe:placetype":"Town",
    "wof:name":"Las Marias",
    "wof:placetype":"locality",
    "wof:population":1823
},
  "geometry": {"coordinates":[-67.14628999999999,18.29328],"type":"Point"}
}