{
  "type": "Feature",
  "properties": {
    "gn:admin1_code":"069",
    "gn:admin2_code":"7268837",
    "gn:asciiname":"Punta Santiago Comunidad",
    "gn:country_code":"PR",
    "gn:dem":2,
    "gn:elevation":"1.0",
    "gn:feature_class":"P",
    "gn:feature_code":"PPL",
    "gn:name":"Punta Santiago Comunidad",
    "gn:population":0,
    "gn:timezone":"America/Puerto_Rico",
    "iso:country":"PR",
    "wof:name":"Punta Santiago Comunidad",
    "wof:placetype":"locality"
},
  "geometry": {"coordinates":[-65.75865999999999,18.1618],"type":"Point"}
}