{
  "type": "Feature",
  "properties": {
    "gn:admin1_code":"119",
    "gn:admin2_code":"7268609",
    "gn:asciiname":"Mameyes",
    "gn:country_code":"PR",
    "gn:dem":13,
    "gn:elevation":"11.0",
    "gn:feature_class":"P",
    "gn:feature_code":"PPL",
    "gn:name":"Mameyes",
    "gn:population":0,
    "gn:timezone":"America/Puerto_Rico",
    "iso:country":"PR",
    "name:und_x_variant":[
        "Palmer",
        "Mamayes"
    ],
    "wof:name":"Mameyes",
    "wof:placetype":"locality"
},
  "geometry": {"coordinates":[-65.77016,18.37023],"type":"Point"}
}