{
  "type": "Feature",
  "properties": {
    "gn:admin1_code":"007",
    "gn:admin2_code":"7268221",
    "gn:asciiname":"Residencial Espiritu Santo",
    "gn:country_code":"PR",
    "gn:dem":243,
    "gn:elevation":"243.0",
    "gn:feature_class":"P",
    "gn:feature_code":"PPL",
    "gn:name":"Residencial Espiritu Santo",
    "gn:population":0,
    "gn:timezone":"America/Puerto_Rico",
    "iso:country":"PR",
    "wof:name":"Residencial Espiritu Santo",
    "wof:placetype":"locality"
},
  "geometry": {"coordinates":[-66.1035,18.26023],"type":"Point"}
}