{
  "type": "Feature",
  "properties": {
    "gn:admin1_code":"119",
    "gn:admin2_code":"7268524",
    "gn:asciiname":"Las Tres T",
    "gn:country_code":"PR",
    "gn:dem":53,
    "gn:elevation":"52.0",
    "gn:feature_class":"P",
    "gn:feature_code":"PPL",
    "gn:name":"Las Tres T",
    "gn:population":0,
    "gn:timezone":"America/Puerto_Rico",
    "iso:country":"PR",
    "wof:name":"Las Tres T",
    "wof:placetype":"locality"
},
  "geometry": {"coordinates":[-65.80544,18.35995],"type":"Point"}
}