{
  "type": "Feature",
  "properties": {
    "gn:admin1_code":"127",
    "gn:admin2_code":"7268944",
    "gn:asciiname":"Iturregui",
    "gn:country_code":"PR",
    "gn:dem":14,
    "gn:elevation":"12.0",
    "gn:feature_class":"P",
    "gn:feature_code":"PPL",
    "gn:name":"Iturregui",
    "gn:population":0,
    "gn:timezone":"America/Puerto_Rico",
    "iso:country":"PR",
    "wof:name":"Iturregui",
    "wof:placetype":"locality"
},
  "geometry": {"coordinates":[-66.00294,18.40189],"type":"Point"}
}